Workbook

Sheet 13.08
A1: SIM | B1: Status | C1: SKU (Sapo) | D1: SKU (mới) | E1: SKU (full) | F1: Total Inventory | H1: Quantity due to expiration | I1: Expiration | J1: Expired date left | K1: Date of Import | L1: Inventory Age | M1: Last 15 days | N1: Last 30 days | O1: Safety Stock (15D) | P1: Reorder Point (30D) | Q1: Vendor | R1: Kho tổng | T1: Phổ Quang - HCM | V1: Đống Đa - Hà Nội | X1: Tân Sơn Nhất - HCM | Z1: Chi nhánh Ký gửi | AB1: Avg Pcs/day | AC1: DOI (Số ngày tồn kho) | AD1: Estimated date out of stock | AE1: Evaluate | AF1: Retail Price | AG1: Total retail price | AH1: Near Expiration Inventory | AI1: OPS | AJ1: Telco | AK1: OD | AL1: WS | AM1: B2C | AN1: Marketing
A2: No. | F2: Stock | G2: Available for sale | M2: Sold | N2: Sold | R2: Stock | S2: Available for sale | T2: Stock | U2: Available for sale | V2: Stock | W2: Available for sale | X2: Stock | Y2: Available for sale | Z2: Stock | AA2: Available for sale
A3: 1 | B3: Temporary | C3: 3HKDATAPOOLSIM | D3: 3HKDATAPOOLSIM | E3: 1D0003DK00000 | F3: 419 | G3: 419 | I3: =VLOOKUP(C3,'Data Products'!$A:$B,2,0) | J3: =IFERROR(I3-TODAY(),"") | K3: 45723 | L3: =TODAY()-K3 | M3: 354 | N3: 380 | R3: 0 | S3: 0 | T3: 326 | U3: 326 | V3: 146 | W3: 146 | X3: 0 | Y3: 0 | Z3: 0 | AA3: 0 | AB3: =N3/30 | AC3: =IFERROR(F3/AB3,"-") | AD3: =IFERROR(TODAY()+AC3,"-") | AE3: =_xlfn.IFS(AC3="-","Not sold yet",AND(AC3<=150,AC3>60),"Out of stock more than 60 days",AC3<=60,"Out of stock less than 60 days",AC3>=150,"Out of stock more than 150 days") | AF3: =VLOOKUP(C3,'Data Products'!$A:$J,10,0) | AG3: =AF3*F3 | AH3: =IF(J3<=90,F3,0) | AI3: =IFERROR(VLOOKUP(C3,$C$3:$AI$42,34,0),"")
A4: 1 | B4: Active | C4: 1D0003DK00000 | D4: 1D0003DK00000 | E4: 1D0003DK00000 | F4: 16943 | G4: 16943 | I4: =VLOOKUP(C4,'Data Products'!$A:$B,2,0) | J4: =IFERROR(I4-TODAY(),"") | K4: 45617 | L4: =TODAY()-K4 | M4: 9349 | N4: 17734 | R4: 0 | S4: 0 | T4: 1378 | U4: 1369 | V4: 115 | W4: 112 | X4: 46 | Y4: 22 | Z4: 0 | AA4: 0 | AB4: =N4/30 | AC4: =IFERROR(F4/AB4,"-") | AD4: =IFERROR(TODAY()+AC4,"-") | AE4: =_xlfn.IFS(AC4="-","Not sold yet",AND(AC4<=150,AC4>60),"Out of stock more than 60 days",AC4<=60,"Out of stock less than 60 days",AC4>=150,"Out of stock more than 150 days") | AF4: =VLOOKUP(C4,'Data Products'!$A:$J,10,0) | AG4: =AF4*F4 | AH4: =IF(J4<=90,F4,0) | AI4: cần có hàng mới 20 - 25/08 để an toàn
A5: 2 | B5: Active | C5: 1D000BCK00000 | D5: 1D000BCK00000 | E5: 1D000BCK00000 | F5: 285 | G5: 285 | I5: =VLOOKUP(C5,'Data Products'!$A:$B,2,0) | J5: =IFERROR(I5-TODAY(),"") | K5: 45191 | L5: =TODAY()-K5 | M5: 17 | N5: 36 | R5: 0 | S5: 0 | T5: 26 | U5: 26 | V5: 416 | W5: 416 | X5: 0 | Y5: 0 | Z5: 0 | AA5: 0 | AB5: =N5/30 | AC5: =IFERROR(F5/AB5,"-") | AD5: =IFERROR(TODAY()+AC5,"-") | AE5: =_xlfn.IFS(AC5="-","Not sold yet",AND(AC5<=150,AC5>60),"Out of stock more than 60 days",AC5<=60,"Out of stock less than 60 days",AC5>=150,"Out of stock more than 150 days") | AF5: =VLOOKUP(C5,'Data Products'!$A:$J,10,0) | AG5: =AF5*F5 | AH5: =IF(J5<=90,F5,0) | AI5: sắp hết hạn, gia hạn thêm 1 tháng
A6: 3 | B6: Active | C6: 1D000ELK00000 | D6: 1D000ELK00000 | E6: 1D000ELK00000 | F6: 4268 | G6: 4268 | I6: =VLOOKUP(C6,'Data Products'!$A:$B,2,0) | J6: =IFERROR(I6-TODAY(),"") | K6: 45752 | L6: =TODAY()-K6 | M6: 28 | N6: 48 | R6: 0 | S6: 0 | T6: 1 | U6: 1 | V6: 1 | W6: 1 | X6: 0 | Y6: 0 | Z6: 0 | AA6: 0 | AB6: =N6/30 | AC6: =IFERROR(F6/AB6,"-") | AD6: =IFERROR(TODAY()+AC6,"-") | AE6: =_xlfn.IFS(AC6="-","Not sold yet",AND(AC6<=150,AC6>60),"Out of stock more than 60 days",AC6<=60,"Out of stock less than 60 days",AC6>=150,"Out of stock more than 150 days") | AF6: =VLOOKUP(C6,'Data Products'!$A:$J,10,0) | AG6: =AF6*F6 | AH6: =IF(J6<=90,F6,0) | AI6: =IFERROR(VLOOKUP(C6,$C$3:$AI$42,34,0),"")
A7: 4 | B7: Active | C7: 1D000JYK00000 | D7: 1D000JYK00000 | E7: 1D000JYK00000 | F7: 879 | G7: 859 | I7: =VLOOKUP(C7,'Data Products'!$A:$B,2,0) | J7: =IFERROR(I7-TODAY(),"") | K7: 45854 | L7: =TODAY()-K7 | M7: 3 | N7: 8 | R7: 0 | S7: 0 | T7: 288 | U7: 288 | V7: 512 | W7: 512 | X7: 20 | Y7: 20 | Z7: 0 | AA7: 0 | AB7: =N7/30 | AC7: =IFERROR(F7/AB7,"-") | AD7: =IFERROR(TODAY()+AC7,"-") | AE7: =_xlfn.IFS(AC7="-","Not sold yet",AND(AC7<=150,AC7>60),"Out of stock more than 60 days",AC7<=60,"Out of stock less than 60 days",AC7>=150,"Out of stock more than 150 days") | AF7: =VLOOKUP(C7,'Data Products'!$A:$J,10,0) | AG7: =AF7*F7 | AH7: =IF(J7<=90,F7,0) | AI7: =IFERROR(VLOOKUP(C7,$C$3:$AI$42,34,0),"")
A8: 5 | B8: Active | C8: 1D000SSK00000 | D8: 1D000SSK00000 | E8: 1D000SSK00000 | F8: 2476 | G8: 2476 | I8: =VLOOKUP(C8,'Data Products'!$A:$B,2,0) | J8: =IFERROR(I8-TODAY(),"") | K8: 45855 | L8: =TODAY()-K8 | M8: 9 | N8: 63 | R8: 0 | S8: 0 | T8: 51 | U8: 51 | V8: 101 | W8: 101 | X8: 0 | Y8: 0 | Z8: 0 | AA8: 0 | AB8: =N8/30 | AC8: =IFERROR(F8/AB8,"-") | AD8: =IFERROR(TODAY()+AC8,"-") | AE8: =_xlfn.IFS(AC8="-","Not sold yet",AND(AC8<=150,AC8>60),"Out of stock more than 60 days",AC8<=60,"Out of stock less than 60 days",AC8>=150,"Out of stock more than 150 days") | AF8: =VLOOKUP(C8,'Data Products'!$A:$J,10,0) | AG8: =AF8*F8 | AH8: =IF(J8<=90,F8,0) | AI8: =IFERROR(VLOOKUP(C8,$C$3:$AI$42,34,0)," ")
A9: 6 | B9: Active | C9: 1D000UBK00000 | D9: 1D000UBK00000 | E9: 1D000UBK00000 | F9: 2062 | G9: 2062 | I9: =VLOOKUP(C9,'Data Products'!$A:$B,2,0) | J9: =IFERROR(I9-TODAY(),"") | K9: 45856 | L9: =TODAY()-K9 | M9: 0 | N9: 0 | R9: 0 | S9: 0 | T9: 1480 | U9: 1478 | V9: 1112 | W9: 1112 | X9: 0 | Y9: 0 | Z9: 0 | AA9: 0 | AB9: =N9/30 | AC9: =IFERROR(F9/AB9,"-") | AD9: =IFERROR(TODAY()+AC9,"-") | AE9: =_xlfn.IFS(AC9="-","Not sold yet",AND(AC9<=150,AC9>60),"Out of stock more than 60 days",AC9<=60,"Out of stock less than 60 days",AC9>=150,"Out of stock more than 150 days") | AF9: =VLOOKUP(C9,'Data Products'!$A:$J,10,0) | AG9: =AF9*F9 | AH9: =IF(J9<=90,F9,0) | AI9: =IFERROR(VLOOKUP(C9,$C$3:$AI$42,34,0),"")
A10: 7 | B10: Active | C10: 1D000WMK00000 | D10: 1D000WMK00000 | E10: 1D000WMK00000 | F10: 440 | G10: 440 | I10: =VLOOKUP(C10,'Data Products'!$A:$B,2,0) | J10: =IFERROR(I10-TODAY(),"") | K10: 45857 | L10: =TODAY()-K10 | M10: 132 | N10: 223 | R10: 0 | S10: 0 | T10: 0 | U10: 0 | V10: 2 | W10: 2 | X10: 0 | Y10: 0 | Z10: 0 | AA10: 0 | AB10: =N10/30 | AC10: =IFERROR(F10/AB10,"-") | AD10: =IFERROR(TODAY()+AC10,"-") | AE10: =_xlfn.IFS(AC10="-","Not sold yet",AND(AC10<=150,AC10>60),"Out of stock more than 60 days",AC10<=60,"Out of stock less than 60 days",AC10>=150,"Out of stock more than 150 days") | AF10: =VLOOKUP(C10,'Data Products'!$A:$J,10,0) | AG10: =AF10*F10 | AH10: =IF(J10<=90,F10,0) | AI10: =IFERROR(VLOOKUP(C10,$C$3:$AI$42,34,0),"")
A11: 8 | B11: Temporary | C11: CNMCU05GBFY05D | D11: CNMCU05GBFY05D | E11: CNMCU05GBFY05D | F11: 1200 | G11: 1200 | I11: =VLOOKUP(C11,'Data Products'!$A:$B,2,0) | J11: =IFERROR(I11-TODAY(),"") | K11: 45858 | L11: =TODAY()-K11 | M11: 0 | N11: 0 | R11: 0 | S11: 0 | T11: 1289 | U11: 1289 | V11: 773 | W11: 773 | X11: 0 | Y11: 0 | Z11: 0 | AA11: 0 | AB11: =N11/30 | AC11: =IFERROR(F11/AB11,"-") | AD11: =IFERROR(TODAY()+AC11,"-") | AE11: =_xlfn.IFS(AC11="-","Not sold yet",AND(AC11<=150,AC11>60),"Out of stock more than 60 days",AC11<=60,"Out of stock less than 60 days",AC11>=150,"Out of stock more than 150 days") | AF11: =VLOOKUP(C11,'Data Products'!$A:$J,10,0) | AG11: =AF11*F11 | AH11: =IF(J11<=90,F11,0) | AI11: =IFERROR(VLOOKUP(C11,$C$3:$AI$42,34,0),"")
A12: 9 | B12: Temporary | C12: CNMCU07GBFY08D | D12: CNMCU07GBFY08D | E12: CNMCU07GBFY08D | F12: 1000 | G12: 1000 | I12: =VLOOKUP(C12,'Data Products'!$A:$B,2,0) | J12: =IFERROR(I12-TODAY(),"") | K12: 45532 | L12: =TODAY()-K12 | M12: 0 | N12: 0 | R12: 0 | S12: 0 | T12: 417 | U12: 416 | V12: 785 | W12: 785 | X12: 0 | Y12: 0 | Z12: 0 | AA12: 0 | AB12: =N12/30 | AC12: =IFERROR(F12/AB12,"-") | AD12: =IFERROR(TODAY()+AC12,"-") | AE12: =_xlfn.IFS(AC12="-","Not sold yet",AND(AC12<=150,AC12>60),"Out of stock more than 60 days",AC12<=60,"Out of stock less than 60 days",AC12>=150,"Out of stock more than 150 days") | AF12: =VLOOKUP(C12,'Data Products'!$A:$J,10,0) | AG12: =AF12*F12 | AH12: =IF(J12<=90,F12,0) | AI12: qua tết push lại, mỗi tuần nhắc lại
A13: 10 | B13: Temporary | C13: KORCU10GBFY05D | D13: KORCU10GBFY05D | E13: KORCU10GBFY05D | F13: 500 | G13: 500 | I13: =VLOOKUP(C13,'Data Products'!$A:$B,2,0) | J13: =IFERROR(I13-TODAY(),"") | K13: 45504 | L13: =TODAY()-K13 | M13: 0 | N13: 0 | R13: 0 | S13: 0 | T13: 3870 | U13: 1017 | V13: 366 | W13: 366 | X13: 0 | Y13: 0 | Z13: 0 | AA13: 0 | AB13: =N13/30 | AC13: =IFERROR(F13/AB13,"-") | AD13: =IFERROR(TODAY()+AC13,"-") | AE13: =_xlfn.IFS(AC13="-","Not sold yet",AND(AC13<=150,AC13>60),"Out of stock more than 60 days",AC13<=60,"Out of stock less than 60 days",AC13>=150,"Out of stock more than 150 days") | AF13: =VLOOKUP(C13,'Data Products'!$A:$J,10,0) | AG13: =AF13*F13 | AH13: =IF(J13<=90,F13,0) | AI13: =IFERROR(VLOOKUP(C13,$C$3:$AI$42,34,0),"")
A14: 11 | B14: Active | C14: 1DCNMCTF00705 | D14: 1DCNMCTF00705 | E14: 1ECNMCTF00705 | F14: 181 | G14: 181 | I14: =VLOOKUP(C14,'Data Products'!$A:$B,2,0) | J14: =IFERROR(I14-TODAY(),"") | K14: 45504 | L14: =TODAY()-K14 | M14: 1 | N14: 1 | R14: 1200 | S14: 1200 | T14: 0 | U14: 0 | V14: 0 | W14: 0 | X14: 0 | Y14: 0 | Z14: 0 | AA14: 0 | AB14: =N14/30 | AC14: =IFERROR(F14/AB14,"-") | AD14: =IFERROR(TODAY()+AC14,"-") | AE14: =_xlfn.IFS(AC14="-","Not sold yet",AND(AC14<=150,AC14>60),"Out of stock more than 60 days",AC14<=60,"Out of stock less than 60 days",AC14>=150,"Out of stock more than 150 days") | AF14: =VLOOKUP(C14,'Data Products'!$A:$J,10,0) | AG14: =AF14*F14 | AH14: =IF(J14<=90,F14,0) | AI14: =IFERROR(VLOOKUP(C14,$C$3:$AI$42,34,0)," ")
A15: 12 | B15: Active | C15: 1DCNMCUF01530 | D15: 1DCNMCUF01530 | E15: 1ECNMCUF01530 | F15: 98 | G15: 98 | I15: =VLOOKUP(C15,'Data Products'!$A:$B,2,0) | J15: =IFERROR(I15-TODAY(),"") | K15: 45648 | L15: =TODAY()-K15 | M15: 4 | N15: 5 | R15: 1000 | S15: 1000 | T15: 0 | U15: 0 | V15: 0 | W15: 0 | X15: 0 | Y15: 0 | Z15: 0 | AA15: 0 | AB15: =N15/30 | AC15: =IFERROR(F15/AB15,"-") | AD15: =IFERROR(TODAY()+AC15,"-") | AE15: =_xlfn.IFS(AC15="-","Not sold yet",AND(AC15<=150,AC15>60),"Out of stock more than 60 days",AC15<=60,"Out of stock less than 60 days",AC15>=150,"Out of stock more than 150 days") | AF15: =VLOOKUP(C15,'Data Products'!$A:$J,10,0) | AG15: =AF15*F15 | AH15: =IF(J15<=90,F15,0) | AI15: =IFERROR(VLOOKUP(C15,$C$3:$AI$42,34,0),"")
A16: 13 | B16: Active | C16: 1DCNMCUF00303 | D16: 1DCNMCUF00303 | E16: 1ECNMCUF00303 | F16: 846 | G16: 846 | I16: =VLOOKUP(C16,'Data Products'!$A:$B,2,0) | J16: =IFERROR(I16-TODAY(),"") | K16: 45504 | L16: =TODAY()-K16 | M16: 101 | N16: 103 | R16: 500 | S16: 500 | T16: 0 | U16: 0 | V16: 0 | W16: 0 | X16: 0 | Y16: 0 | Z16: 0 | AA16: 0 | AB16: =N16/30 | AC16: =IFERROR(F16/AB16,"-") | AD16: =IFERROR(TODAY()+AC16,"-") | AE16: =_xlfn.IFS(AC16="-","Not sold yet",AND(AC16<=150,AC16>60),"Out of stock more than 60 days",AC16<=60,"Out of stock less than 60 days",AC16>=150,"Out of stock more than 150 days") | AF16: =VLOOKUP(C16,'Data Products'!$A:$J,10,0) | AG16: =AF16*F16 | AH16: =IF(J16<=90,F16,0) | AI16: =IFERROR(VLOOKUP(C16,$C$3:$AI$42,34,0),"")
A17: 14 | B17: Active | C17: 1DCNMCUF00505 | D17: 1DCNMCUF00505 | E17: 1ECNMCUF00505 | F17: 0 | G17: 0 | I17: =VLOOKUP(C17,'Data Products'!$A:$B,2,0) | J17: =IFERROR(I17-TODAY(),"") | K17: 45653 | L17: =TODAY()-K17 | M17: 0 | N17: 0 | R17: 0 | S17: 0 | T17: 128 | U17: 128 | V17: 54 | W17: 54 | X17: 0 | Y17: 0 | Z17: 0 | AA17: 0 | AB17: =N17/30 | AC17: =IFERROR(F17/AB17,"-") | AD17: =IFERROR(TODAY()+AC17,"-") | AE17: =_xlfn.IFS(AC17="-","Not sold yet",AND(AC17<=150,AC17>60),"Out of stock more than 60 days",AC17<=60,"Out of stock less than 60 days",AC17>=150,"Out of stock more than 150 days") | AF17: =VLOOKUP(C17,'Data Products'!$A:$J,10,0) | AG17: =AF17*F17 | AH17: =IF(J17<=90,F17,0) | AI17: =IFERROR(VLOOKUP(C17,$C$3:$AI$42,34,0),"")
A18: 15 | B18: Active | C18: 1DTHADTF05010 | D18: 1DTHADTF05010 | E18: 1ETHADTF05010 | F18: 5 | G18: 5 | I18: =VLOOKUP(C18,'Data Products'!$A:$B,2,0) | J18: =IFERROR(I18-TODAY(),"") | K18: 45737 | L18: =TODAY()-K18 | M18: 0 | N18: 0 | R18: 0 | S18: 0 | T18: 0 | U18: 0 | V18: 116 | W18: 116 | X18: 0 | Y18: 0 | Z18: 0 | AA18: 0 | AB18: =N18/30 | AC18: =IFERROR(F18/AB18,"-") | AD18: =IFERROR(TODAY()+AC18,"-") | AE18: =_xlfn.IFS(AC18="-","Not sold yet",AND(AC18<=150,AC18>60),"Out of stock more than 60 days",AC18<=60,"Out of stock less than 60 days",AC18>=150,"Out of stock more than 150 days") | AF18: =VLOOKUP(C18,'Data Products'!$A:$J,10,0) | AG18: =AF18*F18 | AH18: =IF(J18<=90,F18,0)
A19: 16 | B19: Active | C19: 1DWORCBF01030 | D19: 1DWORCBF01030 | E19: 1DWORCBF01030 | F19: 323 | G19: 323 | I19: =VLOOKUP(C19,'Data Products'!$A:$B,2,0) | J19: =IFERROR(I19-TODAY(),"") | K19: 45653 | L19: =TODAY()-K19 | M19: 0 | N19: 110 | R19: 600 | S19: 600 | T19: 100 | U19: 100 | V19: 300 | W19: 300 | X19: 0 | Y19: 0 | Z19: 0 | AA19: 0 | AB19: =N19/30 | AC19: =IFERROR(F19/AB19,"-") | AD19: =IFERROR(TODAY()+AC19,"-") | AE19: =_xlfn.IFS(AC19="-","Not sold yet",AND(AC19<=150,AC19>60),"Out of stock more than 60 days",AC19<=60,"Out of stock less than 60 days",AC19>=150,"Out of stock more than 150 days") | AF19: =VLOOKUP(C19,'Data Products'!$A:$J,10,0) | AG19: =AF19*F19 | AH19: =IF(J19<=90,F19,0)
A20: 17 | B20: Active | C20: 1DTHATMF01507 | D20: 1DTHATMF01507 | E20: 1ETHATMF01507 | F20: 3969 | G20: 3969 | I20: =VLOOKUP(C20,'Data Products'!$A:$B,2,0) | J20: =IFERROR(I20-TODAY(),"") | K20: 45653 | L20: =TODAY()-K20 | M20: 738 | N20: 3160 | R20: 0 | S20: 0 | T20: 27 | U20: 27 | V20: 25 | W20: 25 | X20: 0 | Y20: 0 | Z20: 0 | AA20: 0 | AB20: =N20/30 | AC20: =IFERROR(F20/AB20,"-") | AD20: =IFERROR(TODAY()+AC20,"-") | AE20: =_xlfn.IFS(AC20="-","Not sold yet",AND(AC20<=150,AC20>60),"Out of stock more than 60 days",AC20<=60,"Out of stock less than 60 days",AC20>=150,"Out of stock more than 150 days") | AF20: =VLOOKUP(C20,'Data Products'!$A:$J,10,0) | AG20: =AF20*F20 | AH20: =IF(J20<=90,F20,0) | AI20: cần đầu tháng 9 có hàng mới
A21: 18 | B21: Active | C21: 1DTHATMF05010 | D21: 1DTHATMF05010 | E21: 1ETHATMF05010 | F21: 6918 | G21: 6918 | I21: =VLOOKUP(C21,'Data Products'!$A:$B,2,0) | J21: =IFERROR(I21-TODAY(),"") | K21: 45847 | L21: =TODAY()-K21 | M21: 518 | N21: 1375 | R21: 0 | S21: 0 | T21: 113 | U21: 106 | V21: 1097 | W21: 1097 | X21: 5 | Y21: 0 | Z21: 0 | AA21: 0 | AB21: =N21/30 | AC21: =IFERROR(F21/AB21,"-") | AD21: =IFERROR(TODAY()+AC21,"-") | AE21: =_xlfn.IFS(AC21="-","Not sold yet",AND(AC21<=150,AC21>60),"Out of stock more than 60 days",AC21<=60,"Out of stock less than 60 days",AC21>=150,"Out of stock more than 150 days") | AF21: =VLOOKUP(C21,'Data Products'!$A:$J,10,0) | AG21: =AF21*F21 | AH21: =IF(J21<=90,F21,0) | AI21: cần đầu tháng 9 có hàng mới
A22: 19 | B22: Active | C22: 1DTHATMF01507 | D22: 1DTHATMF01507 | E22: 1ETHATMF01507 | F22: 3969 | G22: 3969 | I22: =VLOOKUP(C22,'Data Products'!$A:$B,2,0) | J22: =IFERROR(I22-TODAY(),"") | K22: 45847 | L22: =TODAY()-K22 | M22: 738 | N22: 3090 | R22: 0 | S22: 0 | T22: 154 | U22: 154 | V22: 310 | W22: 310 | X22: 0 | Y22: 0 | Z22: 0 | AA22: 0 | AB22: =N22/30 | AC22: =IFERROR(F22/AB22,"-") | AD22: =IFERROR(TODAY()+AC22,"-") | AE22: =_xlfn.IFS(AC22="-","Not sold yet",AND(AC22<=150,AC22>60),"Out of stock more than 60 days",AC22<=60,"Out of stock less than 60 days",AC22>=150,"Out of stock more than 150 days") | AF22: =VLOOKUP(C22,'Data Products'!$A:$J,10,0) | AG22: =AF22*F22 | AH22: =IF(J22<=90,F22,0) | AI22: pass quý 1 push lại
A23: 20 | B23: Temporary | C23: CNMCU15GBFY30D | D23: CNMCU15GBFY30D | E23: CNMCU15GBFY30D | F23: 1500 | G23: 1500 | I23: =VLOOKUP(C23,'Data Products'!$A:$B,2,0) | J23: =IFERROR(I23-TODAY(),"") | K23: 45416 | L23: =TODAY()-K23 | M23: 0 | N23: 0 | AB23: =N23/30 | AC23: =IFERROR(F23/AB23,"-") | AD23: =IFERROR(TODAY()+AC23,"-") | AE23: =_xlfn.IFS(AC23="-","Not sold yet",AND(AC23<=150,AC23>60),"Out of stock more than 60 days",AC23<=60,"Out of stock less than 60 days",AC23>=150,"Out of stock more than 150 days") | AF23: =VLOOKUP(C23,'Data Products'!$A:$J,10,0) | AG23: =AF23*F23
A24: 21 | B24: Temporary | C24: CNMCU10GBFY15D | D24: CNMCU10GBFY15D | E24: CNMCU10GBFY15D | F24: 2000 | G24: 2000 | I24: =VLOOKUP(C24,'Data Products'!$A:$B,2,0) | J24: =IFERROR(I24-TODAY(),"") | K24: 45417 | L24: =TODAY()-K24 | M24: 0 | N24: 0 | AB24: =N24/30 | AC24: =IFERROR(F24/AB24,"-") | AD24: =IFERROR(TODAY()+AC24,"-") | AE24: =_xlfn.IFS(AC24="-","Not sold yet",AND(AC24<=150,AC24>60),"Out of stock more than 60 days",AC24<=60,"Out of stock less than 60 days",AC24>=150,"Out of stock more than 150 days") | AF24: =VLOOKUP(C24,'Data Products'!$A:$J,10,0) | AG24: =AF24*F24
AE25: Total stock with retail price | AF25: =AG25/$AG$25 | AG25: =SUM(AG4:AG24) | AH25: =SUM(AH4:AH24) | AI25: =SUM(AI4:AI24)
AE26: Out of stock less than 60 days | AF26: =AG26/$AG$25 | AG26: =SUMIFS($AG$4:$AG$24,$AE$4:$AE$24,$AE$26)
AE27: Not sold yet | AF27: =AG27/$AG$25 | AG27: =SUMIFS($AG$4:$AG$24,$AE$4:$AE$24,AE27)
AE28: Out of stock more than 60 days | AF28: =AG28/$AG$25 | AG28: =SUMIFS($AG$4:$AG$24,$AE$4:$AE$24,AE28)
AE29: Out of stock more than 150 days | AF29: =AG29/$AG$25 | AG29: =SUMIFS($AG$4:$AG$24,$AE$4:$AE$24,AE29)
AE30: Near Expiration Inventory | AF30: =AVERAGE(AE29:AC27)/AVERAGE(AE29:AC27) | AG30: =SUMIF($AC$4:$AC$24,"<90",AG4:AG24)
A32: ESIM VN | B32: Status | C32: SKU | D32: SKU (mới) | F32: Total Inventory | H32: Quantity | I32: Expiration | J32: Expired date left | K32: Date of Import | L32: Inventory Age | M32: Last 15 days | N32: Last 30 days | O32: Safety Stock | P32: Reorder Point | Q32: Vendor | AB32: Avg Pcs/day | AC32: DOI (Số ngày tồn kho) | AD32: Ngày hết hàng dự kiến | AE32: Đánh giá | AF32: Retail Price | AG32: Total retail price | AH32: Near Expiration Inventory | AI32: OPS | AJ32: Telco | AK32: OD | AL32: B2B | AM32: B2C | AN32: Marketing
A33: No. | F33: Stock | G33: Available for sale | M33: Sold | N33: Sold
A34: 1 | B34: Inactive | C34: 3HKDATAPOOLESIM | F34: 0 | G34: 0 | I34: =VLOOKUP(C34,'Data Products'!$A:$J,2,0) | J34: =IFERROR(I34-TODAY(),"") | K34: 45840 | L34: =TODAY()-K34 | M34: 0 | N34: 0 | Q34: 3HK | AB34: =N34/30 | AC34: =IFERROR(F34/AB34,"-") | AD34: =IFERROR(TODAY()+AC34,"-") | AE34: =_xlfn.IFS(AC34="-","Not sold yet",AND(AC34<=150,AC34>60),"Out of stock more than 60 days",AC34<=60,"Out of stock less than 60 days",AC34>=150,"Out of stock more than 150 days") | AF34: =VLOOKUP(C34,'Data Products'!$A:$J,10,0) | AG34: =AF34*F34 | AI34: treo chờ xử lý sau
A35: 2 | B35: Inactive | C35: EEURBGFX15GB15D | F35: 0 | G35: 0 | I35: =VLOOKUP(C35,'Data Products'!$A:$J,2,0) | J35: =IFERROR(I35-TODAY(),"") | K35: 45841 | L35: =TODAY()-K35 | M35: 0 | N35: 0 | Q35: Bouygues | AB35: =N35/30 | AC35: =IFERROR(F35/AB35,"-") | AD35: =IFERROR(TODAY()+AC35,"-") | AE35: =_xlfn.IFS(AC35="-","Not sold yet",AND(AC35<=150,AC35>60),"Out of stock more than 60 days",AC35<=60,"Out of stock less than 60 days",AC35>=150,"Out of stock more than 150 days") | AF35: =VLOOKUP(C35,'Data Products'!$A:$J,10,0) | AG35: =AF35*F35 | AH35: =IF(J35<=90,F35,0)
A36: 3 | B36: Inactive | C36: EEURBGFX20GB15D | F36: 0 | G36: 0 | I36: =VLOOKUP(C36,'Data Products'!$A:$J,2,0) | J36: =IFERROR(I36-TODAY(),"") | K36: 45842 | L36: =TODAY()-K36 | M36: 0 | N36: 0 | Q36: Bouygues | AB36: =N36/30 | AC36: =IFERROR(F36/AB36,"-") | AD36: =IFERROR(TODAY()+AC36,"-") | AE36: =_xlfn.IFS(AC36="-","Not sold yet",AND(AC36<=150,AC36>60),"Out of stock more than 60 days",AC36<=60,"Out of stock less than 60 days",AC36>=150,"Out of stock more than 150 days") | AF36: =VLOOKUP(C36,'Data Products'!$A:$J,10,0) | AG36: =AF36*F36 | AH36: =IF(J36<=90,F36,0)
A37: 4 | B37: Inactive | C37: EEURBGFX30GB30D | F37: 0 | G37: 0 | I37: =VLOOKUP(C37,'Data Products'!$A:$J,2,0) | J37: =IFERROR(I37-TODAY(),"") | K37: 45843 | L37: =TODAY()-K37 | M37: 0 | N37: 0 | Q37: Bouygues | AB37: =N37/30 | AC37: =IFERROR(F37/AB37,"-") | AD37: =IFERROR(TODAY()+AC37,"-") | AE37: =_xlfn.IFS(AC37="-","Not sold yet",AND(AC37<=150,AC37>60),"Out of stock more than 60 days",AC37<=60,"Out of stock less than 60 days",AC37>=150,"Out of stock more than 150 days") | AF37: =VLOOKUP(C37,'Data Products'!$A:$J,10,0) | AG37: =AF37*F37 | AH37: =IF(J37<=90,F37,0)
A38: 5 | B38: Deleted | C38: ECMTCUFY05GB05D | F38: 0 | G38: 0 | I38: =VLOOKUP(C38,'Data Products'!$A:$J,2,0) | J38: =IFERROR(I38-TODAY(),"") | K38: 45844 | L38: =TODAY()-K38 | M38: 0 | N38: 0 | Q38: CU | AB38: =N38/30 | AC38: =IFERROR(F38/AB38,"-") | AD38: =IFERROR(TODAY()+AC38,"-") | AE38: =_xlfn.IFS(AC38="-","Not sold yet",AND(AC38<=150,AC38>60),"Out of stock more than 60 days",AC38<=60,"Out of stock less than 60 days",AC38>=150,"Out of stock more than 150 days") | AF38: =VLOOKUP(C38,'Data Products'!$A:$J,10,0) | AG38: =AF38*F38 | AH38: =IF(J38<=90,F38,0) | AK38: 200
A39: 6 | B39: Temporary | C39: ECNMCUFX15GB30D | D39: 1CCNMCUY01530 | F39: 0 | G39: 0 | I39: =VLOOKUP(C39,'Data Products'!$A:$J,2,0) | J39: =IFERROR(I39-TODAY(),"") | K39: 45845 | L39: =TODAY()-K39 | M39: 0 | N39: 0 | Q39: CU | AB39: =N39/30 | AC39: =IFERROR(F39/AB39,"-") | AD39: =IFERROR(TODAY()+AC39,"-") | AE39: =_xlfn.IFS(AC39="-","Not sold yet",AND(AC39<=150,AC39>60),"Out of stock more than 60 days",AC39<=60,"Out of stock less than 60 days",AC39>=150,"Out of stock more than 150 days") | AF39: =VLOOKUP(C39,'Data Products'!$A:$J,10,0) | AG39: =AF39*F39 | AH39: =IF(J39<=90,F39,0)
A40: 7 | B40: Temporary | C40: 1CKORCUF01005 | D40: 1CKORCUF01005 | F40: 0 | G40: 0 | I40: =VLOOKUP(C40,'Data Products'!$A:$J,2,0) | J40: =IFERROR(I40-TODAY(),"") | K40: 45846 | L40: =TODAY()-K40 | M40: 0 | N40: 0 | Q40: CU | AB40: =N40/30 | AC40: =IFERROR(F40/AB40,"-") | AD40: =IFERROR(TODAY()+AC40,"-") | AE40: =_xlfn.IFS(AC40="-","Not sold yet",AND(AC40<=150,AC40>60),"Out of stock more than 60 days",AC40<=60,"Out of stock less than 60 days",AC40>=150,"Out of stock more than 150 days") | AF40: =VLOOKUP(C40,'Data Products'!$A:$J,10,0) | AG40: =AF40*F40 | AH40: =IF(J40<=90,F40,0)
A41: 8 | B41: Temporary | C41: EKORCUFY30GB30D | F41: 0 | G41: 0 | I41: =VLOOKUP(C41,'Data Products'!$A:$J,2,0) | J41: =IFERROR(I41-TODAY(),"") | K41: 45847 | L41: =TODAY()-K41 | M41: 0 | N41: 0 | Q41: CU | AB41: =N41/30 | AC41: =IFERROR(F41/AB41,"-") | AD41: =IFERROR(TODAY()+AC41,"-") | AE41: =_xlfn.IFS(AC41="-","Not sold yet",AND(AC41<=150,AC41>60),"Out of stock more than 60 days",AC41<=60,"Out of stock less than 60 days",AC41>=150,"Out of stock more than 150 days") | AF41: =VLOOKUP(C41,'Data Products'!$A:$J,10,0) | AG41: =AF41*F41 | AH41: =IF(J41<=90,F41,0)
A42: 9 | B42: Temporary | C42: EA10CUFY05GB08D | F42: 0 | G42: 0 | I42: =VLOOKUP(C42,'Data Products'!$A:$J,2,0) | J42: =IFERROR(I42-TODAY(),"") | K42: 45848 | L42: =TODAY()-K42 | M42: 0 | N42: 0 | Q42: CU | AB42: =N42/30 | AC42: =IFERROR(F42/AB42,"-") | AD42: =IFERROR(TODAY()+AC42,"-") | AE42: =_xlfn.IFS(AC42="-","Not sold yet",AND(AC42<=150,AC42>60),"Out of stock more than 60 days",AC42<=60,"Out of stock less than 60 days",AC42>=150,"Out of stock more than 150 days") | AF42: =VLOOKUP(C42,'Data Products'!$A:$J,10,0) | AG42: =AF42*F42 | AH42: =IF(J42<=90,F42,0)
A43: 10 | B43: Temporary | C43: ECMTCUFY07GB08D | F43: 0 | G43: 0 | I43: =VLOOKUP(C43,'Data Products'!$A:$J,2,0) | J43: =IFERROR(I43-TODAY(),"") | K43: 45849 | L43: =TODAY()-K43 | M43: 0 | N43: 0 | Q43: CU | AB43: =N43/30 | AC43: =IFERROR(F43/AB43,"-") | AD43: =IFERROR(TODAY()+AC43,"-") | AE43: =_xlfn.IFS(AC43="-","Not sold yet",AND(AC43<=150,AC43>60),"Out of stock more than 60 days",AC43<=60,"Out of stock less than 60 days",AC43>=150,"Out of stock more than 150 days") | AF43: =VLOOKUP(C43,'Data Products'!$A:$J,10,0) | AG43: =AF43*F43 | AH43: =IF(J43<=90,F43,0) | AK43: 150
A44: 11 | B44: Inactive | C44: ECNMCUFY05GB05D | F44: 0 | G44: 0 | I44: =VLOOKUP(C44,'Data Products'!$A:$J,2,0) | J44: =IFERROR(I44-TODAY(),"") | K44: 45850 | L44: =TODAY()-K44 | M44: 0 | N44: 0 | Q44: CU | AB44: =N44/30 | AC44: =IFERROR(F44/AB44,"-") | AD44: =IFERROR(TODAY()+AC44,"-") | AE44: =_xlfn.IFS(AC44="-","Not sold yet",AND(AC44<=150,AC44>60),"Out of stock more than 60 days",AC44<=60,"Out of stock less than 60 days",AC44>=150,"Out of stock more than 150 days") | AF44: =VLOOKUP(C44,'Data Products'!$A:$J,10,0) | AG44: =AF44*F44 | AH44: =IF(J44<=90,F44,0)
A45: 12 | B45: Temporary | C45: ECNMCUFY07GB08D | D45: 1CCNMCUF00708 | F45: 0 | G45: 0 | I45: =VLOOKUP(C45,'Data Products'!$A:$J,2,0) | J45: =IFERROR(I45-TODAY(),"") | K45: 45851 | L45: =TODAY()-K45 | M45: 0 | N45: 0 | Q45: CU | AB45: =N45/30 | AC45: =IFERROR(F45/AB45,"-") | AD45: =IFERROR(TODAY()+AC45,"-") | AE45: =_xlfn.IFS(AC45="-","Not sold yet",AND(AC45<=150,AC45>60),"Out of stock more than 60 days",AC45<=60,"Out of stock less than 60 days",AC45>=150,"Out of stock more than 150 days") | AF45: =VLOOKUP(C45,'Data Products'!$A:$J,10,0) | AG45: =AF45*F45 | AH45: =IF(J45<=90,F45,0)
A46: 13 | B46: Temporary | C46: EARECUFY04GB30D | F46: 0 | G46: 0 | I46: =VLOOKUP(C46,'Data Products'!$A:$J,2,0) | J46: =IFERROR(I46-TODAY(),"") | K46: 45852 | L46: =TODAY()-K46 | M46: 0 | N46: 0 | Q46: CU | AB46: =N46/30 | AC46: =IFERROR(F46/AB46,"-") | AD46: =IFERROR(TODAY()+AC46,"-") | AE46: =_xlfn.IFS(AC46="-","Not sold yet",AND(AC46<=150,AC46>60),"Out of stock more than 60 days",AC46<=60,"Out of stock less than 60 days",AC46>=150,"Out of stock more than 150 days") | AF46: =VLOOKUP(C46,'Data Products'!$A:$J,10,0) | AG46: =AF46*F46 | AH46: =IF(J46<=90,F46,0)
A47: 14 | B47: Inactive | C47: EKORCUFY20GB08D | D47: 1CKORCUF02008 | F47: 0 | G47: 0 | I47: =VLOOKUP(C47,'Data Products'!$A:$J,2,0) | J47: =IFERROR(I47-TODAY(),"") | K47: 45853 | L47: =TODAY()-K47 | M47: 0 | N47: 0 | Q47: CU | AB47: =N47/30 | AC47: =IFERROR(F47/AB47,"-") | AD47: =IFERROR(TODAY()+AC47,"-") | AE47: =_xlfn.IFS(AC47="-","Not sold yet",AND(AC47<=150,AC47>60),"Out of stock more than 60 days",AC47<=60,"Out of stock less than 60 days",AC47>=150,"Out of stock more than 150 days") | AF47: =VLOOKUP(C47,'Data Products'!$A:$J,10,0) | AG47: =AF47*F47 | AH47: =IF(J47<=90,F47,0)
A48: 15 | B48: Inactive | C48: ECNMCUFX10GB15D | F48: 0 | G48: 0 | I48: =VLOOKUP(C48,'Data Products'!$A:$J,2,0) | J48: =IFERROR(I48-TODAY(),"") | K48: 45854 | L48: =TODAY()-K48 | M48: 0 | N48: 0 | Q48: CU | AB48: =N48/30 | AC48: =IFERROR(F48/AB48,"-") | AD48: =IFERROR(TODAY()+AC48,"-") | AE48: =_xlfn.IFS(AC48="-","Not sold yet",AND(AC48<=150,AC48>60),"Out of stock more than 60 days",AC48<=60,"Out of stock less than 60 days",AC48>=150,"Out of stock more than 150 days") | AF48: =VLOOKUP(C48,'Data Products'!$A:$J,10,0) | AG48: =AF48*F48 | AH48: =IF(J48<=90,F48,0) | AK48: 340
A49: 16 | B49: Inactive | C49: ETHDD1FY50GB10D | F49: 0 | G49: 0 | I49: =VLOOKUP(C49,'Data Products'!$A:$J,2,0) | J49: =IFERROR(I49-TODAY(),"") | K49: 45855 | L49: =TODAY()-K49 | M49: 0 | N49: 0 | Q49: Dtac | AB49: =N49/30 | AC49: =IFERROR(F49/AB49,"-") | AD49: =IFERROR(TODAY()+AC49,"-") | AE49: =_xlfn.IFS(AC49="-","Not sold yet",AND(AC49<=150,AC49>60),"Out of stock more than 60 days",AC49<=60,"Out of stock less than 60 days",AC49>=150,"Out of stock more than 150 days") | AF49: =VLOOKUP(C49,'Data Products'!$A:$J,10,0) | AG49: =AF49*F49 | AH49: =IF(J49<=90,F49,0)
A50: 17 | B50: Inactive | C50: ETHDDTFY50GB10D | F50: 0 | G50: 0 | I50: =VLOOKUP(C50,'Data Products'!$A:$J,2,0) | J50: =IFERROR(I50-TODAY(),"") | K50: 45856 | L50: =TODAY()-K50 | M50: 0 | N50: 0 | Q50: Dtac | AB50: =N50/30 | AC50: =IFERROR(F50/AB50,"-") | AD50: =IFERROR(TODAY()+AC50,"-") | AE50: =_xlfn.IFS(AC50="-","Not sold yet",AND(AC50<=150,AC50>60),"Out of stock more than 60 days",AC50<=60,"Out of stock less than 60 days",AC50>=150,"Out of stock more than 150 days") | AF50: =VLOOKUP(C50,'Data Products'!$A:$J,10,0) | AG50: =AF50*F50 | AH50: =IF(J50<=90,F50,0) | AK50: 3620
A51: 18 | B51: Inactive | C51: ETHDDTFY15GB07D | F51: 0 | G51: 0 | I51: =VLOOKUP(C51,'Data Products'!$A:$J,2,0) | J51: =IFERROR(I51-TODAY(),"") | K51: 45857 | L51: =TODAY()-K51 | M51: 0 | N51: 0 | Q51: Dtac | AB51: =N51/30 | AC51: =IFERROR(F51/AB51,"-") | AD51: =IFERROR(TODAY()+AC51,"-") | AE51: =_xlfn.IFS(AC51="-","Not sold yet",AND(AC51<=150,AC51>60),"Out of stock more than 60 days",AC51<=60,"Out of stock less than 60 days",AC51>=150,"Out of stock more than 150 days") | AF51: =VLOOKUP(C51,'Data Products'!$A:$J,10,0) | AG51: =AF51*F51 | AH51: =IF(J51<=90,F51,0)
A52: 19 | B52: Active | C52: ETHATMFY50GB10D | D52: 1CTHATMF05010 | E52: 1CTHATMF05010 | F52: 0 | G52: 0 | I52: =VLOOKUP(C52,'Data Products'!$A:$J,2,0) | J52: =IFERROR(I52-TODAY(),"") | K52: 45858 | L52: =TODAY()-K52 | M52: 0 | N52: 0 | Q52: TrueMove | AB52: =N52/30 | AC52: =IFERROR(F52/AB52,"-") | AD52: =IFERROR(TODAY()+AC52,"-") | AE52: =_xlfn.IFS(AC52="-","Not sold yet",AND(AC52<=150,AC52>60),"Out of stock more than 60 days",AC52<=60,"Out of stock less than 60 days",AC52>=150,"Out of stock more than 150 days") | AF52: =VLOOKUP(C52,'Data Products'!$A:$J,10,0) | AG52: =AF52*F52 | AH52: =IF(J52<=90,F52,0) | AI52: mốt có hàng của CB nhé
A53: 20 | B53: Inactive | C53: ETHATMFY15GB07D | D53: 1CTHATMF01507 | E53: 1CTHATMF01507 | F53: 8 | G53: 8 | I53: =VLOOKUP(C53,'Data Products'!$A:$J,2,0) | J53: =IFERROR(I53-TODAY(),"") | K53: 45859 | L53: =TODAY()-K53 | M53: 0 | N53: 0 | Q53: TrueMove | AB53: =N53/30 | AC53: =IFERROR(F53/AB53,"-") | AD53: =IFERROR(TODAY()+AC53,"-") | AE53: =_xlfn.IFS(AC53="-","Not sold yet",AND(AC53<=150,AC53>60),"Out of stock more than 60 days",AC53<=60,"Out of stock less than 60 days",AC53>=150,"Out of stock more than 150 days") | AF53: =VLOOKUP(C53,'Data Products'!$A:$J,10,0) | AG53: =AF53*F53 | AH53: =IF(J53<=90,F53,0) | AI53: dự kiến cuối tháng 4 có hàng
A54: 21 | B54: Inactive | C54: ETHDCBFY50GB10D | D54: 2CTHACBF05010 | E54: 2CTHACBF05010 | F54: 0 | G54: 0 | I54: =VLOOKUP(C54,'Data Products'!$A:$J,2,0) | J54: =IFERROR(I54-TODAY(),"") | K54: 45860 | L54: =TODAY()-K54 | M54: 0 | N54: 0 | Q54: Commbitz | AB54: =N54/30 | AC54: =IFERROR(F54/AB54,"-") | AD54: =IFERROR(TODAY()+AC54,"-") | AE54: =_xlfn.IFS(AC54="-","Not sold yet",AND(AC54<=150,AC54>60),"Out of stock more than 60 days",AC54<=60,"Out of stock less than 60 days",AC54>=150,"Out of stock more than 150 days") | AF54: =VLOOKUP(C54,'Data Products'!$A:$J,10,0) | AG54: =AF54*F54 | AH54: =IF(J54<=90,F54,0)
A55: 22 | B55: Temporary | C55: 2CTHACBF05010 | D55: 2CTHACBF05010 | E55: 2CTHACBF05010 | F55: 2 | G55: 2 | I55: =VLOOKUP(C55,'Data Products'!$A:$J,2,0) | J55: =IFERROR(I55-TODAY(),"") | K55: 45861 | L55: =TODAY()-K55 | M55: 0 | N55: 0 | Q55: Commbitzz | AB55: =N55/30 | AC55: =IFERROR(F55/AB55,"-") | AD55: =IFERROR(TODAY()+AC55,"-") | AE55: =_xlfn.IFS(AC55="-","Not sold yet",AND(AC55<=150,AC55>60),"Out of stock more than 60 days",AC55<=60,"Out of stock less than 60 days",AC55>=150,"Out of stock more than 150 days") | AF55: =VLOOKUP(C55,'Data Products'!$A:$J,10,0) | AG55: =AF55*F55 | AI55: bán hết sẽ clear tồn
A56: 23 | B56: Inactive | C56: ETHDYDFY50GB10D | F56: 0 | G56: 0 | I56: =VLOOKUP(C56,'Data Products'!$A:$J,2,0) | J56: =IFERROR(I56-TODAY(),"") | K56: 45862 | L56: =TODAY()-K56 | M56: 0 | N56: 0 | Q56: YiDao | AB56: =N56/30 | AC56: =IFERROR(F56/AB56,"-") | AD56: =IFERROR(TODAY()+AC56,"-") | AE56: =_xlfn.IFS(AC56="-","Not sold yet",AND(AC56<=150,AC56>60),"Out of stock more than 60 days",AC56<=60,"Out of stock less than 60 days",AC56>=150,"Out of stock more than 150 days") | AF56: =VLOOKUP(C56,'Data Products'!$A:$J,10,0) | AG56: =AF56*F56 | AH56: =IF(J56<=90,F56,0)
A57: 24 | B57: Inactive | C57: ESGP3HFY15GB30D | F57: 0 | G57: 0 | I57: =VLOOKUP(C57,'Data Products'!$A:$J,2,0) | J57: =IFERROR(I57-TODAY(),"") | K57: 45863 | L57: =TODAY()-K57 | M57: 0 | N57: 0 | Q57: 3HK | AB57: =N57/30 | AC57: =IFERROR(F57/AB57,"-") | AD57: =IFERROR(TODAY()+AC57,"-") | AE57: =_xlfn.IFS(AC57="-","Not sold yet",AND(AC57<=150,AC57>60),"Out of stock more than 60 days",AC57<=60,"Out of stock less than 60 days",AC57>=150,"Out of stock more than 150 days") | AF57: =VLOOKUP(C57,'Data Products'!$A:$J,10,0) | AG57: =AF57*F57 | AH57: =IF(J57<=90,F57,0)
A58: 25 | B58: Inactive | C58: ESGP3HFY30GB30D | F58: 0 | G58: 0 | I58: =VLOOKUP(C58,'Data Products'!$A:$J,2,0) | J58: =IFERROR(I58-TODAY(),"") | K58: 45864 | L58: =TODAY()-K58 | M58: 0 | N58: 0 | Q58: 3HK | AB58: =N58/30 | AC58: =IFERROR(F58/AB58,"-") | AD58: =IFERROR(TODAY()+AC58,"-") | AE58: =_xlfn.IFS(AC58="-","Not sold yet",AND(AC58<=150,AC58>60),"Out of stock more than 60 days",AC58<=60,"Out of stock less than 60 days",AC58>=150,"Out of stock more than 150 days") | AF58: =VLOOKUP(C58,'Data Products'!$A:$J,10,0) | AG58: =AF58*F58 | AH58: =IF(J58<=90,F58,0)
A59: 26 | B59: Inactive | C59: EJPNKDPYUNLI04D | F59: 0 | G59: 0 | H59: 200 HSD 21/06/2025 300 HSD 20/08/2025 | I59: =VLOOKUP(C59,'Data Products'!$A:$J,2,0) | J59: =IFERROR(I59-TODAY(),"") | K59: 45865 | L59: =TODAY()-K59 | M59: 0 | N59: 0 | Q59: KDDI | AB59: =N59/30 | AC59: =IFERROR(F59/AB59,"-") | AD59: =IFERROR(TODAY()+AC59,"-") | AE59: =_xlfn.IFS(AC59="-","Not sold yet",AND(AC59<=150,AC59>60),"Out of stock more than 60 days",AC59<=60,"Out of stock less than 60 days",AC59>=150,"Out of stock more than 150 days") | AF59: =VLOOKUP(C59,'Data Products'!$A:$J,10,0) | AG59: =AF59*F59 | AH59: =IF(J59<=90,F59,0) | AK59: 50
A60: 27 | B60: Inactive | C60: EJPNKDPYUNLI07D | F60: 0 | G60: 0 | I60: =VLOOKUP(C60,'Data Products'!$A:$J,2,0) | J60: =IFERROR(I60-TODAY(),"") | K60: 45866 | L60: =TODAY()-K60 | M60: 0 | N60: 0 | Q60: KDDI | AB60: =N60/30 | AC60: =IFERROR(F60/AB60,"-") | AD60: =IFERROR(TODAY()+AC60,"-") | AE60: =_xlfn.IFS(AC60="-","Not sold yet",AND(AC60<=150,AC60>60),"Out of stock more than 60 days",AC60<=60,"Out of stock less than 60 days",AC60>=150,"Out of stock more than 150 days") | AF60: =VLOOKUP(C60,'Data Products'!$A:$J,10,0) | AG60: =AF60*F60 | AH60: =IF(J60<=90,F60,0) | AK60: 80
A61: 28 | B61: Inactive | C61: EJPNKDPYUNLI10D | F61: 0 | G61: 0 | I61: =VLOOKUP(C61,'Data Products'!$A:$J,2,0) | J61: =IFERROR(I61-TODAY(),"") | K61: 45867 | L61: =TODAY()-K61 | M61: 0 | N61: 0 | Q61: KDDI | AB61: =N61/30 | AC61: =IFERROR(F61/AB61,"-") | AD61: =IFERROR(TODAY()+AC61,"-") | AE61: =_xlfn.IFS(AC61="-","Not sold yet",AND(AC61<=150,AC61>60),"Out of stock more than 60 days",AC61<=60,"Out of stock less than 60 days",AC61>=150,"Out of stock more than 150 days") | AF61: =VLOOKUP(C61,'Data Products'!$A:$J,10,0) | AG61: =AF61*F61 | AH61: =IF(J61<=90,F61,0) | AK61: 60
A62: 29 | B62: Inactive | C62: EJPNKDFY20GB07D | F62: 0 | G62: 0 | H62: 100 HSD 20/08/2025 | I62: =VLOOKUP(C62,'Data Products'!$A:$J,2,0) | J62: =IFERROR(I62-TODAY(),"") | K62: 45868 | L62: =TODAY()-K62 | M62: 0 | N62: 0 | Q62: KDDI | AB62: =N62/30 | AC62: =IFERROR(F62/AB62,"-") | AD62: =IFERROR(TODAY()+AC62,"-") | AE62: =_xlfn.IFS(AC62="-","Not sold yet",AND(AC62<=150,AC62>60),"Out of stock more than 60 days",AC62<=60,"Out of stock less than 60 days",AC62>=150,"Out of stock more than 150 days") | AF62: =VLOOKUP(C62,'Data Products'!$A:$J,10,0) | AG62: =AF62*F62 | AH62: =IF(J62<=90,F62,0) | AK62: 40
A63: 30 | B63: Inactive | C63: EJPNK1PYUNLI07D | F63: 0 | G63: 0 | I63: =VLOOKUP(C63,'Data Products'!$A:$J,2,0) | J63: =IFERROR(I63-TODAY(),"") | K63: 45869 | L63: =TODAY()-K63 | M63: 0 | N63: 0 | Q63: KDDI | AB63: =N63/30 | AC63: =IFERROR(F63/AB63,"-") | AD63: =IFERROR(TODAY()+AC63,"-") | AE63: =_xlfn.IFS(AC63="-","Not sold yet",AND(AC63<=150,AC63>60),"Out of stock more than 60 days",AC63<=60,"Out of stock less than 60 days",AC63>=150,"Out of stock more than 150 days") | AF63: =VLOOKUP(C63,'Data Products'!$A:$J,10,0) | AG63: =AF63*F63 | AH63: =IF(J63<=90,F63,0)
A64: 31 | B64: Inactive | C64: EJPNKDPYUNLI15D | F64: 0 | G64: 0 | I64: =VLOOKUP(C64,'Data Products'!$A:$J,2,0) | J64: =IFERROR(I64-TODAY(),"") | K64: 45870 | L64: =TODAY()-K64 | M64: 0 | N64: 0 | Q64: KDDI | AB64: =N64/30 | AC64: =IFERROR(F64/AB64,"-") | AD64: =IFERROR(TODAY()+AC64,"-") | AE64: =_xlfn.IFS(AC64="-","Not sold yet",AND(AC64<=150,AC64>60),"Out of stock more than 60 days",AC64<=60,"Out of stock less than 60 days",AC64>=150,"Out of stock more than 150 days") | AF64: =VLOOKUP(C64,'Data Products'!$A:$J,10,0) | AG64: =AF64*F64 | AH64: =IF(J64<=90,F64,0)
A65: 32 | B65: Inactive | C65: EKORSBPXUNLI05D | F65: 0 | G65: 0 | I65: =VLOOKUP(C65,'Data Products'!$A:$J,2,0) | J65: =IFERROR(I65-TODAY(),"") | K65: 45871 | L65: =TODAY()-K65 | M65: 0 | N65: 0 | Q65: Softbay | AB65: =N65/30 | AC65: =IFERROR(F65/AB65,"-") | AD65: =IFERROR(TODAY()+AC65,"-") | AE65: =_xlfn.IFS(AC65="-","Not sold yet",AND(AC65<=150,AC65>60),"Out of stock more than 60 days",AC65<=60,"Out of stock less than 60 days",AC65>=150,"Out of stock more than 150 days") | AF65: =VLOOKUP(C65,'Data Products'!$A:$J,10,0) | AG65: =AF65*F65 | AH65: =IF(J65<=90,F65,0)
A66: 33 | B66: Inactive | C66: EKORSBPXUNLI07D | F66: 0 | G66: 0 | I66: =VLOOKUP(C66,'Data Products'!$A:$J,2,0) | J66: =IFERROR(I66-TODAY(),"") | K66: 45872 | L66: =TODAY()-K66 | M66: 0 | N66: 0 | Q66: Softbay | AB66: =N66/30 | AC66: =IFERROR(F66/AB66,"-") | AD66: =IFERROR(TODAY()+AC66,"-") | AE66: =_xlfn.IFS(AC66="-","Not sold yet",AND(AC66<=150,AC66>60),"Out of stock more than 60 days",AC66<=60,"Out of stock less than 60 days",AC66>=150,"Out of stock more than 150 days") | AF66: =VLOOKUP(C66,'Data Products'!$A:$J,10,0) | AG66: =AF66*F66 | AH66: =IF(J66<=90,F66,0)
A67: 34 | B67: Inactive | C67: EKORSBPXUNLI10D | F67: 0 | G67: 0 | I67: =VLOOKUP(C67,'Data Products'!$A:$J,2,0) | J67: =IFERROR(I67-TODAY(),"") | K67: 45873 | L67: =TODAY()-K67 | M67: 0 | N67: 0 | Q67: Softbay | AB67: =N67/30 | AC67: =IFERROR(F67/AB67,"-") | AD67: =IFERROR(TODAY()+AC67,"-") | AE67: =_xlfn.IFS(AC67="-","Not sold yet",AND(AC67<=150,AC67>60),"Out of stock more than 60 days",AC67<=60,"Out of stock less than 60 days",AC67>=150,"Out of stock more than 150 days") | AF67: =VLOOKUP(C67,'Data Products'!$A:$J,10,0) | AG67: =AF67*F67 | AH67: =IF(J67<=90,F67,0)
A68: 35 | B68: Active | C68: EVNMVMPX02GB20D | D68: 11VNMVMZ00220 | E68: 11VNMVMZ00220 | F68: 0 | G68: 0 | I68: =VLOOKUP(C68,'Data Products'!$A:$J,2,0) | J68: =IFERROR(I68-TODAY(),"") | K68: 45874 | L68: =TODAY()-K68 | M68: 0 | N68: 0 | Q68: VietnamMobile | AB68: =N68/30 | AC68: =IFERROR(F68/AB68,"-") | AD68: =IFERROR(TODAY()+AC68,"-") | AE68: =_xlfn.IFS(AC68="-","Not sold yet",AND(AC68<=150,AC68>60),"Out of stock more than 60 days",AC68<=60,"Out of stock less than 60 days",AC68>=150,"Out of stock more than 150 days") | AF68: =VLOOKUP(C68,'Data Products'!$A:$J,10,0) | AG68: =AF68*F68 | AH68: =IF(J68<=90,F68,0) | AK68: 50
A69: 36 | B69: Deleted | C69: EUSAVMFY05GB03D | F69: 0 | G69: 0 | I69: =VLOOKUP(C69,'Data Products'!$A:$J,2,0) | J69: =IFERROR(I69-TODAY(),"") | K69: 45875 | L69: =TODAY()-K69 | M69: 0 | N69: 0 | Q69: VietnamMobile | AB69: =N69/30 | AC69: =IFERROR(F69/AB69,"-") | AD69: =IFERROR(TODAY()+AC69,"-") | AE69: =_xlfn.IFS(AC69="-","Not sold yet",AND(AC69<=150,AC69>60),"Out of stock more than 60 days",AC69<=60,"Out of stock less than 60 days",AC69>=150,"Out of stock more than 150 days") | AF69: =VLOOKUP(C69,'Data Products'!$A:$J,10,0) | AG69: =AF69*F69 | AH69: =IF(J69<=90,F69,0)
A70: 37 | B70: Deleted | C70: EUSAVMFY60GB30D | F70: 0 | G70: 0 | I70: =VLOOKUP(C70,'Data Products'!$A:$J,2,0) | J70: =IFERROR(I70-TODAY(),"") | K70: 45876 | L70: =TODAY()-K70 | M70: 0 | N70: 0 | Q70: VietnamMobile | AB70: =N70/30 | AC70: =IFERROR(F70/AB70,"-") | AD70: =IFERROR(TODAY()+AC70,"-") | AE70: =_xlfn.IFS(AC70="-","Not sold yet",AND(AC70<=150,AC70>60),"Out of stock more than 60 days",AC70<=60,"Out of stock less than 60 days",AC70>=150,"Out of stock more than 150 days") | AF70: =VLOOKUP(C70,'Data Products'!$A:$J,10,0) | AG70: =AF70*F70 | AH70: =IF(J70<=90,F70,0)
A71: 38 | B71: Deleted | C71: EUSAVMFY10GB15D | F71: 0 | G71: 0 | I71: =VLOOKUP(C71,'Data Products'!$A:$J,2,0) | J71: =IFERROR(I71-TODAY(),"") | K71: 45877 | L71: =TODAY()-K71 | M71: 0 | N71: 0 | Q71: VietnamMobile | AB71: =N71/30 | AC71: =IFERROR(F71/AB71,"-") | AD71: =IFERROR(TODAY()+AC71,"-") | AE71: =_xlfn.IFS(AC71="-","Not sold yet",AND(AC71<=150,AC71>60),"Out of stock more than 60 days",AC71<=60,"Out of stock less than 60 days",AC71>=150,"Out of stock more than 150 days") | AF71: =VLOOKUP(C71,'Data Products'!$A:$J,10,0) | AG71: =AF71*F71 | AH71: =IF(J71<=90,F71,0)
A72: 39 | B72: Active | C72: EVNMSFPY03GB15D | D72: 11VNMSFP00315 | E72: 11VNMSFP00315 | F72: 0 | G72: 0 | I72: =VLOOKUP(C72,'Data Products'!$A:$J,2,0) | J72: =IFERROR(I72-TODAY(),"") | K72: 45878 | L72: =TODAY()-K72 | M72: 0 | N72: 0 | Q72: Skyfi | AB72: =N72/30 | AC72: =IFERROR(F72/AB72,"-") | AD72: =IFERROR(TODAY()+AC72,"-") | AE72: =_xlfn.IFS(AC72="-","Not sold yet",AND(AC72<=150,AC72>60),"Out of stock more than 60 days",AC72<=60,"Out of stock less than 60 days",AC72>=150,"Out of stock more than 150 days") | AF72: =VLOOKUP(C72,'Data Products'!$A:$J,10,0) | AG72: =AF72*F72
A73: 40 | B73: Inactive | C73: EVNMMBPX03GB07D | F73: 0 | G73: 0 | I73: =VLOOKUP(C73,'Data Products'!$A:$J,2,0) | J73: =IFERROR(I73-TODAY(),"") | K73: 45879 | L73: =TODAY()-K73 | M73: 0 | N73: 0 | Q73: Mobifone | AB73: =N73/30 | AC73: =IFERROR(F73/AB73,"-") | AD73: =IFERROR(TODAY()+AC73,"-") | AE73: =_xlfn.IFS(AC73="-","Not sold yet",AND(AC73<=150,AC73>60),"Out of stock more than 60 days",AC73<=60,"Out of stock less than 60 days",AC73>=150,"Out of stock more than 150 days") | AF73: =VLOOKUP(C73,'Data Products'!$A:$J,10,0) | AG73: =AF73*F73 | AH73: =IF(J73<=90,F73,0)
A74: 41 | B74: Inactive | C74: EVNMMBPX04GB15D | F74: 0 | G74: 0 | I74: =VLOOKUP(C74,'Data Products'!$A:$J,2,0) | J74: =IFERROR(I74-TODAY(),"") | K74: 45880 | L74: =TODAY()-K74 | M74: 0 | N74: 0 | Q74: Mobifone | AB74: =N74/30 | AC74: =IFERROR(F74/AB74,"-") | AD74: =IFERROR(TODAY()+AC74,"-") | AE74: =_xlfn.IFS(AC74="-","Not sold yet",AND(AC74<=150,AC74>60),"Out of stock more than 60 days",AC74<=60,"Out of stock less than 60 days",AC74>=150,"Out of stock more than 150 days") | AF74: =VLOOKUP(C74,'Data Products'!$A:$J,10,0) | AG74: =AF74*F74 | AH74: =IF(J74<=90,F74,0)
A75: 42 | B75: Inactive | C75: EVNMMBPX05GB15D | F75: 0 | G75: 0 | I75: =VLOOKUP(C75,'Data Products'!$A:$J,2,0) | J75: =IFERROR(I75-TODAY(),"") | K75: 45881 | L75: =TODAY()-K75 | M75: 0 | N75: 0 | Q75: Mobifone | AB75: =N75/30 | AC75: =IFERROR(F75/AB75,"-") | AD75: =IFERROR(TODAY()+AC75,"-") | AE75: =_xlfn.IFS(AC75="-","Not sold yet",AND(AC75<=150,AC75>60),"Out of stock more than 60 days",AC75<=60,"Out of stock less than 60 days",AC75>=150,"Out of stock more than 150 days") | AF75: =VLOOKUP(C75,'Data Products'!$A:$J,10,0) | AG75: =AF75*F75 | AH75: =IF(J75<=90,F75,0)
A76: 43 | B76: Inactive | C76: EVNMMBPY05GB20D | F76: 0 | G76: 0 | I76: =VLOOKUP(C76,'Data Products'!$A:$J,2,0) | J76: =IFERROR(I76-TODAY(),"") | K76: 45882 | L76: =TODAY()-K76 | M76: 0 | N76: 0 | Q76: Mobifone | AB76: =N76/30 | AC76: =IFERROR(F76/AB76,"-") | AD76: =IFERROR(TODAY()+AC76,"-") | AE76: =_xlfn.IFS(AC76="-","Not sold yet",AND(AC76<=150,AC76>60),"Out of stock more than 60 days",AC76<=60,"Out of stock less than 60 days",AC76>=150,"Out of stock more than 150 days") | AF76: =VLOOKUP(C76,'Data Products'!$A:$J,10,0) | AG76: =AF76*F76 | AH76: =IF(J76<=90,F76,0)
A77: 44 | B77: Active | C77: 11VNMMBZ00610 | D77: 11VNMMBZ00610 | E77: 11VNMMBZ00610 | F77: 0 | G77: 0 | I77: =VLOOKUP(C77,'Data Products'!$A:$J,2,0) | J77: =IFERROR(I77-TODAY(),"") | K77: 45883 | L77: =TODAY()-K77 | M77: 0 | N77: 0 | Q77: Mobifone | AB77: =N77/30 | AC77: =IFERROR(F77/AB77,"-") | AD77: =IFERROR(TODAY()+AC77,"-") | AE77: =_xlfn.IFS(AC77="-","Not sold yet",AND(AC77<=150,AC77>60),"Out of stock more than 60 days",AC77<=60,"Out of stock less than 60 days",AC77>=150,"Out of stock more than 150 days") | AF77: =VLOOKUP(C77,'Data Products'!$A:$J,10,0) | AG77: =AF77*F77 | AH77: =IF(J77<=90,F77,0)
A78: 45 | B78: Inactive | C78: EUSATLFX01GB07D | F78: 0 | G78: 0 | I78: =VLOOKUP(C78,'Data Products'!$A:$J,2,0) | J78: =IFERROR(I78-TODAY(),"") | K78: 45884 | L78: =TODAY()-K78 | M78: 0 | N78: 0 | Q78: Mobifone | AB78: =N78/30 | AC78: =IFERROR(F78/AB78,"-") | AD78: =IFERROR(TODAY()+AC78,"-") | AE78: =_xlfn.IFS(AC78="-","Not sold yet",AND(AC78<=150,AC78>60),"Out of stock more than 60 days",AC78<=60,"Out of stock less than 60 days",AC78>=150,"Out of stock more than 150 days") | AF78: =VLOOKUP(C78,'Data Products'!$A:$J,10,0) | AG78: =AF78*F78 | AH78: =IF(J78<=90,F78,0)
A79: 46 | B79: Inactive | C79: EUSATLFX05GB30D | F79: 0 | G79: 0 | I79: =VLOOKUP(C79,'Data Products'!$A:$J,2,0) | J79: =IFERROR(I79-TODAY(),"") | K79: 45885 | L79: =TODAY()-K79 | M79: 0 | N79: 0 | Q79: Mobifone | AB79: =N79/30 | AC79: =IFERROR(F79/AB79,"-") | AD79: =IFERROR(TODAY()+AC79,"-") | AE79: =_xlfn.IFS(AC79="-","Not sold yet",AND(AC79<=150,AC79>60),"Out of stock more than 60 days",AC79<=60,"Out of stock less than 60 days",AC79>=150,"Out of stock more than 150 days") | AF79: =VLOOKUP(C79,'Data Products'!$A:$J,10,0) | AG79: =AF79*F79 | AH79: =IF(J79<=90,F79,0)
A80: 47 | B80: Inactive | C80: EUSATLFX10GB30D | F80: 0 | G80: 0 | I80: =VLOOKUP(C80,'Data Products'!$A:$J,2,0) | J80: =IFERROR(I80-TODAY(),"") | K80: 45886 | L80: =TODAY()-K80 | M80: 0 | N80: 0 | Q80: Mobifone | AB80: =N80/30 | AC80: =IFERROR(F80/AB80,"-") | AD80: =IFERROR(TODAY()+AC80,"-") | AE80: =_xlfn.IFS(AC80="-","Not sold yet",AND(AC80<=150,AC80>60),"Out of stock more than 60 days",AC80<=60,"Out of stock less than 60 days",AC80>=150,"Out of stock more than 150 days") | AF80: =VLOOKUP(C80,'Data Products'!$A:$J,10,0) | AG80: =AF80*F80 | AH80: =IF(J80<=90,F80,0)
A81: 48 | B81: Inactive | C81: EUSATLFX20GB30D | F81: 0 | G81: 0 | I81: =VLOOKUP(C81,'Data Products'!$A:$J,2,0) | J81: =IFERROR(I81-TODAY(),"") | K81: 45887 | L81: =TODAY()-K81 | M81: 0 | N81: 0 | Q81: Mobifone | AB81: =N81/30 | AC81: =IFERROR(F81/AB81,"-") | AD81: =IFERROR(TODAY()+AC81,"-") | AE81: =_xlfn.IFS(AC81="-","Not sold yet",AND(AC81<=150,AC81>60),"Out of stock more than 60 days",AC81<=60,"Out of stock less than 60 days",AC81>=150,"Out of stock more than 150 days") | AF81: =VLOOKUP(C81,'Data Products'!$A:$J,10,0) | AG81: =AF81*F81 | AH81: =IF(J81<=90,F81,0)
A82: 49 | B82: Inactive | C82: EUSATLFX50GB30D | F82: 0 | G82: 0 | I82: =VLOOKUP(C82,'Data Products'!$A:$J,2,0) | J82: =IFERROR(I82-TODAY(),"") | K82: 45888 | L82: =TODAY()-K82 | M82: 0 | N82: 0 | Q82: Mobifone | AB82: =N82/30 | AC82: =IFERROR(F82/AB82,"-") | AD82: =IFERROR(TODAY()+AC82,"-") | AE82: =_xlfn.IFS(AC82="-","Not sold yet",AND(AC82<=150,AC82>60),"Out of stock more than 60 days",AC82<=60,"Out of stock less than 60 days",AC82>=150,"Out of stock more than 150 days") | AF82: =VLOOKUP(C82,'Data Products'!$A:$J,10,0) | AG82: =AF82*F82 | AH82: =IF(J82<=90,F82,0)
A83: 50 | B83: Inactive | C83: EE33UBPY500M01D | D83: 4CE33UBP5HM01 | E83: 4CE33UBP5HM01 | F83: 0 | G83: 0 | I83: =VLOOKUP(C83,'Data Products'!$A:$J,2,0) | J83: =IFERROR(I83-TODAY(),"") | K83: 45889 | L83: =TODAY()-K83 | M83: 0 | N83: 0 | Q83: Mobifone | AB83: =N83/30 | AC83: =IFERROR(F83/AB83,"-") | AD83: =IFERROR(TODAY()+AC83,"-") | AE83: =_xlfn.IFS(AC83="-","Not sold yet",AND(AC83<=150,AC83>60),"Out of stock more than 60 days",AC83<=60,"Out of stock less than 60 days",AC83>=150,"Out of stock more than 150 days") | AF83: =VLOOKUP(C83,'Data Products'!$A:$J,10,0) | AG83: =AF83*F83 | AH83: =IF(J83<=90,F83,0)
A84: 51 | B84: Inactive | C84: EE33UBPY500M03D | D84: 4CE33UBP5HM03 | E84: 4CE33UBP5HM03 | F84: 0 | G84: 0 | I84: =VLOOKUP(C84,'Data Products'!$A:$J,2,0) | J84: =IFERROR(I84-TODAY(),"") | K84: 45890 | L84: =TODAY()-K84 | M84: 0 | N84: 0 | Q84: Mobifone | AB84: =N84/30 | AC84: =IFERROR(F84/AB84,"-") | AD84: =IFERROR(TODAY()+AC84,"-") | AE84: =_xlfn.IFS(AC84="-","Not sold yet",AND(AC84<=150,AC84>60),"Out of stock more than 60 days",AC84<=60,"Out of stock less than 60 days",AC84>=150,"Out of stock more than 150 days") | AF84: =VLOOKUP(C84,'Data Products'!$A:$J,10,0) | AG84: =AF84*F84 | AH84: =IF(J84<=90,F84,0)
A85: 52 | B85: Inactive | C85: EE33UBPY500M05D | D85: 4CE33UBP5HM05 | E85: 4CE33UBP5HM05 | F85: 0 | G85: 0 | I85: =VLOOKUP(C85,'Data Products'!$A:$J,2,0) | J85: =IFERROR(I85-TODAY(),"") | K85: 45891 | L85: =TODAY()-K85 | M85: 0 | N85: 0 | Q85: Mobifone | AB85: =N85/30 | AC85: =IFERROR(F85/AB85,"-") | AD85: =IFERROR(TODAY()+AC85,"-") | AE85: =_xlfn.IFS(AC85="-","Not sold yet",AND(AC85<=150,AC85>60),"Out of stock more than 60 days",AC85<=60,"Out of stock less than 60 days",AC85>=150,"Out of stock more than 150 days") | AF85: =VLOOKUP(C85,'Data Products'!$A:$J,10,0) | AG85: =AF85*F85 | AH85: =IF(J85<=90,F85,0)
A86: 53 | B86: Inactive | C86: EE33UBPY500M07D | D86: 4CE33UBP5HM07 | E86: 4CE33UBP5HM07 | F86: 0 | G86: 0 | I86: =VLOOKUP(C86,'Data Products'!$A:$J,2,0) | J86: =IFERROR(I86-TODAY(),"") | K86: 45892 | L86: =TODAY()-K86 | M86: 0 | N86: 0 | Q86: Mobifone | AB86: =N86/30 | AC86: =IFERROR(F86/AB86,"-") | AD86: =IFERROR(TODAY()+AC86,"-") | AE86: =_xlfn.IFS(AC86="-","Not sold yet",AND(AC86<=150,AC86>60),"Out of stock more than 60 days",AC86<=60,"Out of stock less than 60 days",AC86>=150,"Out of stock more than 150 days") | AF86: =VLOOKUP(C86,'Data Products'!$A:$J,10,0) | AG86: =AF86*F86 | AH86: =IF(J86<=90,F86,0)
A87: 54 | B87: Inactive | C87: EE33UBPY500M10D | D87: 4CE33UBP5HM10 | E87: 4CE33UBP5HM10 | F87: 0 | G87: 0 | I87: =VLOOKUP(C87,'Data Products'!$A:$J,2,0) | J87: =IFERROR(I87-TODAY(),"") | K87: 45893 | L87: =TODAY()-K87 | M87: 0 | N87: 0 | Q87: Mobifone | AB87: =N87/30 | AC87: =IFERROR(F87/AB87,"-") | AD87: =IFERROR(TODAY()+AC87,"-") | AE87: =_xlfn.IFS(AC87="-","Not sold yet",AND(AC87<=150,AC87>60),"Out of stock more than 60 days",AC87<=60,"Out of stock less than 60 days",AC87>=150,"Out of stock more than 150 days") | AF87: =VLOOKUP(C87,'Data Products'!$A:$J,10,0) | AG87: =AF87*F87 | AH87: =IF(J87<=90,F87,0)
A88: 55 | B88: Inactive | C88: EE33UBPY500M15D | D88: 4CE33UBP5HM15 | E88: 4CE33UBP5HM15 | F88: 0 | G88: 0 | I88: =VLOOKUP(C88,'Data Products'!$A:$J,2,0) | J88: =IFERROR(I88-TODAY(),"") | K88: 45894 | L88: =TODAY()-K88 | M88: 0 | N88: 0 | Q88: Mobifone | AB88: =N88/30 | AC88: =IFERROR(F88/AB88,"-") | AD88: =IFERROR(TODAY()+AC88,"-") | AE88: =_xlfn.IFS(AC88="-","Not sold yet",AND(AC88<=150,AC88>60),"Out of stock more than 60 days",AC88<=60,"Out of stock less than 60 days",AC88>=150,"Out of stock more than 150 days") | AF88: =VLOOKUP(C88,'Data Products'!$A:$J,10,0) | AG88: =AF88*F88 | AH88: =IF(J88<=90,F88,0)
A89: 56 | B89: Inactive | C89: EE33UBPY01GB03D | D89: 4CE33UBP5HM | E89: 4CE33UBP5HM | F89: 0 | G89: 0 | I89: =VLOOKUP(C89,'Data Products'!$A:$J,2,0) | J89: =IFERROR(I89-TODAY(),"") | K89: 45895 | L89: =TODAY()-K89 | M89: 0 | N89: 0 | Q89: Mobifone | AB89: =N89/30 | AC89: =IFERROR(F89/AB89,"-") | AD89: =IFERROR(TODAY()+AC89,"-") | AE89: =_xlfn.IFS(AC89="-","Not sold yet",AND(AC89<=150,AC89>60),"Out of stock more than 60 days",AC89<=60,"Out of stock less than 60 days",AC89>=150,"Out of stock more than 150 days") | AF89: =VLOOKUP(C89,'Data Products'!$A:$J,10,0) | AG89: =AF89*F89 | AH89: =IF(J89<=90,F89,0)
A90: 57 | B90: Inactive | C90: EE33UBPY01GB05D | D90: 4CE33UBP00105 | E90: 4CE33UBP00105 | F90: 0 | G90: 0 | I90: =VLOOKUP(C90,'Data Products'!$A:$J,2,0) | J90: =IFERROR(I90-TODAY(),"") | K90: 45896 | L90: =TODAY()-K90 | M90: 0 | N90: 0 | Q90: Mobifone | AB90: =N90/30 | AC90: =IFERROR(F90/AB90,"-") | AD90: =IFERROR(TODAY()+AC90,"-") | AE90: =_xlfn.IFS(AC90="-","Not sold yet",AND(AC90<=150,AC90>60),"Out of stock more than 60 days",AC90<=60,"Out of stock less than 60 days",AC90>=150,"Out of stock more than 150 days") | AF90: =VLOOKUP(C90,'Data Products'!$A:$J,10,0) | AG90: =AF90*F90 | AH90: =IF(J90<=90,F90,0)
A91: 58 | B91: Inactive | C91: EE33UBPY01GB07D | D91: 4CE33UBP00107 | E91: 4CE33UBP00107 | F91: 0 | G91: 0 | I91: =VLOOKUP(C91,'Data Products'!$A:$J,2,0) | J91: =IFERROR(I91-TODAY(),"") | K91: 45897 | L91: =TODAY()-K91 | M91: 0 | N91: 0 | Q91: Mobifone | AB91: =N91/30 | AC91: =IFERROR(F91/AB91,"-") | AD91: =IFERROR(TODAY()+AC91,"-") | AE91: =_xlfn.IFS(AC91="-","Not sold yet",AND(AC91<=150,AC91>60),"Out of stock more than 60 days",AC91<=60,"Out of stock less than 60 days",AC91>=150,"Out of stock more than 150 days") | AF91: =VLOOKUP(C91,'Data Products'!$A:$J,10,0) | AG91: =AF91*F91 | AH91: =IF(J91<=90,F91,0)
A92: 59 | B92: Inactive | C92: EE33UBPY01GB10D | D92: 4CE33UBP00110 | E92: 4CE33UBP00110 | F92: 0 | G92: 0 | I92: =VLOOKUP(C92,'Data Products'!$A:$J,2,0) | J92: =IFERROR(I92-TODAY(),"") | K92: 45898 | L92: =TODAY()-K92 | M92: 0 | N92: 0 | Q92: Mobifone | AB92: =N92/30 | AC92: =IFERROR(F92/AB92,"-") | AD92: =IFERROR(TODAY()+AC92,"-") | AE92: =_xlfn.IFS(AC92="-","Not sold yet",AND(AC92<=150,AC92>60),"Out of stock more than 60 days",AC92<=60,"Out of stock less than 60 days",AC92>=150,"Out of stock more than 150 days") | AF92: =VLOOKUP(C92,'Data Products'!$A:$J,10,0) | AG92: =AF92*F92 | AH92: =IF(J92<=90,F92,0)
A93: 60 | B93: Inactive | C93: EE33UBPY01GB15D | D93: 4CE33UBP00115 | E93: 4CE33UBP00115 | F93: 0 | G93: 0 | I93: =VLOOKUP(C93,'Data Products'!$A:$J,2,0) | J93: =IFERROR(I93-TODAY(),"") | K93: 45899 | L93: =TODAY()-K93 | M93: 0 | N93: 0 | Q93: Mobifone | AB93: =N93/30 | AC93: =IFERROR(F93/AB93,"-") | AD93: =IFERROR(TODAY()+AC93,"-") | AE93: =_xlfn.IFS(AC93="-","Not sold yet",AND(AC93<=150,AC93>60),"Out of stock more than 60 days",AC93<=60,"Out of stock less than 60 days",AC93>=150,"Out of stock more than 150 days") | AF93: =VLOOKUP(C93,'Data Products'!$A:$J,10,0) | AG93: =AF93*F93 | AH93: =IF(J93<=90,F93,0)
A94: 61 | B94: Inactive | C94: EE33UBPY01GB20D | D94: 4CE33UBP00120 | E94: 4CE33UBP00120 | F94: 0 | G94: 0 | I94: =VLOOKUP(C94,'Data Products'!$A:$J,2,0) | J94: =IFERROR(I94-TODAY(),"") | K94: 45900 | L94: =TODAY()-K94 | M94: 0 | N94: 0 | Q94: Mobifone | AB94: =N94/30 | AC94: =IFERROR(F94/AB94,"-") | AD94: =IFERROR(TODAY()+AC94,"-") | AE94: =_xlfn.IFS(AC94="-","Not sold yet",AND(AC94<=150,AC94>60),"Out of stock more than 60 days",AC94<=60,"Out of stock less than 60 days",AC94>=150,"Out of stock more than 150 days") | AF94: =VLOOKUP(C94,'Data Products'!$A:$J,10,0) | AG94: =AF94*F94 | AH94: =IF(J94<=90,F94,0)
... A102: 69 | B102: Inactive | C102: EE33UBPY02GB30D | D102: 4CE33UBP00230 | E102: 4CE33UBP00230 | F102: 0 | G102: 0 | I102: =VLOOKUP(C102,'Data Products'!$A:$J,2,0) | J102: =IFERROR(I102-TODAY(),"") | K102: 45908 | L102: =TODAY()-K102 | M102: 0 | N102: 0 | Q102: Mobifone | AB102: =N102/30 | AC102: =IFERROR(F102/AB102,"-") | AD102: =IFERROR(TODAY()+AC102,"-") | AE102: =_xlfn.IFS(AC102="-","Not sold yet",AND(AC102<=150,AC102>60),"Out of stock more than 60 days",AC102<=60,"Out of stock less than 60 days",AC102>=150,"Out of stock more than 150 days") | AF102: =VLOOKUP(C102,'Data Products'!$A:$J,10,0) | AG102: =AF102*F102 | AH102: =IF(J102<=90,F102,0)
A103: 70 | B103: Inactive | C103: ETWNW1FY05GB10D | F103: 0 | G103: 0 | I103: =VLOOKUP(C103,'Data Products'!$A:$J,2,0) | J103: =IFERROR(I103-TODAY(),"") | K103: 45909 | L103: =TODAY()-K103 | M103: 0 | N103: 0 | Q103: Mobifone | AB103: =N103/30 | AC103: =IFERROR(F103/AB103,"-") | AD103: =IFERROR(TODAY()+AC103,"-") | AE103: =_xlfn.IFS(AC103="-","Not sold yet",AND(AC103<=150,AC103>60),"Out of stock more than 60 days",AC103<=60,"Out of stock less than 60 days",AC103>=150,"Out of stock more than 150 days") | AF103: =VLOOKUP(C103,'Data Products'!$A:$J,10,0) | AG103: =AF103*F103 | AH103: =IF(J103<=90,F103,0)
A104: 71 | B104: Inactive | C104: ETWNW1FY05GB15D | F104: 0 | G104: 0 | I104: =VLOOKUP(C104,'Data Products'!$A:$J,2,0) | J104: =IFERROR(I104-TODAY(),"") | K104: 45910 | L104: =TODAY()-K104 | M104: 0 | N104: 0 | Q104: Mobifone | AB104: =N104/30 | AC104: =IFERROR(F104/AB104,"-") | AD104: =IFERROR(TODAY()+AC104,"-") | AE104: =_xlfn.IFS(AC104="-","Not sold yet",AND(AC104<=150,AC104>60),"Out of stock more than 60 days",AC104<=60,"Out of stock less than 60 days",AC104>=150,"Out of stock more than 150 days") | AF104: =VLOOKUP(C104,'Data Products'!$A:$J,10,0) | AG104: =AF104*F104 | AH104: =IF(J104<=90,F104,0) | AI104: đã lên ticket nhờ đẩy tồn
A105: 72 | B105: Inactive | C105: ETWNW1FY10GB15D | F105: 0 | G105: 0 | I105: =VLOOKUP(C105,'Data Products'!$A:$J,2,0) | J105: =IFERROR(I105-TODAY(),"") | K105: 45911 | L105: =TODAY()-K105 | M105: 0 | N105: 0 | Q105: Mobifone | AB105: =N105/30 | AC105: =IFERROR(F105/AB105,"-") | AD105: =IFERROR(TODAY()+AC105,"-") | AE105: =_xlfn.IFS(AC105="-","Not sold yet",AND(AC105<=150,AC105>60),"Out of stock more than 60 days",AC105<=60,"Out of stock less than 60 days",AC105>=150,"Out of stock more than 150 days") | AF105: =VLOOKUP(C105,'Data Products'!$A:$J,10,0) | AG105: =AF105*F105 | AH105: =IF(J105<=90,F105,0)
A106: 45 | B106: Active | C106: ETWNW1FY20GB15D | D106: 2CTHATMF05010 | E106: 2CTHATMF05010 | F106: 0 | G106: 0 | I106: =VLOOKUP(C106,'Data Products'!$A:$J,2,0) | J106: =IFERROR(I106-TODAY(),"") | K106: 45912 | L106: =TODAY()-K106 | M106: 0 | N106: 0 | Q106: TrueMove | AB106: =N106/30 | AC106: =IFERROR(F106/AB106,"-") | AD106: =IFERROR(TODAY()+AC106,"-") | AE106: =_xlfn.IFS(AC106="-","Not sold yet",AND(AC106<=150,AC106>60),"Out of stock more than 60 days",AC106<=60,"Out of stock less than 60 days",AC106>=150,"Out of stock more than 150 days") | AF106: =VLOOKUP(C106,'Data Products'!$A:$J,10,0) | AG106: =AF106*F106
A107: 46 | B107: Active | C107: 1CCNMCUF00708 | D107: 1CCNMCUF00708 | E107: 1CCNMCUF00708 | F107: 0 | G107: 0 | I107: =VLOOKUP(C107,'Data Products'!$A:$J,2,0) | J107: =IFERROR(I107-TODAY(),"") | K107: 45913 | L107: =TODAY()-K107 | M107: 0 | N107: 0 | Q107: TrueMove | AB107: =N107/30 | AC107: =IFERROR(F107/AB107,"-") | AD107: =IFERROR(TODAY()+AC107,"-") | AE107: =_xlfn.IFS(AC107="-","Not sold yet",AND(AC107<=150,AC107>60),"Out of stock more than 60 days",AC107<=60,"Out of stock less than 60 days",AC107>=150,"Out of stock more than 150 days") | AF107: =VLOOKUP(C107,'Data Products'!$A:$J,10,0) | AG107: =AF107*F107 | AI107: không nhập thêm
A108: 47 | B108: Active | C108: 1CKORCUF01005 | D108: 1CKORCUF01005 | E108: 1CKORCUF01005 | F108: 31 | G108: 31 | I108: =VLOOKUP(C108,'Data Products'!$A:$J,2,0) | J108: =IFERROR(I108-TODAY(),"") | K108: 45914 | L108: =TODAY()-K108 | M108: 0 | N108: 0 | Q108: 4HK | AB108: =N108/30 | AC108: =IFERROR(F108/AB108,"-") | AD108: =IFERROR(TODAY()+AC108,"-") | AE108: =_xlfn.IFS(AC108="-","Not sold yet",AND(AC108<=150,AC108>60),"Out of stock more than 60 days",AC108<=60,"Out of stock less than 60 days",AC108>=150,"Out of stock more than 150 days") | AF108: =VLOOKUP(C108,'Data Products'!$A:$J,10,0) | AG108: =AF108*F108 | AI108: khuyến mãi đẩy tồn
...

Sheet 10.08
A1: SIM | B1: Status | C1: SKU (Sapo) | D1: SKU (mới) | E1: SKU (full) | F1: Total Inventory | H1: Quantity due to expiration | I1: Expiration | J1: Expired date left | K1: Date of Import | L1: Inventory Age | M1: Last 15 days | N1: Last 30 days | O1: Safety Stock (15D) | P1: Reorder Point (30D) | Q1: Vendor | R1: Kho tổng | T1: Phổ Quang - HCM | V1: Đống Đa - Hà Nội | X1: Tân Sơn Nhất - HCM | Z1: Chi nhánh Ký gửi | AB1: Avg Pcs/day | AC1: DOI (Số ngày tồn kho) | AD1: Estimated date out of stock | AE1: Evaluate | AF1: Retail Price | AG1: Total retail price | AH1: Near Expiration Inventory | AI1: OPS | AJ1: Telco | AK1: OD | AL1: WS | AM1: B2C | AN1: Marketing
A2: No. | F2: Stock | G2: Available for sale | M2: Sold | N2: Sold | R2: Stock | S2: Available for sale | T2: Stock | U2: Available for sale | V2: Stock | W2: Available for sale | X2: Stock | Y2: Available for sale | Z2: Stock | AA2: Available for sale
A3: 1 | B3: Temporary | C3: 3HKDATAPOOLSIM | D3: 3HKDATAPOOLSIM | E3: 1D0003DK00000 | F3: 419 | G3: 419 | I3: =VLOOKUP(C3,'Data Products'!$A:$B,2,0) | J3: =IFERROR(I3-TODAY(),"") | K3: 45723 | L3: =TODAY()-K3 | M3: 354 | N3: 380 | R3: 0 | S3: 0 | T3: 326 | U3: 326 | V3: 146 | W3: 146 | X3: 0 | Y3: 0 | Z3: 0 | AA3: 0 | AB3: =N3/30 | AC3: =IFERROR(F3/AB3,"-") | AD3: =IFERROR(TODAY()+AC3,"-") | AE3: =_xlfn.IFS(AC3="-","Not sold yet",AND(AC3<=150,AC3>60),"Out of stock more than 60 days",AC3<=60,"Out of stock less than 60 days",AC3>=150,"Out of stock more than 150 days") | AF3: =VLOOKUP(C3,'Data Products'!$A:$J,10,0) | AG3: =AF3*F3 | AH3: =IF(J3<=90,F3,0) | AI3: =IFERROR(VLOOKUP(C3,$C$3:$AI$42,34,0),"")
A4: 1 | B4: Active | C4: 1D0003DK00000 | D4: 1D0003DK00000 | E4: 1D0003DK00000 | F4: 18479 | G4: 18407 | I4: =VLOOKUP(C4,'Data Products'!$A:$B,2,0) | J4: =IFERROR(I4-TODAY(),"") | K4: 45617 | L4: =TODAY()-K4 | M4: 9349 | N4: 15283 | R4: 0 | S4: 0 | T4: 1378 | U4: 1369 | V4: 115 | W4: 112 | X4: 46 | Y4: 22 | Z4: 0 | AA4: 0 | AB4: =N4/30 | AC4: =IFERROR(F4/AB4,"-") | AD4: =IFERROR(TODAY()+AC4,"-") | AE4: =_xlfn.IFS(AC4="-","Not sold yet",AND(AC4<=150,AC4>60),"Out of stock more than 60 days",AC4<=60,"Out of stock less than 60 days",AC4>=150,"Out of stock more than 150 days") | AF4: =VLOOKUP(C4,'Data Products'!$A:$J,10,0) | AG4: =AF4*F4 | AH4: =IF(J4<=90,F4,0) | AI4: cần có hàng mới 20 - 25/08 để an toàn
A5: 2 | B5: Active | C5: 1D000BCK00000 | D5: 1D000BCK00000 | E5: 1D000BCK00000 | F5: 285 | G5: 285 | I5: =VLOOKUP(C5,'Data Products'!$A:$B,2,0) | J5: =IFERROR(I5-TODAY(),"") | K5: 45191 | L5: =TODAY()-K5 | M5: 17 | N5: 36 | R5: 0 | S5: 0 | T5: 26 | U5: 26 | V5: 416 | W5: 416 | X5: 0 | Y5: 0 | Z5: 0 | AA5: 0 | AB5: =N5/30 | AC5: =IFERROR(F5/AB5,"-") | AD5: =IFERROR(TODAY()+AC5,"-") | AE5: =_xlfn.IFS(AC5="-","Not sold yet",AND(AC5<=150,AC5>60),"Out of stock more than 60 days",AC5<=60,"Out of stock less than 60 days",AC5>=150,"Out of stock more than 150 days") | AF5: =VLOOKUP(C5,'Data Products'!$A:$J,10,0) | AG5: =AF5*F5 | AH5: =IF(J5<=90,F5,0) | AI5: sắp hết hạn, gia hạn thêm 1 tháng
A6: 3 | B6: Active | C6: 1D000ELK00000 | D6: 1D000ELK00000 | E6: 1D000ELK00000 | F6: 4268 | G6: 4268 | I6: =VLOOKUP(C6,'Data Products'!$A:$B,2,0) | J6: =IFERROR(I6-TODAY(),"") | K6: 45752 | L6: =TODAY()-K6 | M6: 28 | N6: 48 | R6: 0 | S6: 0 | T6: 1 | U6: 1 | V6: 1 | W6: 1 | X6: 0 | Y6: 0 | Z6: 0 | AA6: 0 | AB6: =N6/30 | AC6: =IFERROR(F6/AB6,"-") | AD6: =IFERROR(TODAY()+AC6,"-") | AE6: =_xlfn.IFS(AC6="-","Not sold yet",AND(AC6<=150,AC6>60),"Out of stock more than 60 days",AC6<=60,"Out of stock less than 60 days",AC6>=150,"Out of stock more than 150 days") | AF6: =VLOOKUP(C6,'Data Products'!$A:$J,10,0) | AG6: =AF6*F6 | AH6: =IF(J6<=90,F6,0) | AI6: =IFERROR(VLOOKUP(C6,$C$3:$AI$42,34,0),"")
A7: 4 | B7: Active | C7: 1D000JYK00000 | D7: 1D000JYK00000 | E7: 1D000JYK00000 | F7: 882 | G7: 862 | I7: =VLOOKUP(C7,'Data Products'!$A:$B,2,0) | J7: =IFERROR(I7-TODAY(),"") | K7: 45854 | L7: =TODAY()-K7 | M7: 3 | N7: 6 | R7: 0 | S7: 0 | T7: 288 | U7: 288 | V7: 512 | W7: 512 | X7: 20 | Y7: 20 | Z7: 0 | AA7: 0 | AB7: =N7/30 | AC7: =IFERROR(F7/AB7,"-") | AD7: =IFERROR(TODAY()+AC7,"-") | AE7: =_xlfn.IFS(AC7="-","Not sold yet",AND(AC7<=150,AC7>60),"Out of stock more than 60 days",AC7<=60,"Out of stock less than 60 days",AC7>=150,"Out of stock more than 150 days") | AF7: =VLOOKUP(C7,'Data Products'!$A:$J,10,0) | AG7: =AF7*F7 | AH7: =IF(J7<=90,F7,0) | AI7: =IFERROR(VLOOKUP(C7,$C$3:$AI$42,34,0),"")
A8: 5 | B8: Active | C8: 1D000SSK00000 | D8: 1D000SSK00000 | E8: 1D000SSK00000 | F8: 2468 | G8: 2468 | I8: =VLOOKUP(C8,'Data Products'!$A:$B,2,0) | J8: =IFERROR(I8-TODAY(),"") | K8: 45855 | L8: =TODAY()-K8 | M8: 9 | N8: 52 | R8: 0 | S8: 0 | T8: 51 | U8: 51 | V8: 101 | W8: 101 | X8: 0 | Y8: 0 | Z8: 0 | AA8: 0 | AB8: =N8/30 | AC8: =IFERROR(F8/AB8,"-") | AD8: =IFERROR(TODAY()+AC8,"-") | AE8: =_xlfn.IFS(AC8="-","Not sold yet",AND(AC8<=150,AC8>60),"Out of stock more than 60 days",AC8<=60,"Out of stock less than 60 days",AC8>=150,"Out of stock more than 150 days") | AF8: =VLOOKUP(C8,'Data Products'!$A:$J,10,0) | AG8: =AF8*F8 | AH8: =IF(J8<=90,F8,0) | AI8: =IFERROR(VLOOKUP(C8,$C$3:$AI$42,34,0)," ")
A9: 6 | B9: Active | C9: 1D000UBK00000 | D9: 1D000UBK00000 | E9: 1D000UBK00000 | F9: 2062 | G9: 2062 | I9: =VLOOKUP(C9,'Data Products'!$A:$B,2,0) | J9: =IFERROR(I9-TODAY(),"") | K9: 45856 | L9: =TODAY()-K9 | M9: 0 | N9: 0 | R9: 0 | S9: 0 | T9: 1480 | U9: 1478 | V9: 1112 | W9: 1112 | X9: 0 | Y9: 0 | Z9: 0 | AA9: 0 | AB9: =N9/30 | AC9: =IFERROR(F9/AB9,"-") | AD9: =IFERROR(TODAY()+AC9,"-") | AE9: =_xlfn.IFS(AC9="-","Not sold yet",AND(AC9<=150,AC9>60),"Out of stock more than 60 days",AC9<=60,"Out of stock less than 60 days",AC9>=150,"Out of stock more than 150 days") | AF9: =VLOOKUP(C9,'Data Products'!$A:$J,10,0) | AG9: =AF9*F9 | AH9: =IF(J9<=90,F9,0) | AI9: =IFERROR(VLOOKUP(C9,$C$3:$AI$42,34,0),"")
A10: 7 | B10: Active | C10: 1D000WMK00000 | D10: 1D000WMK00000 | E10: 1D000WMK00000 | F10: 461 | G10: 458 | I10: =VLOOKUP(C10,'Data Products'!$A:$B,2,0) | J10: =IFERROR(I10-TODAY(),"") | K10: 45857 | L10: =TODAY()-K10 | M10: 132 | N10: 267 | R10: 0 | S10: 0 | T10: 0 | U10: 0 | V10: 2 | W10: 2 | X10: 0 | Y10: 0 | Z10: 0 | AA10: 0 | AB10: =N10/30 | AC10: =IFERROR(F10/AB10,"-") | AD10: =IFERROR(TODAY()+AC10,"-") | AE10: =_xlfn.IFS(AC10="-","Not sold yet",AND(AC10<=150,AC10>60),"Out of stock more than 60 days",AC10<=60,"Out of stock less than 60 days",AC10>=150,"Out of stock more than 150 days") | AF10: =VLOOKUP(C10,'Data Products'!$A:$J,10,0) | AG10: =AF10*F10 | AH10: =IF(J10<=90,F10,0) | AI10: =IFERROR(VLOOKUP(C10,$C$3:$AI$42,34,0),"")
A11: 8 | B11: Temporary | C11: CNMCU05GBFY05D | D11: CNMCU05GBFY05D | E11: CNMCU05GBFY05D | F11: 1200 | G11: 1200 | I11: =VLOOKUP(C11,'Data Products'!$A:$B,2,0) | J11: =IFERROR(I11-TODAY(),"") | K11: 45858 | L11: =TODAY()-K11 | M11: 0 | N11: 0 | R11: 0 | S11: 0 | T11: 1289 | U11: 1289 | V11: 773 | W11: 773 | X11: 0 | Y11: 0 | Z11: 0 | AA11: 0 | AB11: =N11/30 | AC11: =IFERROR(F11/AB11,"-") | AD11: =IFERROR(TODAY()+AC11,"-") | AE11: =_xlfn.IFS(AC11="-","Not sold yet",AND(AC11<=150,AC11>60),"Out of stock more than 60 days",AC11<=60,"Out of stock less than 60 days",AC11>=150,"Out of stock more than 150 days") | AF11: =VLOOKUP(C11,'Data Products'!$A:$J,10,0) | AG11: =AF11*F11 | AH11: =IF(J11<=90,F11,0) | AI11: =IFERROR(VLOOKUP(C11,$C$3:$AI$42,34,0),"")
A12: 9 | B12: Temporary | C12: CNMCU07GBFY08D | D12: CNMCU07GBFY08D | E12: CNMCU07GBFY08D | F12: 1000 | G12: 1000 | I12: =VLOOKUP(C12,'Data Products'!$A:$B,2,0) | J12: =IFERROR(I12-TODAY(),"") | K12: 45532 | L12: =TODAY()-K12 | M12: 0 | N12: 0 | R12: 0 | S12: 0 | T12: 417 | U12: 416 | V12: 785 | W12: 785 | X12: 0 | Y12: 0 | Z12: 0 | AA12: 0 | AB12: =N12/30 | AC12: =IFERROR(F12/AB12,"-") | AD12: =IFERROR(TODAY()+AC12,"-") | AE12: =_xlfn.IFS(AC12="-","Not sold yet",AND(AC12<=150,AC12>60),"Out of stock more than 60 days",AC12<=60,"Out of stock less than 60 days",AC12>=150,"Out of stock more than 150 days") | AF12: =VLOOKUP(C12,'Data Products'!$A:$J,10,0) | AG12: =AF12*F12 | AH12: =IF(J12<=90,F12,0) | AI12: qua tết push lại, mỗi tuần nhắc lại
A13: 10 | B13: Temporary | C13: KORCU10GBFY05D | D13: KORCU10GBFY05D | E13: KORCU10GBFY05D | F13: 500 | G13: 500 | I13: =VLOOKUP(C13,'Data Products'!$A:$B,2,0) | J13: =IFERROR(I13-TODAY(),"") | K13: 45504 | L13: =TODAY()-K13 | M13: 0 | N13: 0 | R13: 0 | S13: 0 | T13: 3870 | U13: 1017 | V13: 366 | W13: 366 | X13: 0 | Y13: 0 | Z13: 0 | AA13: 0 | AB13: =N13/30 | AC13: =IFERROR(F13/AB13,"-") | AD13: =IFERROR(TODAY()+AC13,"-") | AE13: =_xlfn.IFS(AC13="-","Not sold yet",AND(AC13<=150,AC13>60),"Out of stock more than 60 days",AC13<=60,"Out of stock less than 60 days",AC13>=150,"Out of stock more than 150 days") | AF13: =VLOOKUP(C13,'Data Products'!$A:$J,10,0) | AG13: =AF13*F13 | AH13: =IF(J13<=90,F13,0) | AI13: =IFERROR(VLOOKUP(C13,$C$3:$AI$42,34,0),"")
A14: 11 | B14: Active | C14: 1DCNMCTF00705 | D14: 1DCNMCTF00705 | E14: 1ECNMCTF00705 | F14: 181 | G14: 181 | I14: =VLOOKUP(C14,'Data Products'!$A:$B,2,0) | J14: =IFERROR(I14-TODAY(),"") | K14: 45504 | L14: =TODAY()-K14 | M14: 1 | N14: 1 | R14: 1200 | S14: 1200 | T14: 0 | U14: 0 | V14: 0 | W14: 0 | X14: 0 | Y14: 0 | Z14: 0 | AA14: 0 | AB14: =N14/30 | AC14: =IFERROR(F14/AB14,"-") | AD14: =IFERROR(TODAY()+AC14,"-") | AE14: =_xlfn.IFS(AC14="-","Not sold yet",AND(AC14<=150,AC14>60),"Out of stock more than 60 days",AC14<=60,"Out of stock less than 60 days",AC14>=150,"Out of stock more than 150 days") | AF14: =VLOOKUP(C14,'Data Products'!$A:$J,10,0) | AG14: =AF14*F14 | AH14: =IF(J14<=90,F14,0) | AI14: =IFERROR(VLOOKUP(C14,$C$3:$AI$42,34,0)," ")
A15: 12 | B15: Active | C15: 1DCNMCUF01530 | D15: 1DCNMCUF01530 | E15: 1ECNMCUF01530 | F15: 98 | G15: 98 | I15: =VLOOKUP(C15,'Data Products'!$A:$B,2,0) | J15: =IFERROR(I15-TODAY(),"") | K15: 45648 | L15: =TODAY()-K15 | M15: 4 | N15: 7 | R15: 1000 | S15: 1000 | T15: 0 | U15: 0 | V15: 0 | W15: 0 | X15: 0 | Y15: 0 | Z15: 0 | AA15: 0 | AB15: =N15/30 | AC15: =IFERROR(F15/AB15,"-") | AD15: =IFERROR(TODAY()+AC15,"-") | AE15: =_xlfn.IFS(AC15="-","Not sold yet",AND(AC15<=150,AC15>60),"Out of stock more than 60 days",AC15<=60,"Out of stock less than 60 days",AC15>=150,"Out of stock more than 150 days") | AF15: =VLOOKUP(C15,'Data Products'!$A:$J,10,0) | AG15: =AF15*F15 | AH15: =IF(J15<=90,F15,0) | AI15: =IFERROR(VLOOKUP(C15,$C$3:$AI$42,34,0),"")
A16: 13 | B16: Active | C16: 1DCNMCUF00303 | D16: 1DCNMCUF00303 | E16: 1ECNMCUF00303 | F16: 846 | G16: 846 | I16: =VLOOKUP(C16,'Data Products'!$A:$B,2,0) | J16: =IFERROR(I16-TODAY(),"") | K16: 45504 | L16: =TODAY()-K16 | M16: 101 | N16: 103 | R16: 500 | S16: 500 | T16: 0 | U16: 0 | V16: 0 | W16: 0 | X16: 0 | Y16: 0 | Z16: 0 | AA16: 0 | AB16: =N16/30 | AC16: =IFERROR(F16/AB16,"-") | AD16: =IFERROR(TODAY()+AC16,"-") | AE16: =_xlfn.IFS(AC16="-","Not sold yet",AND(AC16<=150,AC16>60),"Out of stock more than 60 days",AC16<=60,"Out of stock less than 60 days",AC16>=150,"Out of stock more than 150 days") | AF16: =VLOOKUP(C16,'Data Products'!$A:$J,10,0) | AG16: =AF16*F16 | AH16: =IF(J16<=90,F16,0) | AI16: =IFERROR(VLOOKUP(C16,$C$3:$AI$42,34,0),"")
A17: 14 | B17: Active | C17: 1DCNMCUF00505 | D17: 1DCNMCUF00505 | E17: 1ECNMCUF00505 | F17: 0 | G17: 0 | I17: =VLOOKUP(C17,'Data Products'!$A:$B,2,0) | J17: =IFERROR(I17-TODAY(),"") | K17: 45653 | L17: =TODAY()-K17 | M17: 0 | N17: 0 | R17: 0 | S17: 0 | T17: 128 | U17: 128 | V17: 54 | W17: 54 | X17: 0 | Y17: 0 | Z17: 0 | AA17: 0 | AB17: =N17/30 | AC17: =IFERROR(F17/AB17,"-") | AD17: =IFERROR(TODAY()+AC17,"-") | AE17: =_xlfn.IFS(AC17="-","Not sold yet",AND(AC17<=150,AC17>60),"Out of stock more than 60 days",AC17<=60,"Out of stock less than 60 days",AC17>=150,"Out of stock more than 150 days") | AF17: =VLOOKUP(C17,'Data Products'!$A:$J,10,0) | AG17: =AF17*F17 | AH17: =IF(J17<=90,F17,0) | AI17: =IFERROR(VLOOKUP(C17,$C$3:$AI$42,34,0),"")
A18: 15 | B18: Active | C18: 1DTHADTF05010 | D18: 1DTHADTF05010 | E18: 1ETHADTF05010 | F18: 5 | G18: 5 | I18: =VLOOKUP(C18,'Data Products'!$A:$B,2,0) | J18: =IFERROR(I18-TODAY(),"") | K18: 45737 | L18: =TODAY()-K18 | M18: 0 | N18: 0 | R18: 0 | S18: 0 | T18: 0 | U18: 0 | V18: 116 | W18: 116 | X18: 0 | Y18: 0 | Z18: 0 | AA18: 0 | AB18: =N18/30 | AC18: =IFERROR(F18/AB18,"-") | AD18: =IFERROR(TODAY()+AC18,"-") | AE18: =_xlfn.IFS(AC18="-","Not sold yet",AND(AC18<=150,AC18>60),"Out of stock more than 60 days",AC18<=60,"Out of stock less than 60 days",AC18>=150,"Out of stock more than 150 days") | AF18: =VLOOKUP(C18,'Data Products'!$A:$J,10,0) | AG18: =AF18*F18 | AH18: =IF(J18<=90,F18,0)
A19: 16 | B19: Active | C19: 1DWORCBF01030 | D19: 1DWORCBF01030 | E19: 1DWORCBF01030 | F19: 323 | G19: 323 | I19: =VLOOKUP(C19,'Data Products'!$A:$B,2,0) | J19: =IFERROR(I19-TODAY(),"") | K19: 45653 | L19: =TODAY()-K19 | M19: 0 | N19: 113 | R19: 600 | S19: 600 | T19: 100 | U19: 100 | V19: 300 | W19: 300 | X19: 0 | Y19: 0 | Z19: 0 | AA19: 0 | AB19: =N19/30 | AC19: =IFERROR(F19/AB19,"-") | AD19: =IFERROR(TODAY()+AC19,"-") | AE19: =_xlfn.IFS(AC19="-","Not sold yet",AND(AC19<=150,AC19>60),"Out of stock more than 60 days",AC19<=60,"Out of stock less than 60 days",AC19>=150,"Out of stock more than 150 days") | AF19: =VLOOKUP(C19,'Data Products'!$A:$J,10,0) | AG19: =AF19*F19 | AH19: =IF(J19<=90,F19,0)
A20: 17 | B20: Active | C20: 1DTHATMF01507 | D20: 1DTHATMF01507 | E20: 1ETHATMF01507 | F20: 3984 | G20: 3977 | I20: =VLOOKUP(C20,'Data Products'!$A:$B,2,0) | J20: =IFERROR(I20-TODAY(),"") | K20: 45653 | L20: =TODAY()-K20 | M20: 738 | N20: 3090 | R20: 0 | S20: 0 | T20: 27 | U20: 27 | V20: 25 | W20: 25 | X20: 0 | Y20: 0 | Z20: 0 | AA20: 0 | AB20: =N20/30 | AC20: =IFERROR(F20/AB20,"-") | AD20: =IFERROR(TODAY()+AC20,"-") | AE20: =_xlfn.IFS(AC20="-","Not sold yet",AND(AC20<=150,AC20>60),"Out of stock more than 60 days",AC20<=60,"Out of stock less than 60 days",AC20>=150,"Out of stock more than 150 days") | AF20: =VLOOKUP(C20,'Data Products'!$A:$J,10,0) | AG20: =AF20*F20 | AH20: =IF(J20<=90,F20,0) | AI20: cần đầu tháng 9 có hàng mới
A21: 18 | B21: Active | C21: 1DTHATMF05010 | D21: 1DTHATMF05010 | E21: 1ETHATMF05010 | F21: 7590 | G21: 7581 | I21: =VLOOKUP(C21,'Data Products'!$A:$B,2,0) | J21: =IFERROR(I21-TODAY(),"") | K21: 45847 | L21: =TODAY()-K21 | M21: 518 | N21: 811 | R21: 0 | S21: 0 | T21: 113 | U21: 106 | V21: 1097 | W21: 1097 | X21: 5 | Y21: 0 | Z21: 0 | AA21: 0 | AB21: =N21/30 | AC21: =IFERROR(F21/AB21,"-") | AD21: =IFERROR(TODAY()+AC21,"-") | AE21: =_xlfn.IFS(AC21="-","Not sold yet",AND(AC21<=150,AC21>60),"Out of stock more than 60 days",AC21<=60,"Out of stock less than 60 days",AC21>=150,"Out of stock more than 150 days") | AF21: =VLOOKUP(C21,'Data Products'!$A:$J,10,0) | AG21: =AF21*F21 | AH21: =IF(J21<=90,F21,0) | AI21: cần đầu tháng 9 có hàng mới
A22: 19 | B22: Active | C22: 1DTHATMF01507 | D22: 1DTHATMF01507 | E22: 1ETHATMF01507 | F22: 3984 | G22: 3977 | I22: =VLOOKUP(C22,'Data Products'!$A:$B,2,0) | J22: =IFERROR(I22-TODAY(),"") | K22: 45847 | L22: =TODAY()-K22 | M22: 738 | N22: 3090 | R22: 0 | S22: 0 | T22: 154 | U22: 154 | V22: 310 | W22: 310 | X22: 0 | Y22: 0 | Z22: 0 | AA22: 0 | AB22: =N22/30 | AC22: =IFERROR(F22/AB22,"-") | AD22: =IFERROR(TODAY()+AC22,"-") | AE22: =_xlfn.IFS(AC22="-","Not sold yet",AND(AC22<=150,AC22>60),"Out of stock more than 60 days",AC22<=60,"Out of stock less than 60 days",AC22>=150,"Out of stock more than 150 days") | AF22: =VLOOKUP(C22,'Data Products'!$A:$J,10,0) | AG22: =AF22*F22 | AH22: =IF(J22<=90,F22,0) | AI22: pass quý 1 push lại
A23: 20 | B23: Temporary | C23: CNMCU15GBFY30D | D23: CNMCU15GBFY30D | E23: CNMCU15GBFY30D | F23: 1500 | G23: 1500 | I23: =VLOOKUP(C23,'Data Products'!$A:$B,2,0) | J23: =IFERROR(I23-TODAY(),"") | K23: 45416 | L23: =TODAY()-K23 | M23: 0 | N23: 0 | AB23: =N23/30 | AC23: =IFERROR(F23/AB23,"-") | AD23: =IFERROR(TODAY()+AC23,"-") | AE23: =_xlfn.IFS(AC23="-","Not sold yet",AND(AC23<=150,AC23>60),"Out of stock more than 60 days",AC23<=60,"Out of stock less than 60 days",AC23>=150,"Out of stock more than 150 days") | AF23: =VLOOKUP(C23,'Data Products'!$A:$J,10,0) | AG23: =AF23*F23
A24: 21 | B24: Temporary | C24: CNMCU10GBFY15D | D24: CNMCU10GBFY15D | E24: CNMCU10GBFY15D | F24: 2000 | G24: 2000 | I24: =VLOOKUP(C24,'Data Products'!$A:$B,2,0) | J24: =IFERROR(I24-TODAY(),"") | K24: 45417 | L24: =TODAY()-K24 | M24: 0 | N24: 0 | AB24: =N24/30 | AC24: =IFERROR(F24/AB24,"-") | AD24: =IFERROR(TODAY()+AC24,"-") | AE24: =_xlfn.IFS(AC24="-","Not sold yet",AND(AC24<=150,AC24>60),"Out of stock more than 60 days",AC24<=60,"Out of stock less than 60 days",AC24>=150,"Out of stock more than 150 days") | AF24: =VLOOKUP(C24,'Data Products'!$A:$J,10,0) | AG24: =AF24*F24
AE25: Total stock with retail price | AF25: =AG25/$AG$25 | AG25: =SUM(AG4:AG24) | AH25: =SUM(AH4:AH24) | AI25: =SUM(AI4:AI24)
AE26: Out of stock less than 60 days | AF26: =AG26/$AG$25 | AG26: =SUMIFS($AG$4:$AG$24,$AE$4:$AE$24,$AE$26)
AE27: Not sold yet | AF27: =AG27/$AG$25 | AG27: =SUMIFS($AG$4:$AG$24,$AE$4:$AE$24,AE27)
AE28: Out of stock more than 60 days | AF28: =AG28/$AG$25 | AG28: =SUMIFS($AG$4:$AG$24,$AE$4:$AE$24,AE28)
AE29: Out of stock more than 150 days | AF29: =AG29/$AG$25 | AG29: =SUMIFS($AG$4:$AG$24,$AE$4:$AE$24,AE29)
AE30: Near Expiration Inventory | AF30: =AVERAGE(AE29:AC27)/AVERAGE(AE29:AC27) | AG30: =SUMIF($AC$4:$AC$24,"<90",AG4:AG24)
A32: ESIM VN | B32: Status | C32: SKU | D32: SKU (mới) | F32: Total Inventory | H32: Quantity | I32: Expiration | J32: Expired date left | K32: Date of Import | L32: Inventory Age | M32: Last 15 days | N32: Last 30 days | O32: Safety Stock | P32: Reorder Point | Q32: Vendor | AB32: Avg Pcs/day | AC32: DOI (Số ngày tồn kho) | AD32: Ngày hết hàng dự kiến | AE32: Đánh giá | AF32: Retail Price | AG32: Total retail price | AH32: Near Expiration Inventory | AI32: OPS | AJ32: Telco | AK32: OD | AL32: B2B | AM32: B2C | AN32: Marketing
A33: No. | F33: Stock | G33: Available for sale | M33: Sold | N33: Sold
A34: 1 | B34: Inactive | C34: 3HKDATAPOOLESIM | F34: 0 | G34: 0 | I34: =VLOOKUP(C34,'Data Products'!$A:$J,2,0) | J34: =IFERROR(I34-TODAY(),"") | K34: 45840 | L34: =TODAY()-K34 | M34: 0 | N34: 0 | Q34: 3HK | AB34: =N34/30 | AC34: =IFERROR(F34/AB34,"-") | AD34: =IFERROR(TODAY()+AC34,"-") | AE34: =_xlfn.IFS(AC34="-","Not sold yet",AND(AC34<=150,AC34>60),"Out of stock more than 60 days",AC34<=60,"Out of stock less than 60 days",AC34>=150,"Out of stock more than 150 days") | AF34: =VLOOKUP(C34,'Data Products'!$A:$J,10,0) | AG34: =AF34*F34 | AI34: treo chờ xử lý sau
A35: 2 | B35: Inactive | C35: EEURBGFX15GB15D | F35: 0 | G35: 0 | I35: =VLOOKUP(C35,'Data Products'!$A:$J,2,0) | J35: =IFERROR(I35-TODAY(),"") | K35: 45841 | L35: =TODAY()-K35 | M35: 0 | N35: 0 | Q35: Bouygues | AB35: =N35/30 | AC35: =IFERROR(F35/AB35,"-") | AD35: =IFERROR(TODAY()+AC35,"-") | AE35: =_xlfn.IFS(AC35="-","Not sold yet",AND(AC35<=150,AC35>60),"Out of stock more than 60 days",AC35<=60,"Out of stock less than 60 days",AC35>=150,"Out of stock more than 150 days") | AF35: =VLOOKUP(C35,'Data Products'!$A:$J,10,0) | AG35: =AF35*F35 | AH35: =IF(J35<=90,F35,0)
A36: 3 | B36: Inactive | C36: EEURBGFX20GB15D | F36: 0 | G36: 0 | I36: =VLOOKUP(C36,'Data Products'!$A:$J,2,0) | J36: =IFERROR(I36-TODAY(),"") | K36: 45842 | L36: =TODAY()-K36 | M36: 0 | N36: 0 | Q36: Bouygues | AB36: =N36/30 | AC36: =IFERROR(F36/AB36,"-") | AD36: =IFERROR(TODAY()+AC36,"-") | AE36: =_xlfn.IFS(AC36="-","Not sold yet",AND(AC36<=150,AC36>60),"Out of stock more than 60 days",AC36<=60,"Out of stock less than 60 days",AC36>=150,"Out of stock more than 150 days") | AF36: =VLOOKUP(C36,'Data Products'!$A:$J,10,0) | AG36: =AF36*F36 | AH36: =IF(J36<=90,F36,0)
A37: 4 | B37: Inactive | C37: EEURBGFX30GB30D | F37: 0 | G37: 0 | I37: =VLOOKUP(C37,'Data Products'!$A:$J,2,0) | J37: =IFERROR(I37-TODAY(),"") | K37: 45843 | L37: =TODAY()-K37 | M37: 0 | N37: 0 | Q37: Bouygues | AB37: =N37/30 | AC37: =IFERROR(F37/AB37,"-") | AD37: =IFERROR(TODAY()+AC37,"-") | AE37: =_xlfn.IFS(AC37="-","Not sold yet",AND(AC37<=150,AC37>60),"Out of stock more than 60 days",AC37<=60,"Out of stock less than 60 days",AC37>=150,"Out of stock more than 150 days") | AF37: =VLOOKUP(C37,'Data Products'!$A:$J,10,0) | AG37: =AF37*F37 | AH37: =IF(J37<=90,F37,0)
A38: 5 | B38: Deleted | C38: ECMTCUFY05GB05D | F38: 0 | G38: 0 | I38: =VLOOKUP(C38,'Data Products'!$A:$J,2,0) | J38: =IFERROR(I38-TODAY(),"") | K38: 45844 | L38: =TODAY()-K38 | M38: 0 | N38: 0 | Q38: CU | AB38: =N38/30 | AC38: =IFERROR(F38/AB38,"-") | AD38: =IFERROR(TODAY()+AC38,"-") | AE38: =_xlfn.IFS(AC38="-","Not sold yet",AND(AC38<=150,AC38>60),"Out of stock more than 60 days",AC38<=60,"Out of stock less than 60 days",AC38>=150,"Out of stock more than 150 days") | AF38: =VLOOKUP(C38,'Data Products'!$A:$J,10,0) | AG38: =AF38*F38 | AH38: =IF(J38<=90,F38,0) | AK38: 200
A39: 6 | B39: Temporary | C39: ECNMCUFX15GB30D | D39: 1CCNMCUY01530 | F39: 0 | G39: 0 | I39: =VLOOKUP(C39,'Data Products'!$A:$J,2,0) | J39: =IFERROR(I39-TODAY(),"") | K39: 45845 | L39: =TODAY()-K39 | M39: 0 | N39: 0 | Q39: CU | AB39: =N39/30 | AC39: =IFERROR(F39/AB39,"-") | AD39: =IFERROR(TODAY()+AC39,"-") | AE39: =_xlfn.IFS(AC39="-","Not sold yet",AND(AC39<=150,AC39>60),"Out of stock more than 60 days",AC39<=60,"Out of stock less than 60 days",AC39>=150,"Out of stock more than 150 days") | AF39: =VLOOKUP(C39,'Data Products'!$A:$J,10,0) | AG39: =AF39*F39 | AH39: =IF(J39<=90,F39,0)
A40: 7 | B40: Temporary | C40: 1CKORCUF01005 | D40: 1CKORCUF01005 | F40: 0 | G40: 0 | I40: =VLOOKUP(C40,'Data Products'!$A:$J,2,0) | J40: =IFERROR(I40-TODAY(),"") | K40: 45846 | L40: =TODAY()-K40 | M40: 0 | N40: 0 | Q40: CU | AB40: =N40/30 | AC40: =IFERROR(F40/AB40,"-") | AD40: =IFERROR(TODAY()+AC40,"-") | AE40: =_xlfn.IFS(AC40="-","Not sold yet",AND(AC40<=150,AC40>60),"Out of stock more than 60 days",AC40<=60,"Out of stock less than 60 days",AC40>=150,"Out of stock more than 150 days") | AF40: =VLOOKUP(C40,'Data Products'!$A:$J,10,0) | AG40: =AF40*F40 | AH40: =IF(J40<=90,F40,0)
A41: 8 | B41: Temporary | C41: EKORCUFY30GB30D | F41: 0 | G41: 0 | I41: =VLOOKUP(C41,'Data Products'!$A:$J,2,0) | J41: =IFERROR(I41-TODAY(),"") | K41: 45847 | L41: =TODAY()-K41 | M41: 0 | N41: 0 | Q41: CU | AB41: =N41/30 | AC41: =IFERROR(F41/AB41,"-") | AD41: =IFERROR(TODAY()+AC41,"-") | AE41: =_xlfn.IFS(AC41="-","Not sold yet",AND(AC41<=150,AC41>60),"Out of stock more than 60 days",AC41<=60,"Out of stock less than 60 days",AC41>=150,"Out of stock more than 150 days") | AF41: =VLOOKUP(C41,'Data Products'!$A:$J,10,0) | AG41: =AF41*F41 | AH41: =IF(J41<=90,F41,0)
A42: 9 | B42: Temporary | C42: EA10CUFY05GB08D | F42: 0 | G42: 0 | I42: =VLOOKUP(C42,'Data Products'!$A:$J,2,0) | J42: =IFERROR(I42-TODAY(),"") | K42: 45848 | L42: =TODAY()-K42 | M42: 0 | N42: 0 | Q42: CU | AB42: =N42/30 | AC42: =IFERROR(F42/AB42,"-") | AD42: =IFERROR(TODAY()+AC42,"-") | AE42: =_xlfn.IFS(AC42="-","Not sold yet",AND(AC42<=150,AC42>60),"Out of stock more than 60 days",AC42<=60,"Out of stock less than 60 days",AC42>=150,"Out of stock more than 150 days") | AF42: =VLOOKUP(C42,'Data Products'!$A:$J,10,0) | AG42: =AF42*F42 | AH42: =IF(J42<=90,F42,0)
A43: 10 | B43: Temporary | C43: ECMTCUFY07GB08D | F43: 0 | G43: 0 | I43: =VLOOKUP(C43,'Data Products'!$A:$J,2,0) | J43: =IFERROR(I43-TODAY(),"") | K43: 45849 | L43: =TODAY()-K43 | M43: 0 | N43: 0 | Q43: CU | AB43: =N43/30 | AC43: =IFERROR(F43/AB43,"-") | AD43: =IFERROR(TODAY()+AC43,"-") | AE43: =_xlfn.IFS(AC43="-","Not sold yet",AND(AC43<=150,AC43>60),"Out of stock more than 60 days",AC43<=60,"Out of stock less than 60 days",AC43>=150,"Out of stock more than 150 days") | AF43: =VLOOKUP(C43,'Data Products'!$A:$J,10,0) | AG43: =AF43*F43 | AH43: =IF(J43<=90,F43,0) | AK43: 150
A44: 11 | B44: Inactive | C44: ECNMCUFY05GB05D | F44: 0 | G44: 0 | I44: =VLOOKUP(C44,'Data Products'!$A:$J,2,0) | J44: =IFERROR(I44-TODAY(),"") | K44: 45850 | L44: =TODAY()-K44 | M44: 0 | N44: 0 | Q44: CU | AB44: =N44/30 | AC44: =IFERROR(F44/AB44,"-") | AD44: =IFERROR(TODAY()+AC44,"-") | AE44: =_xlfn.IFS(AC44="-","Not sold yet",AND(AC44<=150,AC44>60),"Out of stock more than 60 days",AC44<=60,"Out of stock less than 60 days",AC44>=150,"Out of stock more than 150 days") | AF44: =VLOOKUP(C44,'Data Products'!$A:$J,10,0) | AG44: =AF44*F44 | AH44: =IF(J44<=90,F44,0)
A45: 12 | B45: Temporary | C45: ECNMCUFY07GB08D | D45: 1CCNMCUF00708 | F45: 0 | G45: 0 | I45: =VLOOKUP(C45,'Data Products'!$A:$J,2,0) | J45: =IFERROR(I45-TODAY(),"") | K45: 45851 | L45: =TODAY()-K45 | M45: 0 | N45: 0 | Q45: CU | AB45: =N45/30 | AC45: =IFERROR(F45/AB45,"-") | AD45: =IFERROR(TODAY()+AC45,"-") | AE45: =_xlfn.IFS(AC45="-","Not sold yet",AND(AC45<=150,AC45>60),"Out of stock more than 60 days",AC45<=60,"Out of stock less than 60 days",AC45>=150,"Out of stock more than 150 days") | AF45: =VLOOKUP(C45,'Data Products'!$A:$J,10,0) | AG45: =AF45*F45 | AH45: =IF(J45<=90,F45,0)
A46: 13 | B46: Temporary | C46: EARECUFY04GB30D | F46: 0 | G46: 0 | I46: =VLOOKUP(C46,'Data Products'!$A:$J,2,0) | J46: =IFERROR(I46-TODAY(),"") | K46: 45852 | L46: =TODAY()-K46 | M46: 0 | N46: 0 | Q46: CU | AB46: =N46/30 | AC46: =IFERROR(F46/AB46,"-") | AD46: =IFERROR(TODAY()+AC46,"-") | AE46: =_xlfn.IFS(AC46="-","Not sold yet",AND(AC46<=150,AC46>60),"Out of stock more than 60 days",AC46<=60,"Out of stock less than 60 days",AC46>=150,"Out of stock more than 150 days") | AF46: =VLOOKUP(C46,'Data Products'!$A:$J,10,0) | AG46: =AF46*F46 | AH46: =IF(J46<=90,F46,0)
A47: 14 | B47: Inactive | C47: EKORCUFY20GB08D | D47: 1CKORCUF02008 | F47: 0 | G47: 0 | I47: =VLOOKUP(C47,'Data Products'!$A:$J,2,0) | J47: =IFERROR(I47-TODAY(),"") | K47: 45853 | L47: =TODAY()-K47 | M47: 0 | N47: 0 | Q47: CU | AB47: =N47/30 | AC47: =IFERROR(F47/AB47,"-") | AD47: =IFERROR(TODAY()+AC47,"-") | AE47: =_xlfn.IFS(AC47="-","Not sold yet",AND(AC47<=150,AC47>60),"Out of stock more than 60 days",AC47<=60,"Out of stock less than 60 days",AC47>=150,"Out of stock more than 150 days") | AF47: =VLOOKUP(C47,'Data Products'!$A:$J,10,0) | AG47: =AF47*F47 | AH47: =IF(J47<=90,F47,0)
A48: 15 | B48: Inactive | C48: ECNMCUFX10GB15D | F48: 0 | G48: 0 | I48: =VLOOKUP(C48,'Data Products'!$A:$J,2,0) | J48: =IFERROR(I48-TODAY(),"") | K48: 45854 | L48: =TODAY()-K48 | M48: 0 | N48: 0 | Q48: CU | AB48: =N48/30 | AC48: =IFERROR(F48/AB48,"-") | AD48: =IFERROR(TODAY()+AC48,"-") | AE48: =_xlfn.IFS(AC48="-","Not sold yet",AND(AC48<=150,AC48>60),"Out of stock more than 60 days",AC48<=60,"Out of stock less than 60 days",AC48>=150,"Out of stock more than 150 days") | AF48: =VLOOKUP(C48,'Data Products'!$A:$J,10,0) | AG48: =AF48*F48 | AH48: =IF(J48<=90,F48,0) | AK48: 340
A49: 16 | B49: Inactive | C49: ETHDD1FY50GB10D | F49: 0 | G49: 0 | I49: =VLOOKUP(C49,'Data Products'!$A:$J,2,0) | J49: =IFERROR(I49-TODAY(),"") | K49: 45855 | L49: =TODAY()-K49 | M49: 0 | N49: 0 | Q49: Dtac | AB49: =N49/30 | AC49: =IFERROR(F49/AB49,"-") | AD49: =IFERROR(TODAY()+AC49,"-") | AE49: =_xlfn.IFS(AC49="-","Not sold yet",AND(AC49<=150,AC49>60),"Out of stock more than 60 days",AC49<=60,"Out of stock less than 60 days",AC49>=150,"Out of stock more than 150 days") | AF49: =VLOOKUP(C49,'Data Products'!$A:$J,10,0) | AG49: =AF49*F49 | AH49: =IF(J49<=90,F49,0)
A50: 17 | B50: Inactive | C50: ETHDDTFY50GB10D | F50: 0 | G50: 0 | I50: =VLOOKUP(C50,'Data Products'!$A:$J,2,0) | J50: =IFERROR(I50-TODAY(),"") | K50: 45856 | L50: =TODAY()-K50 | M50: 0 | N50: 0 | Q50: Dtac | AB50: =N50/30 | AC50: =IFERROR(F50/AB50,"-") | AD50: =IFERROR(TODAY()+AC50,"-") | AE50: =_xlfn.IFS(AC50="-","Not sold yet",AND(AC50<=150,AC50>60),"Out of stock more than 60 days",AC50<=60,"Out of stock less than 60 days",AC50>=150,"Out of stock more than 150 days") | AF50: =VLOOKUP(C50,'Data Products'!$A:$J,10,0) | AG50: =AF50*F50 | AH50: =IF(J50<=90,F50,0) | AK50: 3620
A51: 18 | B51: Inactive | C51: ETHDDTFY15GB07D | F51: 0 | G51: 0 | I51: =VLOOKUP(C51,'Data Products'!$A:$J,2,0) | J51: =IFERROR(I51-TODAY(),"") | K51: 45857 | L51: =TODAY()-K51 | M51: 0 | N51: 0 | Q51: Dtac | AB51: =N51/30 | AC51: =IFERROR(F51/AB51,"-") | AD51: =IFERROR(TODAY()+AC51,"-") | AE51: =_xlfn.IFS(AC51="-","Not sold yet",AND(AC51<=150,AC51>60),"Out of stock more than 60 days",AC51<=60,"Out of stock less than 60 days",AC51>=150,"Out of stock more than 150 days") | AF51: =VLOOKUP(C51,'Data Products'!$A:$J,10,0) | AG51: =AF51*F51 | AH51: =IF(J51<=90,F51,0)
A52: 19 | B52: Active | C52: ETHATMFY50GB10D | D52: 1CTHATMF05010 | E52: 1CTHATMF05010 | F52: 0 | G52: 0 | I52: =VLOOKUP(C52,'Data Products'!$A:$J,2,0) | J52: =IFERROR(I52-TODAY(),"") | K52: 45858 | L52: =TODAY()-K52 | M52: 0 | N52: 0 | Q52: TrueMove | AB52: =N52/30 | AC52: =IFERROR(F52/AB52,"-") | AD52: =IFERROR(TODAY()+AC52,"-") | AE52: =_xlfn.IFS(AC52="-","Not sold yet",AND(AC52<=150,AC52>60),"Out of stock more than 60 days",AC52<=60,"Out of stock less than 60 days",AC52>=150,"Out of stock more than 150 days") | AF52: =VLOOKUP(C52,'Data Products'!$A:$J,10,0) | AG52: =AF52*F52 | AH52: =IF(J52<=90,F52,0) | AI52: mốt có hàng của CB nhé
A53: 20 | B53: Inactive | C53: ETHATMFY15GB07D | D53: 1CTHATMF01507 | E53: 1CTHATMF01507 | F53: 8 | G53: 8 | I53: =VLOOKUP(C53,'Data Products'!$A:$J,2,0) | J53: =IFERROR(I53-TODAY(),"") | K53: 45859 | L53: =TODAY()-K53 | M53: 0 | N53: 0 | Q53: TrueMove | AB53: =N53/30 | AC53: =IFERROR(F53/AB53,"-") | AD53: =IFERROR(TODAY()+AC53,"-") | AE53: =_xlfn.IFS(AC53="-","Not sold yet",AND(AC53<=150,AC53>60),"Out of stock more than 60 days",AC53<=60,"Out of stock less than 60 days",AC53>=150,"Out of stock more than 150 days") | AF53: =VLOOKUP(C53,'Data Products'!$A:$J,10,0) | AG53: =AF53*F53 | AH53: =IF(J53<=90,F53,0) | AI53: dự kiến cuối tháng 4 có hàng
A54: 21 | B54: Inactive | C54: ETHDCBFY50GB10D | D54: 2CTHACBF05010 | E54: 2CTHACBF05010 | F54: 0 | G54: 0 | I54: =VLOOKUP(C54,'Data Products'!$A:$J,2,0) | J54: =IFERROR(I54-TODAY(),"") | K54: 45860 | L54: =TODAY()-K54 | M54: 0 | N54: 0 | Q54: Commbitz | AB54: =N54/30 | AC54: =IFERROR(F54/AB54,"-") | AD54: =IFERROR(TODAY()+AC54,"-") | AE54: =_xlfn.IFS(AC54="-","Not sold yet",AND(AC54<=150,AC54>60),"Out of stock more than 60 days",AC54<=60,"Out of stock less than 60 days",AC54>=150,"Out of stock more than 150 days") | AF54: =VLOOKUP(C54,'Data Products'!$A:$J,10,0) | AG54: =AF54*F54 | AH54: =IF(J54<=90,F54,0)
A55: 22 | B55: Temporary | C55: 2CTHACBF05010 | D55: 2CTHACBF05010 | E55: 2CTHACBF05010 | F55: 2 | G55: 2 | I55: =VLOOKUP(C55,'Data Products'!$A:$J,2,0) | J55: =IFERROR(I55-TODAY(),"") | K55: 45861 | L55: =TODAY()-K55 | M55: 0 | N55: 0 | Q55: Commbitzz | AB55: =N55/30 | AC55: =IFERROR(F55/AB55,"-") | AD55: =IFERROR(TODAY()+AC55,"-") | AE55: =_xlfn.IFS(AC55="-","Not sold yet",AND(AC55<=150,AC55>60),"Out of stock more than 60 days",AC55<=60,"Out of stock less than 60 days",AC55>=150,"Out of stock more than 150 days") | AF55: =VLOOKUP(C55,'Data Products'!$A:$J,10,0) | AG55: =AF55*F55 | AI55: bán hết sẽ clear tồn
A56: 23 | B56: Inactive | C56: ETHDYDFY50GB10D | F56: 0 | G56: 0 | I56: =VLOOKUP(C56,'Data Products'!$A:$J,2,0) | J56: =IFERROR(I56-TODAY(),"") | K56: 45862 | L56: =TODAY()-K56 | M56: 0 | N56: 0 | Q56: YiDao | AB56: =N56/30 | AC56: =IFERROR(F56/AB56,"-") | AD56: =IFERROR(TODAY()+AC56,"-") | AE56: =_xlfn.IFS(AC56="-","Not sold yet",AND(AC56<=150,AC56>60),"Out of stock more than 60 days",AC56<=60,"Out of stock less than 60 days",AC56>=150,"Out of stock more than 150 days") | AF56: =VLOOKUP(C56,'Data Products'!$A:$J,10,0) | AG56: =AF56*F56 | AH56: =IF(J56<=90,F56,0)
A57: 24 | B57: Inactive | C57: ESGP3HFY15GB30D | F57: 0 | G57: 0 | I57: =VLOOKUP(C57,'Data Products'!$A:$J,2,0) | J57: =IFERROR(I57-TODAY(),"") | K57: 45863 | L57: =TODAY()-K57 | M57: 0 | N57: 0 | Q57: 3HK | AB57: =N57/30 | AC57: =IFERROR(F57/AB57,"-") | AD57: =IFERROR(TODAY()+AC57,"-") | AE57: =_xlfn.IFS(AC57="-","Not sold yet",AND(AC57<=150,AC57>60),"Out of stock more than 60 days",AC57<=60,"Out of stock less than 60 days",AC57>=150,"Out of stock more than 150 days") | AF57: =VLOOKUP(C57,'Data Products'!$A:$J,10,0) | AG57: =AF57*F57 | AH57: =IF(J57<=90,F57,0)
A58: 25 | B58: Inactive | C58: ESGP3HFY30GB30D | F58: 0 | G58: 0 | I58: =VLOOKUP(C58,'Data Products'!$A:$J,2,0) | J58: =IFERROR(I58-TODAY(),"") | K58: 45864 | L58: =TODAY()-K58 | M58: 0 | N58: 0 | Q58: 3HK | AB58: =N58/30 | AC58: =IFERROR(F58/AB58,"-") | AD58: =IFERROR(TODAY()+AC58,"-") | AE58: =_xlfn.IFS(AC58="-","Not sold yet",AND(AC58<=150,AC58>60),"Out of stock more than 60 days",AC58<=60,"Out of stock less than 60 days",AC58>=150,"Out of stock more than 150 days") | AF58: =VLOOKUP(C58,'Data Products'!$A:$J,10,0) | AG58: =AF58*F58 | AH58: =IF(J58<=90,F58,0)
A59: 26 | B59: Inactive | C59: EJPNKDPYUNLI04D | F59: 0 | G59: 0 | H59: 200 HSD 21/06/2025 300 HSD 20/08/2025 | I59: =VLOOKUP(C59,'Data Products'!$A:$J,2,0) | J59: =IFERROR(I59-TODAY(),"") | K59: 45865 | L59: =TODAY()-K59 | M59: 0 | N59: 0 | Q59: KDDI | AB59: =N59/30 | AC59: =IFERROR(F59/AB59,"-") | AD59: =IFERROR(TODAY()+AC59,"-") | AE59: =_xlfn.IFS(AC59="-","Not sold yet",AND(AC59<=150,AC59>60),"Out of stock more than 60 days",AC59<=60,"Out of stock less than 60 days",AC59>=150,"Out of stock more than 150 days") | AF59: =VLOOKUP(C59,'Data Products'!$A:$J,10,0) | AG59: =AF59*F59 | AH59: =IF(J59<=90,F59,0) | AK59: 50
A60: 27 | B60: Inactive | C60: EJPNKDPYUNLI07D | F60: 0 | G60: 0 | I60: =VLOOKUP(C60,'Data Products'!$A:$J,2,0) | J60: =IFERROR(I60-TODAY(),"") | K60: 45866 | L60: =TODAY()-K60 | M60: 0 | N60: 0 | Q60: KDDI | AB60: =N60/30 | AC60: =IFERROR(F60/AB60,"-") | AD60: =IFERROR(TODAY()+AC60,"-") | AE60: =_xlfn.IFS(AC60="-","Not sold yet",AND(AC60<=150,AC60>60),"Out of stock more than 60 days",AC60<=60,"Out of stock less than 60 days",AC60>=150,"Out of stock more than 150 days") | AF60: =VLOOKUP(C60,'Data Products'!$A:$J,10,0) | AG60: =AF60*F60 | AH60: =IF(J60<=90,F60,0) | AK60: 80
A61: 28 | B61: Inactive | C61: EJPNKDPYUNLI10D | F61: 0 | G61: 0 | I61: =VLOOKUP(C61,'Data Products'!$A:$J,2,0) | J61: =IFERROR(I61-TODAY(),"") | K61: 45867 | L61: =TODAY()-K61 | M61: 0 | N61: 0 | Q61: KDDI | AB61: =N61/30 | AC61: =IFERROR(F61/AB61,"-") | AD61: =IFERROR(TODAY()+AC61,"-") | AE61: =_xlfn.IFS(AC61="-","Not sold yet",AND(AC61<=150,AC61>60),"Out of stock more than 60 days",AC61<=60,"Out of stock less than 60 days",AC61>=150,"Out of stock more than 150 days") | AF61: =VLOOKUP(C61,'Data Products'!$A:$J,10,0) | AG61: =AF61*F61 | AH61: =IF(J61<=90,F61,0) | AK61: 60
A62: 29 | B62: Inactive | C62: EJPNKDFY20GB07D | F62: 0 | G62: 0 | H62: 100 HSD 20/08/2025 | I62: =VLOOKUP(C62,'Data Products'!$A:$J,2,0) | J62: =IFERROR(I62-TODAY(),"") | K62: 45868 | L62: =TODAY()-K62 | M62: 0 | N62: 0 | Q62: KDDI | AB62: =N62/30 | AC62: =IFERROR(F62/AB62,"-") | AD62: =IFERROR(TODAY()+AC62,"-") | AE62: =_xlfn.IFS(AC62="-","Not sold yet",AND(AC62<=150,AC62>60),"Out of stock more than 60 days",AC62<=60,"Out of stock less than 60 days",AC62>=150,"Out of stock more than 150 days") | AF62: =VLOOKUP(C62,'Data Products'!$A:$J,10,0) | AG62: =AF62*F62 | AH62: =IF(J62<=90,F62,0) | AK62: 40
A63: 30 | B63: Inactive | C63: EJPNK1PYUNLI07D | F63: 0 | G63: 0 | I63: =VLOOKUP(C63,'Data Products'!$A:$J,2,0) | J63: =IFERROR(I63-TODAY(),"") | K63: 45869 | L63: =TODAY()-K63 | M63: 0 | N63: 0 | Q63: KDDI | AB63: =N63/30 | AC63: =IFERROR(F63/AB63,"-") | AD63: =IFERROR(TODAY()+AC63,"-") | AE63: =_xlfn.IFS(AC63="-","Not sold yet",AND(AC63<=150,AC63>60),"Out of stock more than 60 days",AC63<=60,"Out of stock less than 60 days",AC63>=150,"Out of stock more than 150 days") | AF63: =VLOOKUP(C63,'Data Products'!$A:$J,10,0) | AG63: =AF63*F63 | AH63: =IF(J63<=90,F63,0)
A64: 31 | B64: Inactive | C64: EJPNKDPYUNLI15D | F64: 0 | G64: 0 | I64: =VLOOKUP(C64,'Data Products'!$A:$J,2,0) | J64: =IFERROR(I64-TODAY(),"") | K64: 45870 | L64: =TODAY()-K64 | M64: 0 | N64: 0 | Q64: KDDI | AB64: =N64/30 | AC64: =IFERROR(F64/AB64,"-") | AD64: =IFERROR(TODAY()+AC64,"-") | AE64: =_xlfn.IFS(AC64="-","Not sold yet",AND(AC64<=150,AC64>60),"Out of stock more than 60 days",AC64<=60,"Out of stock less than 60 days",AC64>=150,"Out of stock more than 150 days") | AF64: =VLOOKUP(C64,'Data Products'!$A:$J,10,0) | AG64: =AF64*F64 | AH64: =IF(J64<=90,F64,0)
A65: 32 | B65: Inactive | C65: EKORSBPXUNLI05D | F65: 0 | G65: 0 | I65: =VLOOKUP(C65,'Data Products'!$A:$J,2,0) | J65: =IFERROR(I65-TODAY(),"") | K65: 45871 | L65: =TODAY()-K65 | M65: 0 | N65: 0 | Q65: Softbay | AB65: =N65/30 | AC65: =IFERROR(F65/AB65,"-") | AD65: =IFERROR(TODAY()+AC65,"-") | AE65: =_xlfn.IFS(AC65="-","Not sold yet",AND(AC65<=150,AC65>60),"Out of stock more than 60 days",AC65<=60,"Out of stock less than 60 days",AC65>=150,"Out of stock more than 150 days") | AF65: =VLOOKUP(C65,'Data Products'!$A:$J,10,0) | AG65: =AF65*F65 | AH65: =IF(J65<=90,F65,0)
A66: 33 | B66: Inactive | C66: EKORSBPXUNLI07D | F66: 0 | G66: 0 | I66: =VLOOKUP(C66,'Data Products'!$A:$J,2,0) | J66: =IFERROR(I66-TODAY(),"") | K66: 45872 | L66: =TODAY()-K66 | M66: 0 | N66: 0 | Q66: Softbay | AB66: =N66/30 | AC66: =IFERROR(F66/AB66,"-") | AD66: =IFERROR(TODAY()+AC66,"-") | AE66: =_xlfn.IFS(AC66="-","Not sold yet",AND(AC66<=150,AC66>60),"Out of stock more than 60 days",AC66<=60,"Out of stock less than 60 days",AC66>=150,"Out of stock more than 150 days") | AF66: =VLOOKUP(C66,'Data Products'!$A:$J,10,0) | AG66: =AF66*F66 | AH66: =IF(J66<=90,F66,0)
A67: 34 | B67: Inactive | C67: EKORSBPXUNLI10D | F67: 0 | G67: 0 | I67: =VLOOKUP(C67,'Data Products'!$A:$J,2,0) | J67: =IFERROR(I67-TODAY(),"") | K67: 45873 | L67: =TODAY()-K67 | M67: 0 | N67: 0 | Q67: Softbay | AB67: =N67/30 | AC67: =IFERROR(F67/AB67,"-") | AD67: =IFERROR(TODAY()+AC67,"-") | AE67: =_xlfn.IFS(AC67="-","Not sold yet",AND(AC67<=150,AC67>60),"Out of stock more than 60 days",AC67<=60,"Out of stock less than 60 days",AC67>=150,"Out of stock more than 150 days") | AF67: =VLOOKUP(C67,'Data Products'!$A:$J,10,0) | AG67: =AF67*F67 | AH67: =IF(J67<=90,F67,0)
A68: 35 | B68: Active | C68: EVNMVMPX02GB20D | D68: 11VNMVMZ00220 | E68: 11VNMVMZ00220 | F68: 0 | G68: 0 | I68: =VLOOKUP(C68,'Data Products'!$A:$J,2,0) | J68: =IFERROR(I68-TODAY(),"") | K68: 45874 | L68: =TODAY()-K68 | M68: 0 | N68: 0 | Q68: VietnamMobile | AB68: =N68/30 | AC68: =IFERROR(F68/AB68,"-") | AD68: =IFERROR(TODAY()+AC68,"-") | AE68: =_xlfn.IFS(AC68="-","Not sold yet",AND(AC68<=150,AC68>60),"Out of stock more than 60 days",AC68<=60,"Out of stock less than 60 days",AC68>=150,"Out of stock more than 150 days") | AF68: =VLOOKUP(C68,'Data Products'!$A:$J,10,0) | AG68: =AF68*F68 | AH68: =IF(J68<=90,F68,0) | AK68: 50
A69: 36 | B69: Deleted | C69: EUSAVMFY05GB03D | F69: 0 | G69: 0 | I69: =VLOOKUP(C69,'Data Products'!$A:$J,2,0) | J69: =IFERROR(I69-TODAY(),"") | K69: 45875 | L69: =TODAY()-K69 | M69: 0 | N69: 0 | Q69: VietnamMobile | AB69: =N69/30 | AC69: =IFERROR(F69/AB69,"-") | AD69: =IFERROR(TODAY()+AC69,"-") | AE69: =_xlfn.IFS(AC69="-","Not sold yet",AND(AC69<=150,AC69>60),"Out of stock more than 60 days",AC69<=60,"Out of stock less than 60 days",AC69>=150,"Out of stock more than 150 days") | AF69: =VLOOKUP(C69,'Data Products'!$A:$J,10,0) | AG69: =AF69*F69 | AH69: =IF(J69<=90,F69,0)
A70: 37 | B70: Deleted | C70: EUSAVMFY60GB30D | F70: 0 | G70: 0 | I70: =VLOOKUP(C70,'Data Products'!$A:$J,2,0) | J70: =IFERROR(I70-TODAY(),"") | K70: 45876 | L70: =TODAY()-K70 | M70: 0 | N70: 0 | Q70: VietnamMobile | AB70: =N70/30 | AC70: =IFERROR(F70/AB70,"-") | AD70: =IFERROR(TODAY()+AC70,"-") | AE70: =_xlfn.IFS(AC70="-","Not sold yet",AND(AC70<=150,AC70>60),"Out of stock more than 60 days",AC70<=60,"Out of stock less than 60 days",AC70>=150,"Out of stock more than 150 days") | AF70: =VLOOKUP(C70,'Data Products'!$A:$J,10,0) | AG70: =AF70*F70 | AH70: =IF(J70<=90,F70,0)
A71: 38 | B71: Deleted | C71: EUSAVMFY10GB15D | F71: 0 | G71: 0 | I71: =VLOOKUP(C71,'Data Products'!$A:$J,2,0) | J71: =IFERROR(I71-TODAY(),"") | K71: 45877 | L71: =TODAY()-K71 | M71: 0 | N71: 0 | Q71: VietnamMobile | AB71: =N71/30 | AC71: =IFERROR(F71/AB71,"-") | AD71: =IFERROR(TODAY()+AC71,"-") | AE71: =_xlfn.IFS(AC71="-","Not sold yet",AND(AC71<=150,AC71>60),"Out of stock more than 60 days",AC71<=60,"Out of stock less than 60 days",AC71>=150,"Out of stock more than 150 days") | AF71: =VLOOKUP(C71,'Data Products'!$A:$J,10,0) | AG71: =AF71*F71 | AH71: =IF(J71<=90,F71,0)
A72: 39 | B72: Active | C72: EVNMSFPY03GB15D | D72: 11VNMSFP00315 | E72: 11VNMSFP00315 | F72: 0 | G72: 0 | I72: =VLOOKUP(C72,'Data Products'!$A:$J,2,0) | J72: =IFERROR(I72-TODAY(),"") | K72: 45878 | L72: =TODAY()-K72 | M72: 0 | N72: 0 | Q72: Skyfi | AB72: =N72/30 | AC72: =IFERROR(F72/AB72,"-") | AD72: =IFERROR(TODAY()+AC72,"-") | AE72: =_xlfn.IFS(AC72="-","Not sold yet",AND(AC72<=150,AC72>60),"Out of stock more than 60 days",AC72<=60,"Out of stock less than 60 days",AC72>=150,"Out of stock more than 150 days") | AF72: =VLOOKUP(C72,'Data Products'!$A:$J,10,0) | AG72: =AF72*F72
A73: 40 | B73: Inactive | C73: EVNMMBPX03GB07D | F73: 0 | G73: 0 | I73: =VLOOKUP(C73,'Data Products'!$A:$J,2,0) | J73: =IFERROR(I73-TODAY(),"") | K73: 45879 | L73: =TODAY()-K73 | M73: 0 | N73: 0 | Q73: Mobifone | AB73: =N73/30 | AC73: =IFERROR(F73/AB73,"-") | AD73: =IFERROR(TODAY()+AC73,"-") | AE73: =_xlfn.IFS(AC73="-","Not sold yet",AND(AC73<=150,AC73>60),"Out of stock more than 60 days",AC73<=60,"Out of stock less than 60 days",AC73>=150,"Out of stock more than 150 days") | AF73: =VLOOKUP(C73,'Data Products'!$A:$J,10,0) | AG73: =AF73*F73 | AH73: =IF(J73<=90,F73,0)
A74: 41 | B74: Inactive | C74: EVNMMBPX04GB15D | F74: 0 | G74: 0 | I74: =VLOOKUP(C74,'Data Products'!$A:$J,2,0) | J74: =IFERROR(I74-TODAY(),"") | K74: 45880 | L74: =TODAY()-K74 | M74: 0 | N74: 0 | Q74: Mobifone | AB74: =N74/30 | AC74: =IFERROR(F74/AB74,"-") | AD74: =IFERROR(TODAY()+AC74,"-") | AE74: =_xlfn.IFS(AC74="-","Not sold yet",AND(AC74<=150,AC74>60),"Out of stock more than 60 days",AC74<=60,"Out of stock less than 60 days",AC74>=150,"Out of stock more than 150 days") | AF74: =VLOOKUP(C74,'Data Products'!$A:$J,10,0) | AG74: =AF74*F74 | AH74: =IF(J74<=90,F74,0)
A75: 42 | B75: Inactive | C75: EVNMMBPX05GB15D | F75: 0 | G75: 0 | I75: =VLOOKUP(C75,'Data Products'!$A:$J,2,0) | J75: =IFERROR(I75-TODAY(),"") | K75: 45881 | L75: =TODAY()-K75 | M75: 0 | N75: 0 | Q75: Mobifone | AB75: =N75/30 | AC75: =IFERROR(F75/AB75,"-") | AD75: =IFERROR(TODAY()+AC75,"-") | AE75: =_xlfn.IFS(AC75="-","Not sold yet",AND(AC75<=150,AC75>60),"Out of stock more than 60 days",AC75<=60,"Out of stock less than 60 days",AC75>=150,"Out of stock more than 150 days") | AF75: =VLOOKUP(C75,'Data Products'!$A:$J,10,0) | AG75: =AF75*F75 | AH75: =IF(J75<=90,F75,0)
A76: 43 | B76: Inactive | C76: EVNMMBPY05GB20D | F76: 0 | G76: 0 | I76: =VLOOKUP(C76,'Data Products'!$A:$J,2,0) | J76: =IFERROR(I76-TODAY(),"") | K76: 45882 | L76: =TODAY()-K76 | M76: 0 | N76: 0 | Q76: Mobifone | AB76: =N76/30 | AC76: =IFERROR(F76/AB76,"-") | AD76: =IFERROR(TODAY()+AC76,"-") | AE76: =_xlfn.IFS(AC76="-","Not sold yet",AND(AC76<=150,AC76>60),"Out of stock more than 60 days",AC76<=60,"Out of stock less than 60 days",AC76>=150,"Out of stock more than 150 days") | AF76: =VLOOKUP(C76,'Data Products'!$A:$J,10,0) | AG76: =AF76*F76 | AH76: =IF(J76<=90,F76,0)
A77: 44 | B77: Active | C77: 11VNMMBZ00610 | D77: 11VNMMBZ00610 | E77: 11VNMMBZ00610 | F77: 0 | G77: 0 | I77: =VLOOKUP(C77,'Data Products'!$A:$J,2,0) | J77: =IFERROR(I77-TODAY(),"") | K77: 45883 | L77: =TODAY()-K77 | M77: 0 | N77: 0 | Q77: Mobifone | AB77: =N77/30 | AC77: =IFERROR(F77/AB77,"-") | AD77: =IFERROR(TODAY()+AC77,"-") | AE77: =_xlfn.IFS(AC77="-","Not sold yet",AND(AC77<=150,AC77>60),"Out of stock more than 60 days",AC77<=60,"Out of stock less than 60 days",AC77>=150,"Out of stock more than 150 days") | AF77: =VLOOKUP(C77,'Data Products'!$A:$J,10,0) | AG77: =AF77*F77 | AH77: =IF(J77<=90,F77,0)
A78: 45 | B78: Inactive | C78: EUSATLFX01GB07D | F78: 0 | G78: 0 | I78: =VLOOKUP(C78,'Data Products'!$A:$J,2,0) | J78: =IFERROR(I78-TODAY(),"") | K78: 45884 | L78: =TODAY()-K78 | M78: 0 | N78: 0 | Q78: Mobifone | AB78: =N78/30 | AC78: =IFERROR(F78/AB78,"-") | AD78: =IFERROR(TODAY()+AC78,"-") | AE78: =_xlfn.IFS(AC78="-","Not sold yet",AND(AC78<=150,AC78>60),"Out of stock more than 60 days",AC78<=60,"Out of stock less than 60 days",AC78>=150,"Out of stock more than 150 days") | AF78: =VLOOKUP(C78,'Data Products'!$A:$J,10,0) | AG78: =AF78*F78 | AH78: =IF(J78<=90,F78,0)
A79: 46 | B79: Inactive | C79: EUSATLFX05GB30D | F79: 0 | G79: 0 | I79: =VLOOKUP(C79,'Data Products'!$A:$J,2,0) | J79: =IFERROR(I79-TODAY(),"") | K79: 45885 | L79: =TODAY()-K79 | M79: 0 | N79: 0 | Q79: Mobifone | AB79: =N79/30 | AC79: =IFERROR(F79/AB79,"-") | AD79: =IFERROR(TODAY()+AC79,"-") | AE79: =_xlfn.IFS(AC79="-","Not sold yet",AND(AC79<=150,AC79>60),"Out of stock more than 60 days",AC79<=60,"Out of stock less than 60 days",AC79>=150,"Out of stock more than 150 days") | AF79: =VLOOKUP(C79,'Data Products'!$A:$J,10,0) | AG79: =AF79*F79 | AH79: =IF(J79<=90,F79,0)
A80: 47 | B80: Inactive | C80: EUSATLFX10GB30D | F80: 0 | G80: 0 | I80: =VLOOKUP(C80,'Data Products'!$A:$J,2,0) | J80: =IFERROR(I80-TODAY(),"") | K80: 45886 | L80: =TODAY()-K80 | M80: 0 | N80: 0 | Q80: Mobifone | AB80: =N80/30 | AC80: =IFERROR(F80/AB80,"-") | AD80: =IFERROR(TODAY()+AC80,"-") | AE80: =_xlfn.IFS(AC80="-","Not sold yet",AND(AC80<=150,AC80>60),"Out of stock more than 60 days",AC80<=60,"Out of stock less than 60 days",AC80>=150,"Out of stock more than 150 days") | AF80: =VLOOKUP(C80,'Data Products'!$A:$J,10,0) | AG80: =AF80*F80 | AH80: =IF(J80<=90,F80,0)
A81: 48 | B81: Inactive | C81: EUSATLFX20GB30D | F81: 0 | G81: 0 | I81: =VLOOKUP(C81,'Data Products'!$A:$J,2,0) | J81: =IFERROR(I81-TODAY(),"") | K81: 45887 | L81: =TODAY()-K81 | M81: 0 | N81: 0 | Q81: Mobifone | AB81: =N81/30 | AC81: =IFERROR(F81/AB81,"-") | AD81: =IFERROR(TODAY()+AC81,"-") | AE81: =_xlfn.IFS(AC81="-","Not sold yet",AND(AC81<=150,AC81>60),"Out of stock more than 60 days",AC81<=60,"Out of stock less than 60 days",AC81>=150,"Out of stock more than 150 days") | AF81: =VLOOKUP(C81,'Data Products'!$A:$J,10,0) | AG81: =AF81*F81 | AH81: =IF(J81<=90,F81,0)
A82: 49 | B82: Inactive | C82: EUSATLFX50GB30D | F82: 0 | G82: 0 | I82: =VLOOKUP(C82,'Data Products'!$A:$J,2,0) | J82: =IFERROR(I82-TODAY(),"") | K82: 45888 | L82: =TODAY()-K82 | M82: 0 | N82: 0 | Q82: Mobifone | AB82: =N82/30 | AC82: =IFERROR(F82/AB82,"-") | AD82: =IFERROR(TODAY()+AC82,"-") | AE82: =_xlfn.IFS(AC82="-","Not sold yet",AND(AC82<=150,AC82>60),"Out of stock more than 60 days",AC82<=60,"Out of stock less than 60 days",AC82>=150,"Out of stock more than 150 days") | AF82: =VLOOKUP(C82,'Data Products'!$A:$J,10,0) | AG82: =AF82*F82 | AH82: =IF(J82<=90,F82,0)
A83: 50 | B83: Inactive | C83: EE33UBPY500M01D | D83: 4CE33UBP5HM01 | E83: 4CE33UBP5HM01 | F83: 0 | G83: 0 | I83: =VLOOKUP(C83,'Data Products'!$A:$J,2,0) | J83: =IFERROR(I83-TODAY(),"") | K83: 45889 | L83: =TODAY()-K83 | M83: 0 | N83: 0 | Q83: Mobifone | AB83: =N83/30 | AC83: =IFERROR(F83/AB83,"-") | AD83: =IFERROR(TODAY()+AC83,"-") | AE83: =_xlfn.IFS(AC83="-","Not sold yet",AND(AC83<=150,AC83>60),"Out of stock more than 60 days",AC83<=60,"Out of stock less than 60 days",AC83>=150,"Out of stock more than 150 days") | AF83: =VLOOKUP(C83,'Data Products'!$A:$J,10,0) | AG83: =AF83*F83 | AH83: =IF(J83<=90,F83,0)
A84: 51 | B84: Inactive | C84: EE33UBPY500M03D | D84: 4CE33UBP5HM03 | E84: 4CE33UBP5HM03 | F84: 0 | G84: 0 | I84: =VLOOKUP(C84,'Data Products'!$A:$J,2,0) | J84: =IFERROR(I84-TODAY(),"") | K84: 45890 | L84: =TODAY()-K84 | M84: 0 | N84: 0 | Q84: Mobifone | AB84: =N84/30 | AC84: =IFERROR(F84/AB84,"-") | AD84: =IFERROR(TODAY()+AC84,"-") | AE84: =_xlfn.IFS(AC84="-","Not sold yet",AND(AC84<=150,AC84>60),"Out of stock more than 60 days",AC84<=60,"Out of stock less than 60 days",AC84>=150,"Out of stock more than 150 days") | AF84: =VLOOKUP(C84,'Data Products'!$A:$J,10,0) | AG84: =AF84*F84 | AH84: =IF(J84<=90,F84,0)
A85: 52 | B85: Inactive | C85: EE33UBPY500M05D | D85: 4CE33UBP5HM05 | E85: 4CE33UBP5HM05 | F85: 0 | G85: 0 | I85: =VLOOKUP(C85,'Data Products'!$A:$J,2,0) | J85: =IFERROR(I85-TODAY(),"") | K85: 45891 | L85: =TODAY()-K85 | M85: 0 | N85: 0 | Q85: Mobifone | AB85: =N85/30 | AC85: =IFERROR(F85/AB85,"-") | AD85: =IFERROR(TODAY()+AC85,"-") | AE85: =_xlfn.IFS(AC85="-","Not sold yet",AND(AC85<=150,AC85>60),"Out of stock more than 60 days",AC85<=60,"Out of stock less than 60 days",AC85>=150,"Out of stock more than 150 days") | AF85: =VLOOKUP(C85,'Data Products'!$A:$J,10,0) | AG85: =AF85*F85 | AH85: =IF(J85<=90,F85,0)
A86: 53 | B86: Inactive | C86: EE33UBPY500M07D | D86: 4CE33UBP5HM07 | E86: 4CE33UBP5HM07 | F86: 0 | G86: 0 | I86: =VLOOKUP(C86,'Data Products'!$A:$J,2,0) | J86: =IFERROR(I86-TODAY(),"") | K86: 45892 | L86: =TODAY()-K86 | M86: 0 | N86: 0 | Q86: Mobifone | AB86: =N86/30 | AC86: =IFERROR(F86/AB86,"-") | AD86: =IFERROR(TODAY()+AC86,"-") | AE86: =_xlfn.IFS(AC86="-","Not sold yet",AND(AC86<=150,AC86>60),"Out of stock more than 60 days",AC86<=60,"Out of stock less than 60 days",AC86>=150,"Out of stock more than 150 days") | AF86: =VLOOKUP(C86,'Data Products'!$A:$J,10,0) | AG86: =AF86*F86 | AH86: =IF(J86<=90,F86,0)
A87: 54 | B87: Inactive | C87: EE33UBPY500M10D | D87: 4CE33UBP5HM10 | E87: 4CE33UBP5HM10 | F87: 0 | G87: 0 | I87: =VLOOKUP(C87,'Data Products'!$A:$J,2,0) | J87: =IFERROR(I87-TODAY(),"") | K87: 45893 | L87: =TODAY()-K87 | M87: 0 | N87: 0 | Q87: Mobifone | AB87: =N87/30 | AC87: =IFERROR(F87/AB87,"-") | AD87: =IFERROR(TODAY()+AC87,"-") | AE87: =_xlfn.IFS(AC87="-","Not sold yet",AND(AC87<=150,AC87>60),"Out of stock more than 60 days",AC87<=60,"Out of stock less than 60 days",AC87>=150,"Out of stock more than 150 days") | AF87: =VLOOKUP(C87,'Data Products'!$A:$J,10,0) | AG87: =AF87*F87 | AH87: =IF(J87<=90,F87,0)
A88: 55 | B88: Inactive | C88: EE33UBPY500M15D | D88: 4CE33UBP5HM15 | E88: 4CE33UBP5HM15 | F88: 0 | G88: 0 | I88: =VLOOKUP(C88,'Data Products'!$A:$J,2,0) | J88: =IFERROR(I88-TODAY(),"") | K88: 45894 | L88: =TODAY()-K88 | M88: 0 | N88: 0 | Q88: Mobifone | AB88: =N88/30 | AC88: =IFERROR(F88/AB88,"-") | AD88: =IFERROR(TODAY()+AC88,"-") | AE88: =_xlfn.IFS(AC88="-","Not sold yet",AND(AC88<=150,AC88>60),"Out of stock more than 60 days",AC88<=60,"Out of stock less than 60 days",AC88>=150,"Out of stock more than 150 days") | AF88: =VLOOKUP(C88,'Data Products'!$A:$J,10,0) | AG88: =AF88*F88 | AH88: =IF(J88<=90,F88,0)
A89: 56 | B89: Inactive | C89: EE33UBPY01GB03D | D89: 4CE33UBP5HM | E89: 4CE33UBP5HM | F89: 0 | G89: 0 | I89: =VLOOKUP(C89,'Data Products'!$A:$J,2,0) | J89: =IFERROR(I89-TODAY(),"") | K89: 45895 | L89: =TODAY()-K89 | M89: 0 | N89: 0 | Q89: Mobifone | AB89: =N89/30 | AC89: =IFERROR(F89/AB89,"-") | AD89: =IFERROR(TODAY()+AC89,"-") | AE89: =_xlfn.IFS(AC89="-","Not sold yet",AND(AC89<=150,AC89>60),"Out of stock more than 60 days",AC89<=60,"Out of stock less than 60 days",AC89>=150,"Out of stock more than 150 days") | AF89: =VLOOKUP(C89,'Data Products'!$A:$J,10,0) | AG89: =AF89*F89 | AH89: =IF(J89<=90,F89,0)
A90: 57 | B90: Inactive | C90: EE33UBPY01GB05D | D90: 4CE33UBP00105 | E90: 4CE33UBP00105 | F90: 0 | G90: 0 | I90: =VLOOKUP(C90,'Data Products'!$A:$J,2,0) | J90: =IFERROR(I90-TODAY(),"") | K90: 45896 | L90: =TODAY()-K90 | M90: 0 | N90: 0 | Q90: Mobifone | AB90: =N90/30 | AC90: =IFERROR(F90/AB90,"-") | AD90: =IFERROR(TODAY()+AC90,"-") | AE90: =_xlfn.IFS(AC90="-","Not sold yet",AND(AC90<=150,AC90>60),"Out of stock more than 60 days",AC90<=60,"Out of stock less than 60 days",AC90>=150,"Out of stock more than 150 days") | AF90: =VLOOKUP(C90,'Data Products'!$A:$J,10,0) | AG90: =AF90*F90 | AH90: =IF(J90<=90,F90,0)
A91: 58 | B91: Inactive | C91: EE33UBPY01GB07D | D91: 4CE33UBP00107 | E91: 4CE33UBP00107 | F91: 0 | G91: 0 | I91: =VLOOKUP(C91,'Data Products'!$A:$J,2,0) | J91: =IFERROR(I91-TODAY(),"") | K91: 45897 | L91: =TODAY()-K91 | M91: 0 | N91: 0 | Q91: Mobifone | AB91: =N91/30 | AC91: =IFERROR(F91/AB91,"-") | AD91: =IFERROR(TODAY()+AC91,"-") | AE91: =_xlfn.IFS(AC91="-","Not sold yet",AND(AC91<=150,AC91>60),"Out of stock more than 60 days",AC91<=60,"Out of stock less than 60 days",AC91>=150,"Out of stock more than 150 days") | AF91: =VLOOKUP(C91,'Data Products'!$A:$J,10,0) | AG91: =AF91*F91 | AH91: =IF(J91<=90,F91,0)
A92: 59 | B92: Inactive | C92: EE33UBPY01GB10D | D92: 4CE33UBP00110 | E92: 4CE33UBP00110 | F92: 0 | G92: 0 | I92: =VLOOKUP(C92,'Data Products'!$A:$J,2,0) | J92: =IFERROR(I92-TODAY(),"") | K92: 45898 | L92: =TODAY()-K92 | M92: 0 | N92: 0 | Q92: Mobifone | AB92: =N92/30 | AC92: =IFERROR(F92/AB92,"-") | AD92: =IFERROR(TODAY()+AC92,"-") | AE92: =_xlfn.IFS(AC92="-","Not sold yet",AND(AC92<=150,AC92>60),"Out of stock more than 60 days",AC92<=60,"Out of stock less than 60 days",AC92>=150,"Out of stock more than 150 days") | AF92: =VLOOKUP(C92,'Data Products'!$A:$J,10,0) | AG92: =AF92*F92 | AH92: =IF(J92<=90,F92,0)
A93: 60 | B93: Inactive | C93: EE33UBPY01GB15D | D93: 4CE33UBP00115 | E93: 4CE33UBP00115 | F93: 0 | G93: 0 | I93: =VLOOKUP(C93,'Data Products'!$A:$J,2,0) | J93: =IFERROR(I93-TODAY(),"") | K93: 45899 | L93: =TODAY()-K93 | M93: 0 | N93: 0 | Q93: Mobifone | AB93: =N93/30 | AC93: =IFERROR(F93/AB93,"-") | AD93: =IFERROR(TODAY()+AC93,"-") | AE93: =_xlfn.IFS(AC93="-","Not sold yet",AND(AC93<=150,AC93>60),"Out of stock more than 60 days",AC93<=60,"Out of stock less than 60 days",AC93>=150,"Out of stock more than 150 days") | AF93: =VLOOKUP(C93,'Data Products'!$A:$J,10,0) | AG93: =AF93*F93 | AH93: =IF(J93<=90,F93,0)
A94: 61 | B94: Inactive | C94: EE33UBPY01GB20D | D94: 4CE33UBP00120 | E94: 4CE33UBP00120 | F94: 0 | G94: 0 | I94: =VLOOKUP(C94,'Data Products'!$A:$J,2,0) | J94: =IFERROR(I94-TODAY(),"") | K94: 45900 | L94: =TODAY()-K94 | M94: 0 | N94: 0 | Q94: Mobifone | AB94: =N94/30 | AC94: =IFERROR(F94/AB94,"-") | AD94: =IFERROR(TODAY()+AC94,"-") | AE94: =_xlfn.IFS(AC94="-","Not sold yet",AND(AC94<=150,AC94>60),"Out of stock more than 60 days",AC94<=60,"Out of stock less than 60 days",AC94>=150,"Out of stock more than 150 days") | AF94: =VLOOKUP(C94,'Data Products'!$A:$J,10,0) | AG94: =AF94*F94 | AH94: =IF(J94<=90,F94,0)
... A102: 69 | B102: Inactive | C102: EE33UBPY02GB30D | D102: 4CE33UBP00230 | E102: 4CE33UBP00230 | F102: 0 | G102: 0 | I102: =VLOOKUP(C102,'Data Products'!$A:$J,2,0) | J102: =IFERROR(I102-TODAY(),"") | K102: 45908 | L102: =TODAY()-K102 | M102: 0 | N102: 0 | Q102: Mobifone | AB102: =N102/30 | AC102: =IFERROR(F102/AB102,"-") | AD102: =IFERROR(TODAY()+AC102,"-") | AE102: =_xlfn.IFS(AC102="-","Not sold yet",AND(AC102<=150,AC102>60),"Out of stock more than 60 days",AC102<=60,"Out of stock less than 60 days",AC102>=150,"Out of stock more than 150 days") | AF102: =VLOOKUP(C102,'Data Products'!$A:$J,10,0) | AG102: =AF102*F102 | AH102: =IF(J102<=90,F102,0)
A103: 70 | B103: Inactive | C103: ETWNW1FY05GB10D | F103: 0 | G103: 0 | I103: =VLOOKUP(C103,'Data Products'!$A:$J,2,0) | J103: =IFERROR(I103-TODAY(),"") | K103: 45909 | L103: =TODAY()-K103 | M103: 0 | N103: 0 | Q103: Mobifone | AB103: =N103/30 | AC103: =IFERROR(F103/AB103,"-") | AD103: =IFERROR(TODAY()+AC103,"-") | AE103: =_xlfn.IFS(AC103="-","Not sold yet",AND(AC103<=150,AC103>60),"Out of stock more than 60 days",AC103<=60,"Out of stock less than 60 days",AC103>=150,"Out of stock more than 150 days") | AF103: =VLOOKUP(C103,'Data Products'!$A:$J,10,0) | AG103: =AF103*F103 | AH103: =IF(J103<=90,F103,0)
A104: 71 | B104: Inactive | C104: ETWNW1FY05GB15D | F104: 0 | G104: 0 | I104: =VLOOKUP(C104,'Data Products'!$A:$J,2,0) | J104: =IFERROR(I104-TODAY(),"") | K104: 45910 | L104: =TODAY()-K104 | M104: 0 | N104: 0 | Q104: Mobifone | AB104: =N104/30 | AC104: =IFERROR(F104/AB104,"-") | AD104: =IFERROR(TODAY()+AC104,"-") | AE104: =_xlfn.IFS(AC104="-","Not sold yet",AND(AC104<=150,AC104>60),"Out of stock more than 60 days",AC104<=60,"Out of stock less than 60 days",AC104>=150,"Out of stock more than 150 days") | AF104: =VLOOKUP(C104,'Data Products'!$A:$J,10,0) | AG104: =AF104*F104 | AH104: =IF(J104<=90,F104,0) | AI104: đã lên ticket nhờ đẩy tồn
A105: 72 | B105: Inactive | C105: ETWNW1FY10GB15D | F105: 0 | G105: 0 | I105: =VLOOKUP(C105,'Data Products'!$A:$J,2,0) | J105: =IFERROR(I105-TODAY(),"") | K105: 45911 | L105: =TODAY()-K105 | M105: 0 | N105: 0 | Q105: Mobifone | AB105: =N105/30 | AC105: =IFERROR(F105/AB105,"-") | AD105: =IFERROR(TODAY()+AC105,"-") | AE105: =_xlfn.IFS(AC105="-","Not sold yet",AND(AC105<=150,AC105>60),"Out of stock more than 60 days",AC105<=60,"Out of stock less than 60 days",AC105>=150,"Out of stock more than 150 days") | AF105: =VLOOKUP(C105,'Data Products'!$A:$J,10,0) | AG105: =AF105*F105 | AH105: =IF(J105<=90,F105,0)
A106: 45 | B106: Active | C106: ETWNW1FY20GB15D | D106: 2CTHATMF05010 | E106: 2CTHATMF05010 | F106: 0 | G106: 0 | I106: =VLOOKUP(C106,'Data Products'!$A:$J,2,0) | J106: =IFERROR(I106-TODAY(),"") | K106: 45912 | L106: =TODAY()-K106 | M106: 0 | N106: 0 | Q106: TrueMove | AB106: =N106/30 | AC106: =IFERROR(F106/AB106,"-") | AD106: =IFERROR(TODAY()+AC106,"-") | AE106: =_xlfn.IFS(AC106="-","Not sold yet",AND(AC106<=150,AC106>60),"Out of stock more than 60 days",AC106<=60,"Out of stock less than 60 days",AC106>=150,"Out of stock more than 150 days") | AF106: =VLOOKUP(C106,'Data Products'!$A:$J,10,0) | AG106: =AF106*F106
A107: 46 | B107: Active | C107: 1CCNMCUF00708 | D107: 1CCNMCUF00708 | E107: 1CCNMCUF00708 | F107: 0 | G107: 0 | I107: =VLOOKUP(C107,'Data Products'!$A:$J,2,0) | J107: =IFERROR(I107-TODAY(),"") | K107: 45913 | L107: =TODAY()-K107 | M107: 0 | N107: 0 | Q107: TrueMove | AB107: =N107/30 | AC107: =IFERROR(F107/AB107,"-") | AD107: =IFERROR(TODAY()+AC107,"-") | AE107: =_xlfn.IFS(AC107="-","Not sold yet",AND(AC107<=150,AC107>60),"Out of stock more than 60 days",AC107<=60,"Out of stock less than 60 days",AC107>=150,"Out of stock more than 150 days") | AF107: =VLOOKUP(C107,'Data Products'!$A:$J,10,0) | AG107: =AF107*F107 | AI107: không nhập thêm
A108: 47 | B108: Active | C108: 1CKORCUF01005 | D108: 1CKORCUF01005 | E108: 1CKORCUF01005 | F108: 31 | G108: 31 | I108: =VLOOKUP(C108,'Data Products'!$A:$J,2,0) | J108: =IFERROR(I108-TODAY(),"") | K108: 45914 | L108: =TODAY()-K108 | M108: 0 | N108: 0 | Q108: 4HK | AB108: =N108/30 | AC108: =IFERROR(F108/AB108,"-") | AD108: =IFERROR(TODAY()+AC108,"-") | AE108: =_xlfn.IFS(AC108="-","Not sold yet",AND(AC108<=150,AC108>60),"Out of stock more than 60 days",AC108<=60,"Out of stock less than 60 days",AC108>=150,"Out of stock more than 150 days") | AF108: =VLOOKUP(C108,'Data Products'!$A:$J,10,0) | AG108: =AF108*F108 | AI108: khuyến mãi đẩy tồn
...

Sheet 06.08
A1: SIM | B1: Status | C1: SKU (Sapo) | D1: SKU (mới) | E1: SKU (full) | F1: Total Inventory | H1: Quantity due to expiration | I1: Expiration | J1: Expired date left | K1: Date of Import | L1: Inventory Age | M1: Last 15 days | N1: Last 30 days | O1: Safety Stock (15D) | P1: Reorder Point (30D) | Q1: Vendor | R1: Kho tổng | T1: Phổ Quang - HCM | V1: Đống Đa - Hà Nội | X1: Tân Sơn Nhất - HCM | Z1: Chi nhánh Ký gửi | AB1: Avg Pcs/day | AC1: DOI (Số ngày tồn kho) | AD1: Estimated date out of stock | AE1: Evaluate | AF1: Retail Price | AG1: Total retail price | AH1: Near Expiration Inventory | AI1: OPS | AJ1: Telco | AK1: OD | AL1: WS | AM1: B2C | AN1: Marketing
A2: No. | F2: Stock | G2: Available for sale | M2: Sold | N2: Sold | R2: Stock | S2: Available for sale | T2: Stock | U2: Available for sale | V2: Stock | W2: Available for sale | X2: Stock | Y2: Available for sale | Z2: Stock | AA2: Available for sale
A3: 1 | B3: Temporary | C3: 3HKDATAPOOLSIM | D3: 3HKDATAPOOLSIM | E3: 1D0003DK00000 | F3: 419 | G3: 419 | I3: =VLOOKUP(C3,'Data Products'!$A:$B,2,0) | J3: =IFERROR(I3-TODAY(),"") | K3: 45723 | L3: =TODAY()-K3 | M3: 354 | N3: 380 | R3: 0 | S3: 0 | T3: 326 | U3: 326 | V3: 146 | W3: 146 | X3: 0 | Y3: 0 | Z3: 0 | AA3: 0 | AB3: =N3/30 | AC3: =IFERROR(F3/AB3,"-") | AD3: =IFERROR(TODAY()+AC3,"-") | AE3: =_xlfn.IFS(AC3="-","Not sold yet",AND(AC3<=150,AC3>60),"Out of stock more than 60 days",AC3<=60,"Out of stock less than 60 days",AC3>=150,"Out of stock more than 150 days") | AF3: =VLOOKUP(C3,'Data Products'!$A:$J,10,0) | AG3: =AF3*F3 | AH3: =IF(J3<=90,F3,0) | AI3: =IFERROR(VLOOKUP(C3,$C$3:$AI$42,34,0),"")
A4: 1 | B4: Active | C4: 1D0003DK00000 | D4: 1D0003DK00000 | E4: 1D0003DK00000 | F4: 19815 | G4: 19763 | I4: =VLOOKUP(C4,'Data Products'!$A:$B,2,0) | J4: =IFERROR(I4-TODAY(),"") | K4: 45617 | L4: =TODAY()-K4 | M4: 9349 | N4: 17027 | R4: 0 | S4: 0 | T4: 1378 | U4: 1369 | V4: 115 | W4: 112 | X4: 46 | Y4: 22 | Z4: 0 | AA4: 0 | AB4: =N4/30 | AC4: =IFERROR(F4/AB4,"-") | AD4: =IFERROR(TODAY()+AC4,"-") | AE4: =_xlfn.IFS(AC4="-","Not sold yet",AND(AC4<=150,AC4>60),"Out of stock more than 60 days",AC4<=60,"Out of stock less than 60 days",AC4>=150,"Out of stock more than 150 days") | AF4: =VLOOKUP(C4,'Data Products'!$A:$J,10,0) | AG4: =AF4*F4 | AH4: =IF(J4<=90,F4,0) | AI4: cần có hàng mới 20 - 25/08 để an toàn
A5: 2 | B5: Active | C5: 1D000BCK00000 | D5: 1D000BCK00000 | E5: 1D000BCK00000 | F5: 292 | G5: 292 | I5: =VLOOKUP(C5,'Data Products'!$A:$B,2,0) | J5: =IFERROR(I5-TODAY(),"") | K5: 45191 | L5: =TODAY()-K5 | M5: 17 | N5: 29 | R5: 0 | S5: 0 | T5: 26 | U5: 26 | V5: 416 | W5: 416 | X5: 0 | Y5: 0 | Z5: 0 | AA5: 0 | AB5: =N5/30 | AC5: =IFERROR(F5/AB5,"-") | AD5: =IFERROR(TODAY()+AC5,"-") | AE5: =_xlfn.IFS(AC5="-","Not sold yet",AND(AC5<=150,AC5>60),"Out of stock more than 60 days",AC5<=60,"Out of stock less than 60 days",AC5>=150,"Out of stock more than 150 days") | AF5: =VLOOKUP(C5,'Data Products'!$A:$J,10,0) | AG5: =AF5*F5 | AH5: =IF(J5<=90,F5,0) | AI5: sắp hết hạn, gia hạn thêm 1 tháng
A6: 3 | B6: Active | C6: 1D000ELK00000 | D6: 1D000ELK00000 | E6: 1D000ELK00000 | F6: 4268 | G6: 4268 | I6: =VLOOKUP(C6,'Data Products'!$A:$B,2,0) | J6: =IFERROR(I6-TODAY(),"") | K6: 45752 | L6: =TODAY()-K6 | M6: 28 | N6: 48 | R6: 0 | S6: 0 | T6: 1 | U6: 1 | V6: 1 | W6: 1 | X6: 0 | Y6: 0 | Z6: 0 | AA6: 0 | AB6: =N6/30 | AC6: =IFERROR(F6/AB6,"-") | AD6: =IFERROR(TODAY()+AC6,"-") | AE6: =_xlfn.IFS(AC6="-","Not sold yet",AND(AC6<=150,AC6>60),"Out of stock more than 60 days",AC6<=60,"Out of stock less than 60 days",AC6>=150,"Out of stock more than 150 days") | AF6: =VLOOKUP(C6,'Data Products'!$A:$J,10,0) | AG6: =AF6*F6 | AH6: =IF(J6<=90,F6,0) | AI6: =IFERROR(VLOOKUP(C6,$C$3:$AI$42,34,0),"")
A7: 4 | B7: Active | C7: 1D000JYK00000 | D7: 1D000JYK00000 | E7: 1D000JYK00000 | F7: 884 | G7: 864 | I7: =VLOOKUP(C7,'Data Products'!$A:$B,2,0) | J7: =IFERROR(I7-TODAY(),"") | K7: 45854 | L7: =TODAY()-K7 | M7: 3 | N7: 7 | R7: 0 | S7: 0 | T7: 288 | U7: 288 | V7: 512 | W7: 512 | X7: 20 | Y7: 20 | Z7: 0 | AA7: 0 | AB7: =N7/30 | AC7: =IFERROR(F7/AB7,"-") | AD7: =IFERROR(TODAY()+AC7,"-") | AE7: =_xlfn.IFS(AC7="-","Not sold yet",AND(AC7<=150,AC7>60),"Out of stock more than 60 days",AC7<=60,"Out of stock less than 60 days",AC7>=150,"Out of stock more than 150 days") | AF7: =VLOOKUP(C7,'Data Products'!$A:$J,10,0) | AG7: =AF7*F7 | AH7: =IF(J7<=90,F7,0) | AI7: =IFERROR(VLOOKUP(C7,$C$3:$AI$42,34,0),"")
A8: 5 | B8: Active | C8: 1D000SSK00000 | D8: 1D000SSK00000 | E8: 1D000SSK00000 | F8: 2468 | G8: 2468 | I8: =VLOOKUP(C8,'Data Products'!$A:$B,2,0) | J8: =IFERROR(I8-TODAY(),"") | K8: 45855 | L8: =TODAY()-K8 | M8: 9 | N8: 56 | R8: 0 | S8: 0 | T8: 51 | U8: 51 | V8: 101 | W8: 101 | X8: 0 | Y8: 0 | Z8: 0 | AA8: 0 | AB8: =N8/30 | AC8: =IFERROR(F8/AB8,"-") | AD8: =IFERROR(TODAY()+AC8,"-") | AE8: =_xlfn.IFS(AC8="-","Not sold yet",AND(AC8<=150,AC8>60),"Out of stock more than 60 days",AC8<=60,"Out of stock less than 60 days",AC8>=150,"Out of stock more than 150 days") | AF8: =VLOOKUP(C8,'Data Products'!$A:$J,10,0) | AG8: =AF8*F8 | AH8: =IF(J8<=90,F8,0) | AI8: =IFERROR(VLOOKUP(C8,$C$3:$AI$42,34,0)," ")
A9: 6 | B9: Active | C9: 1D000UBK00000 | D9: 1D000UBK00000 | E9: 1D000UBK00000 | F9: 2062 | G9: 2062 | I9: =VLOOKUP(C9,'Data Products'!$A:$B,2,0) | J9: =IFERROR(I9-TODAY(),"") | K9: 45856 | L9: =TODAY()-K9 | M9: 0 | N9: 0 | R9: 0 | S9: 0 | T9: 1480 | U9: 1478 | V9: 1112 | W9: 1112 | X9: 0 | Y9: 0 | Z9: 0 | AA9: 0 | AB9: =N9/30 | AC9: =IFERROR(F9/AB9,"-") | AD9: =IFERROR(TODAY()+AC9,"-") | AE9: =_xlfn.IFS(AC9="-","Not sold yet",AND(AC9<=150,AC9>60),"Out of stock more than 60 days",AC9<=60,"Out of stock less than 60 days",AC9>=150,"Out of stock more than 150 days") | AF9: =VLOOKUP(C9,'Data Products'!$A:$J,10,0) | AG9: =AF9*F9 | AH9: =IF(J9<=90,F9,0) | AI9: =IFERROR(VLOOKUP(C9,$C$3:$AI$42,34,0),"")
A10: 7 | B10: Active | C10: 1D000WMK00000 | D10: 1D000WMK00000 | E10: 1D000WMK00000 | F10: 479 | G10: 479 | I10: =VLOOKUP(C10,'Data Products'!$A:$B,2,0) | J10: =IFERROR(I10-TODAY(),"") | K10: 45857 | L10: =TODAY()-K10 | M10: 132 | N10: 271 | R10: 0 | S10: 0 | T10: 0 | U10: 0 | V10: 2 | W10: 2 | X10: 0 | Y10: 0 | Z10: 0 | AA10: 0 | AB10: =N10/30 | AC10: =IFERROR(F10/AB10,"-") | AD10: =IFERROR(TODAY()+AC10,"-") | AE10: =_xlfn.IFS(AC10="-","Not sold yet",AND(AC10<=150,AC10>60),"Out of stock more than 60 days",AC10<=60,"Out of stock less than 60 days",AC10>=150,"Out of stock more than 150 days") | AF10: =VLOOKUP(C10,'Data Products'!$A:$J,10,0) | AG10: =AF10*F10 | AH10: =IF(J10<=90,F10,0) | AI10: =IFERROR(VLOOKUP(C10,$C$3:$AI$42,34,0),"")
A11: 8 | B11: Temporary | C11: CNMCU05GBFY05D | D11: CNMCU05GBFY05D | E11: CNMCU05GBFY05D | F11: 1200 | G11: 1200 | I11: =VLOOKUP(C11,'Data Products'!$A:$B,2,0) | J11: =IFERROR(I11-TODAY(),"") | K11: 45858 | L11: =TODAY()-K11 | M11: 0 | N11: 0 | R11: 0 | S11: 0 | T11: 1289 | U11: 1289 | V11: 773 | W11: 773 | X11: 0 | Y11: 0 | Z11: 0 | AA11: 0 | AB11: =N11/30 | AC11: =IFERROR(F11/AB11,"-") | AD11: =IFERROR(TODAY()+AC11,"-") | AE11: =_xlfn.IFS(AC11="-","Not sold yet",AND(AC11<=150,AC11>60),"Out of stock more than 60 days",AC11<=60,"Out of stock less than 60 days",AC11>=150,"Out of stock more than 150 days") | AF11: =VLOOKUP(C11,'Data Products'!$A:$J,10,0) | AG11: =AF11*F11 | AH11: =IF(J11<=90,F11,0) | AI11: =IFERROR(VLOOKUP(C11,$C$3:$AI$42,34,0),"")
A12: 9 | B12: Temporary | C12: CNMCU07GBFY08D | D12: CNMCU07GBFY08D | E12: CNMCU07GBFY08D | F12: 1000 | G12: 1000 | I12: =VLOOKUP(C12,'Data Products'!$A:$B,2,0) | J12: =IFERROR(I12-TODAY(),"") | K12: 45532 | L12: =TODAY()-K12 | M12: 0 | N12: 0 | R12: 0 | S12: 0 | T12: 417 | U12: 416 | V12: 785 | W12: 785 | X12: 0 | Y12: 0 | Z12: 0 | AA12: 0 | AB12: =N12/30 | AC12: =IFERROR(F12/AB12,"-") | AD12: =IFERROR(TODAY()+AC12,"-") | AE12: =_xlfn.IFS(AC12="-","Not sold yet",AND(AC12<=150,AC12>60),"Out of stock more than 60 days",AC12<=60,"Out of stock less than 60 days",AC12>=150,"Out of stock more than 150 days") | AF12: =VLOOKUP(C12,'Data Products'!$A:$J,10,0) | AG12: =AF12*F12 | AH12: =IF(J12<=90,F12,0) | AI12: qua tết push lại, mỗi tuần nhắc lại
A13: 10 | B13: Temporary | C13: KORCU10GBFY05D | D13: KORCU10GBFY05D | E13: KORCU10GBFY05D | F13: 500 | G13: 500 | I13: =VLOOKUP(C13,'Data Products'!$A:$B,2,0) | J13: =IFERROR(I13-TODAY(),"") | K13: 45504 | L13: =TODAY()-K13 | M13: 0 | N13: 0 | R13: 0 | S13: 0 | T13: 3870 | U13: 1017 | V13: 366 | W13: 366 | X13: 0 | Y13: 0 | Z13: 0 | AA13: 0 | AB13: =N13/30 | AC13: =IFERROR(F13/AB13,"-") | AD13: =IFERROR(TODAY()+AC13,"-") | AE13: =_xlfn.IFS(AC13="-","Not sold yet",AND(AC13<=150,AC13>60),"Out of stock more than 60 days",AC13<=60,"Out of stock less than 60 days",AC13>=150,"Out of stock more than 150 days") | AF13: =VLOOKUP(C13,'Data Products'!$A:$J,10,0) | AG13: =AF13*F13 | AH13: =IF(J13<=90,F13,0) | AI13: =IFERROR(VLOOKUP(C13,$C$3:$AI$42,34,0),"")
A14: 11 | B14: Active | C14: 1DCNMCTF00705 | D14: 1DCNMCTF00705 | E14: 1ECNMCTF00705 | F14: 181 | G14: 181 | I14: =VLOOKUP(C14,'Data Products'!$A:$B,2,0) | J14: =IFERROR(I14-TODAY(),"") | K14: 45504 | L14: =TODAY()-K14 | M14: 1 | N14: 1 | R14: 1200 | S14: 1200 | T14: 0 | U14: 0 | V14: 0 | W14: 0 | X14: 0 | Y14: 0 | Z14: 0 | AA14: 0 | AB14: =N14/30 | AC14: =IFERROR(F14/AB14,"-") | AD14: =IFERROR(TODAY()+AC14,"-") | AE14: =_xlfn.IFS(AC14="-","Not sold yet",AND(AC14<=150,AC14>60),"Out of stock more than 60 days",AC14<=60,"Out of stock less than 60 days",AC14>=150,"Out of stock more than 150 days") | AF14: =VLOOKUP(C14,'Data Products'!$A:$J,10,0) | AG14: =AF14*F14 | AH14: =IF(J14<=90,F14,0) | AI14: =IFERROR(VLOOKUP(C14,$C$3:$AI$42,34,0)," ")
A15: 12 | B15: Active | C15: 1DCNMCUF01530 | D15: 1DCNMCUF01530 | E15: 1ECNMCUF01530 | F15: 100 | G15: 100 | I15: =VLOOKUP(C15,'Data Products'!$A:$B,2,0) | J15: =IFERROR(I15-TODAY(),"") | K15: 45648 | L15: =TODAY()-K15 | M15: 4 | N15: 6 | R15: 1000 | S15: 1000 | T15: 0 | U15: 0 | V15: 0 | W15: 0 | X15: 0 | Y15: 0 | Z15: 0 | AA15: 0 | AB15: =N15/30 | AC15: =IFERROR(F15/AB15,"-") | AD15: =IFERROR(TODAY()+AC15,"-") | AE15: =_xlfn.IFS(AC15="-","Not sold yet",AND(AC15<=150,AC15>60),"Out of stock more than 60 days",AC15<=60,"Out of stock less than 60 days",AC15>=150,"Out of stock more than 150 days") | AF15: =VLOOKUP(C15,'Data Products'!$A:$J,10,0) | AG15: =AF15*F15 | AH15: =IF(J15<=90,F15,0) | AI15: =IFERROR(VLOOKUP(C15,$C$3:$AI$42,34,0),"")
A16: 13 | B16: Active | C16: 1DCNMCUF00303 | D16: 1DCNMCUF00303 | E16: 1ECNMCUF00303 | F16: 847 | G16: 847 | I16: =VLOOKUP(C16,'Data Products'!$A:$B,2,0) | J16: =IFERROR(I16-TODAY(),"") | K16: 45504 | L16: =TODAY()-K16 | M16: 101 | N16: 102 | R16: 500 | S16: 500 | T16: 0 | U16: 0 | V16: 0 | W16: 0 | X16: 0 | Y16: 0 | Z16: 0 | AA16: 0 | AB16: =N16/30 | AC16: =IFERROR(F16/AB16,"-") | AD16: =IFERROR(TODAY()+AC16,"-") | AE16: =_xlfn.IFS(AC16="-","Not sold yet",AND(AC16<=150,AC16>60),"Out of stock more than 60 days",AC16<=60,"Out of stock less than 60 days",AC16>=150,"Out of stock more than 150 days") | AF16: =VLOOKUP(C16,'Data Products'!$A:$J,10,0) | AG16: =AF16*F16 | AH16: =IF(J16<=90,F16,0) | AI16: =IFERROR(VLOOKUP(C16,$C$3:$AI$42,34,0),"")
A17: 14 | B17: Active | C17: 1DCNMCUF00505 | D17: 1DCNMCUF00505 | E17: 1ECNMCUF00505 | F17: 0 | G17: 0 | I17: =VLOOKUP(C17,'Data Products'!$A:$B,2,0) | J17: =IFERROR(I17-TODAY(),"") | K17: 45653 | L17: =TODAY()-K17 | M17: 0 | N17: 0 | R17: 0 | S17: 0 | T17: 128 | U17: 128 | V17: 54 | W17: 54 | X17: 0 | Y17: 0 | Z17: 0 | AA17: 0 | AB17: =N17/30 | AC17: =IFERROR(F17/AB17,"-") | AD17: =IFERROR(TODAY()+AC17,"-") | AE17: =_xlfn.IFS(AC17="-","Not sold yet",AND(AC17<=150,AC17>60),"Out of stock more than 60 days",AC17<=60,"Out of stock less than 60 days",AC17>=150,"Out of stock more than 150 days") | AF17: =VLOOKUP(C17,'Data Products'!$A:$J,10,0) | AG17: =AF17*F17 | AH17: =IF(J17<=90,F17,0) | AI17: =IFERROR(VLOOKUP(C17,$C$3:$AI$42,34,0),"")
A18: 15 | B18: Active | C18: 1DTHADTF05010 | D18: 1DTHADTF05010 | E18: 1ETHADTF05010 | F18: 5 | G18: 5 | I18: =VLOOKUP(C18,'Data Products'!$A:$B,2,0) | J18: =IFERROR(I18-TODAY(),"") | K18: 45737 | L18: =TODAY()-K18 | M18: 0 | N18: 0 | R18: 0 | S18: 0 | T18: 0 | U18: 0 | V18: 116 | W18: 116 | X18: 0 | Y18: 0 | Z18: 0 | AA18: 0 | AB18: =N18/30 | AC18: =IFERROR(F18/AB18,"-") | AD18: =IFERROR(TODAY()+AC18,"-") | AE18: =_xlfn.IFS(AC18="-","Not sold yet",AND(AC18<=150,AC18>60),"Out of stock more than 60 days",AC18<=60,"Out of stock less than 60 days",AC18>=150,"Out of stock more than 150 days") | AF18: =VLOOKUP(C18,'Data Products'!$A:$J,10,0) | AG18: =AF18*F18 | AH18: =IF(J18<=90,F18,0)
A19: 16 | B19: Active | C19: 1DWORCBF01030 | D19: 1DWORCBF01030 | E19: 1DWORCBF01030 | F19: 353 | G19: 353 | I19: =VLOOKUP(C19,'Data Products'!$A:$B,2,0) | J19: =IFERROR(I19-TODAY(),"") | K19: 45653 | L19: =TODAY()-K19 | M19: 0 | N19: 83 | R19: 600 | S19: 600 | T19: 100 | U19: 100 | V19: 300 | W19: 300 | X19: 0 | Y19: 0 | Z19: 0 | AA19: 0 | AB19: =N19/30 | AC19: =IFERROR(F19/AB19,"-") | AD19: =IFERROR(TODAY()+AC19,"-") | AE19: =_xlfn.IFS(AC19="-","Not sold yet",AND(AC19<=150,AC19>60),"Out of stock more than 60 days",AC19<=60,"Out of stock less than 60 days",AC19>=150,"Out of stock more than 150 days") | AF19: =VLOOKUP(C19,'Data Products'!$A:$J,10,0) | AG19: =AF19*F19 | AH19: =IF(J19<=90,F19,0)
A20: 17 | B20: Active | C20: 1DTHATMF01507 | D20: 1DTHATMF01507 | E20: 1ETHATMF01507 | F20: 4155 | G20: 4150 | I20: =VLOOKUP(C20,'Data Products'!$A:$B,2,0) | J20: =IFERROR(I20-TODAY(),"") | K20: 45653 | L20: =TODAY()-K20 | M20: 738 | N20: 2961 | R20: 0 | S20: 0 | T20: 27 | U20: 27 | V20: 25 | W20: 25 | X20: 0 | Y20: 0 | Z20: 0 | AA20: 0 | AB20: =N20/30 | AC20: =IFERROR(F20/AB20,"-") | AD20: =IFERROR(TODAY()+AC20,"-") | AE20: =_xlfn.IFS(AC20="-","Not sold yet",AND(AC20<=150,AC20>60),"Out of stock more than 60 days",AC20<=60,"Out of stock less than 60 days",AC20>=150,"Out of stock more than 150 days") | AF20: =VLOOKUP(C20,'Data Products'!$A:$J,10,0) | AG20: =AF20*F20 | AH20: =IF(J20<=90,F20,0) | AI20: cần đầu tháng 9 có hàng mới
A21: 18 | B21: Active | C21: 1DTHATMF05010 | D21: 1DTHATMF05010 | E21: 1ETHATMF05010 | F21: 7632 | G21: 7621 | I21: =VLOOKUP(C21,'Data Products'!$A:$B,2,0) | J21: =IFERROR(I21-TODAY(),"") | K21: 45847 | L21: =TODAY()-K21 | M21: 518 | N21: 854 | R21: 0 | S21: 0 | T21: 113 | U21: 106 | V21: 1097 | W21: 1097 | X21: 5 | Y21: 0 | Z21: 0 | AA21: 0 | AB21: =N21/30 | AC21: =IFERROR(F21/AB21,"-") | AD21: =IFERROR(TODAY()+AC21,"-") | AE21: =_xlfn.IFS(AC21="-","Not sold yet",AND(AC21<=150,AC21>60),"Out of stock more than 60 days",AC21<=60,"Out of stock less than 60 days",AC21>=150,"Out of stock more than 150 days") | AF21: =VLOOKUP(C21,'Data Products'!$A:$J,10,0) | AG21: =AF21*F21 | AH21: =IF(J21<=90,F21,0) | AI21: cần đầu tháng 9 có hàng mới
A22: 19 | B22: Active | C22: 1DTHATMF01507 | D22: 1DTHATMF01507 | E22: 1ETHATMF01507 | F22: 4155 | G22: 4150 | I22: =VLOOKUP(C22,'Data Products'!$A:$B,2,0) | J22: =IFERROR(I22-TODAY(),"") | K22: 45847 | L22: =TODAY()-K22 | M22: 738 | N22: 2961 | R22: 0 | S22: 0 | T22: 154 | U22: 154 | V22: 310 | W22: 310 | X22: 0 | Y22: 0 | Z22: 0 | AA22: 0 | AB22: =N22/30 | AC22: =IFERROR(F22/AB22,"-") | AD22: =IFERROR(TODAY()+AC22,"-") | AE22: =_xlfn.IFS(AC22="-","Not sold yet",AND(AC22<=150,AC22>60),"Out of stock more than 60 days",AC22<=60,"Out of stock less than 60 days",AC22>=150,"Out of stock more than 150 days") | AF22: =VLOOKUP(C22,'Data Products'!$A:$J,10,0) | AG22: =AF22*F22 | AH22: =IF(J22<=90,F22,0) | AI22: pass quý 1 push lại
A23: 20 | B23: Temporary | C23: CNMCU15GBFY30D | D23: CNMCU15GBFY30D | E23: CNMCU15GBFY30D | F23: 1500 | G23: 1500 | I23: =VLOOKUP(C23,'Data Products'!$A:$B,2,0) | J23: =IFERROR(I23-TODAY(),"") | K23: 45416 | L23: =TODAY()-K23 | M23: 0 | N23: 0 | AB23: =N23/30 | AC23: =IFERROR(F23/AB23,"-") | AD23: =IFERROR(TODAY()+AC23,"-") | AE23: =_xlfn.IFS(AC23="-","Not sold yet",AND(AC23<=150,AC23>60),"Out of stock more than 60 days",AC23<=60,"Out of stock less than 60 days",AC23>=150,"Out of stock more than 150 days") | AF23: =VLOOKUP(C23,'Data Products'!$A:$J,10,0) | AG23: =AF23*F23
A24: 21 | B24: Temporary | C24: CNMCU10GBFY15D | D24: CNMCU10GBFY15D | E24: CNMCU10GBFY15D | F24: 2000 | G24: 2000 | I24: =VLOOKUP(C24,'Data Products'!$A:$B,2,0) | J24: =IFERROR(I24-TODAY(),"") | K24: 45417 | L24: =TODAY()-K24 | M24: 0 | N24: 0 | AB24: =N24/30 | AC24: =IFERROR(F24/AB24,"-") | AD24: =IFERROR(TODAY()+AC24,"-") | AE24: =_xlfn.IFS(AC24="-","Not sold yet",AND(AC24<=150,AC24>60),"Out of stock more than 60 days",AC24<=60,"Out of stock less than 60 days",AC24>=150,"Out of stock more than 150 days") | AF24: =VLOOKUP(C24,'Data Products'!$A:$J,10,0) | AG24: =AF24*F24
AE25: Total stock with retail price | AF25: =AG25/$AG$25 | AG25: =SUM(AG4:AG24) | AH25: =SUM(AH4:AH24) | AI25: =SUM(AI4:AI24)
AE26: Out of stock less than 60 days | AF26: =AG26/$AG$25 | AG26: =SUMIFS($AG$4:$AG$24,$AE$4:$AE$24,$AE$26)
AE27: Not sold yet | AF27: =AG27/$AG$25 | AG27: =SUMIFS($AG$4:$AG$24,$AE$4:$AE$24,AE27)
AE28: Out of stock more than 60 days | AF28: =AG28/$AG$25 | AG28: =SUMIFS($AG$4:$AG$24,$AE$4:$AE$24,AE28)
AE29: Out of stock more than 150 days | AF29: =AG29/$AG$25 | AG29: =SUMIFS($AG$4:$AG$24,$AE$4:$AE$24,AE29)
AE30: Near Expiration Inventory | AF30: =AVERAGE(AE29:AC27)/AVERAGE(AE29:AC27) | AG30: =SUMIF($AC$4:$AC$24,"<90",AG4:AG24)
A32: ESIM VN | B32: Status | C32: SKU | D32: SKU (mới) | F32: Total Inventory | H32: Quantity | I32: Expiration | J32: Expired date left | K32: Date of Import | L32: Inventory Age | M32: Last 15 days | N32: Last 30 days | O32: Safety Stock | P32: Reorder Point | Q32: Vendor | AB32: Avg Pcs/day | AC32: DOI (Số ngày tồn kho) | AD32: Ngày hết hàng dự kiến | AE32: Đánh giá | AF32: Retail Price | AG32: Total retail price | AH32: Near Expiration Inventory | AI32: OPS | AJ32: Telco | AK32: OD | AL32: B2B | AM32: B2C | AN32: Marketing
A33: No. | F33: Stock | G33: Available for sale | M33: Sold | N33: Sold
A34: 1 | B34: Inactive | C34: 3HKDATAPOOLESIM | F34: 1610 | G34: 1610 | I34: =VLOOKUP(C34,'Data Products'!$A:$J,2,0) | J34: =IFERROR(I34-TODAY(),"") | K34: 45840 | L34: =TODAY()-K34 | M34: 0 | N34: 0 | Q34: 3HK | AB34: =N34/30 | AC34: =IFERROR(F34/AB34,"-") | AD34: =IFERROR(TODAY()+AC34,"-") | AE34: =_xlfn.IFS(AC34="-","Not sold yet",AND(AC34<=150,AC34>60),"Out of stock more than 60 days",AC34<=60,"Out of stock less than 60 days",AC34>=150,"Out of stock more than 150 days") | AF34: =VLOOKUP(C34,'Data Products'!$A:$J,10,0) | AG34: =AF34*F34 | AI34: treo chờ xử lý sau
A35: 2 | B35: Inactive | C35: EEURBGFX15GB15D | F35: 0 | G35: 0 | I35: =VLOOKUP(C35,'Data Products'!$A:$J,2,0) | J35: =IFERROR(I35-TODAY(),"") | K35: 45841 | L35: =TODAY()-K35 | M35: 0 | N35: 0 | Q35: Bouygues | AB35: =N35/30 | AC35: =IFERROR(F35/AB35,"-") | AD35: =IFERROR(TODAY()+AC35,"-") | AE35: =_xlfn.IFS(AC35="-","Not sold yet",AND(AC35<=150,AC35>60),"Out of stock more than 60 days",AC35<=60,"Out of stock less than 60 days",AC35>=150,"Out of stock more than 150 days") | AF35: =VLOOKUP(C35,'Data Products'!$A:$J,10,0) | AG35: =AF35*F35 | AH35: =IF(J35<=90,F35,0)
A36: 3 | B36: Inactive | C36: EEURBGFX20GB15D | F36: 0 | G36: 0 | I36: =VLOOKUP(C36,'Data Products'!$A:$J,2,0) | J36: =IFERROR(I36-TODAY(),"") | K36: 45842 | L36: =TODAY()-K36 | M36: 0 | N36: 0 | Q36: Bouygues | AB36: =N36/30 | AC36: =IFERROR(F36/AB36,"-") | AD36: =IFERROR(TODAY()+AC36,"-") | AE36: =_xlfn.IFS(AC36="-","Not sold yet",AND(AC36<=150,AC36>60),"Out of stock more than 60 days",AC36<=60,"Out of stock less than 60 days",AC36>=150,"Out of stock more than 150 days") | AF36: =VLOOKUP(C36,'Data Products'!$A:$J,10,0) | AG36: =AF36*F36 | AH36: =IF(J36<=90,F36,0)
A37: 4 | B37: Inactive | C37: EEURBGFX30GB30D | F37: 0 | G37: 0 | I37: =VLOOKUP(C37,'Data Products'!$A:$J,2,0) | J37: =IFERROR(I37-TODAY(),"") | K37: 45843 | L37: =TODAY()-K37 | M37: 0 | N37: 0 | Q37: Bouygues | AB37: =N37/30 | AC37: =IFERROR(F37/AB37,"-") | AD37: =IFERROR(TODAY()+AC37,"-") | AE37: =_xlfn.IFS(AC37="-","Not sold yet",AND(AC37<=150,AC37>60),"Out of stock more than 60 days",AC37<=60,"Out of stock less than 60 days",AC37>=150,"Out of stock more than 150 days") | AF37: =VLOOKUP(C37,'Data Products'!$A:$J,10,0) | AG37: =AF37*F37 | AH37: =IF(J37<=90,F37,0)
A38: 5 | B38: Deleted | C38: ECMTCUFY05GB05D | F38: 0 | G38: 0 | I38: =VLOOKUP(C38,'Data Products'!$A:$J,2,0) | J38: =IFERROR(I38-TODAY(),"") | K38: 45844 | L38: =TODAY()-K38 | M38: 0 | N38: 0 | Q38: CU | AB38: =N38/30 | AC38: =IFERROR(F38/AB38,"-") | AD38: =IFERROR(TODAY()+AC38,"-") | AE38: =_xlfn.IFS(AC38="-","Not sold yet",AND(AC38<=150,AC38>60),"Out of stock more than 60 days",AC38<=60,"Out of stock less than 60 days",AC38>=150,"Out of stock more than 150 days") | AF38: =VLOOKUP(C38,'Data Products'!$A:$J,10,0) | AG38: =AF38*F38 | AH38: =IF(J38<=90,F38,0) | AK38: 200
A39: 6 | B39: Temporary | C39: ECNMCUFX15GB30D | D39: 1CCNMCUY01530 | F39: 0 | G39: 0 | I39: =VLOOKUP(C39,'Data Products'!$A:$J,2,0) | J39: =IFERROR(I39-TODAY(),"") | K39: 45845 | L39: =TODAY()-K39 | M39: 0 | N39: 0 | Q39: CU | AB39: =N39/30 | AC39: =IFERROR(F39/AB39,"-") | AD39: =IFERROR(TODAY()+AC39,"-") | AE39: =_xlfn.IFS(AC39="-","Not sold yet",AND(AC39<=150,AC39>60),"Out of stock more than 60 days",AC39<=60,"Out of stock less than 60 days",AC39>=150,"Out of stock more than 150 days") | AF39: =VLOOKUP(C39,'Data Products'!$A:$J,10,0) | AG39: =AF39*F39 | AH39: =IF(J39<=90,F39,0)
A40: 7 | B40: Temporary | C40: 1CKORCUF01005 | D40: 1CKORCUF01005 | F40: 0 | G40: 0 | I40: =VLOOKUP(C40,'Data Products'!$A:$J,2,0) | J40: =IFERROR(I40-TODAY(),"") | K40: 45846 | L40: =TODAY()-K40 | M40: 0 | N40: 0 | Q40: CU | AB40: =N40/30 | AC40: =IFERROR(F40/AB40,"-") | AD40: =IFERROR(TODAY()+AC40,"-") | AE40: =_xlfn.IFS(AC40="-","Not sold yet",AND(AC40<=150,AC40>60),"Out of stock more than 60 days",AC40<=60,"Out of stock less than 60 days",AC40>=150,"Out of stock more than 150 days") | AF40: =VLOOKUP(C40,'Data Products'!$A:$J,10,0) | AG40: =AF40*F40 | AH40: =IF(J40<=90,F40,0)
A41: 8 | B41: Temporary | C41: EKORCUFY30GB30D | F41: 0 | G41: 0 | I41: =VLOOKUP(C41,'Data Products'!$A:$J,2,0) | J41: =IFERROR(I41-TODAY(),"") | K41: 45847 | L41: =TODAY()-K41 | M41: 0 | N41: 0 | Q41: CU | AB41: =N41/30 | AC41: =IFERROR(F41/AB41,"-") | AD41: =IFERROR(TODAY()+AC41,"-") | AE41: =_xlfn.IFS(AC41="-","Not sold yet",AND(AC41<=150,AC41>60),"Out of stock more than 60 days",AC41<=60,"Out of stock less than 60 days",AC41>=150,"Out of stock more than 150 days") | AF41: =VLOOKUP(C41,'Data Products'!$A:$J,10,0) | AG41: =AF41*F41 | AH41: =IF(J41<=90,F41,0)
A42: 9 | B42: Temporary | C42: EA10CUFY05GB08D | F42: 0 | G42: 0 | I42: =VLOOKUP(C42,'Data Products'!$A:$J,2,0) | J42: =IFERROR(I42-TODAY(),"") | K42: 45848 | L42: =TODAY()-K42 | M42: 0 | N42: 0 | Q42: CU | AB42: =N42/30 | AC42: =IFERROR(F42/AB42,"-") | AD42: =IFERROR(TODAY()+AC42,"-") | AE42: =_xlfn.IFS(AC42="-","Not sold yet",AND(AC42<=150,AC42>60),"Out of stock more than 60 days",AC42<=60,"Out of stock less than 60 days",AC42>=150,"Out of stock more than 150 days") | AF42: =VLOOKUP(C42,'Data Products'!$A:$J,10,0) | AG42: =AF42*F42 | AH42: =IF(J42<=90,F42,0)
A43: 10 | B43: Temporary | C43: ECMTCUFY07GB08D | F43: 0 | G43: 0 | I43: =VLOOKUP(C43,'Data Products'!$A:$J,2,0) | J43: =IFERROR(I43-TODAY(),"") | K43: 45849 | L43: =TODAY()-K43 | M43: 0 | N43: 0 | Q43: CU | AB43: =N43/30 | AC43: =IFERROR(F43/AB43,"-") | AD43: =IFERROR(TODAY()+AC43,"-") | AE43: =_xlfn.IFS(AC43="-","Not sold yet",AND(AC43<=150,AC43>60),"Out of stock more than 60 days",AC43<=60,"Out of stock less than 60 days",AC43>=150,"Out of stock more than 150 days") | AF43: =VLOOKUP(C43,'Data Products'!$A:$J,10,0) | AG43: =AF43*F43 | AH43: =IF(J43<=90,F43,0) | AK43: 150
A44: 11 | B44: Inactive | C44: ECNMCUFY05GB05D | F44: 0 | G44: 0 | I44: =VLOOKUP(C44,'Data Products'!$A:$J,2,0) | J44: =IFERROR(I44-TODAY(),"") | K44: 45850 | L44: =TODAY()-K44 | M44: 0 | N44: 0 | Q44: CU | AB44: =N44/30 | AC44: =IFERROR(F44/AB44,"-") | AD44: =IFERROR(TODAY()+AC44,"-") | AE44: =_xlfn.IFS(AC44="-","Not sold yet",AND(AC44<=150,AC44>60),"Out of stock more than 60 days",AC44<=60,"Out of stock less than 60 days",AC44>=150,"Out of stock more than 150 days") | AF44: =VLOOKUP(C44,'Data Products'!$A:$J,10,0) | AG44: =AF44*F44 | AH44: =IF(J44<=90,F44,0)
A45: 12 | B45: Temporary | C45: ECNMCUFY07GB08D | D45: 1CCNMCUF00708 | F45: 0 | G45: 0 | I45: =VLOOKUP(C45,'Data Products'!$A:$J,2,0) | J45: =IFERROR(I45-TODAY(),"") | K45: 45851 | L45: =TODAY()-K45 | M45: 0 | N45: 0 | Q45: CU | AB45: =N45/30 | AC45: =IFERROR(F45/AB45,"-") | AD45: =IFERROR(TODAY()+AC45,"-") | AE45: =_xlfn.IFS(AC45="-","Not sold yet",AND(AC45<=150,AC45>60),"Out of stock more than 60 days",AC45<=60,"Out of stock less than 60 days",AC45>=150,"Out of stock more than 150 days") | AF45: =VLOOKUP(C45,'Data Products'!$A:$J,10,0) | AG45: =AF45*F45 | AH45: =IF(J45<=90,F45,0)
A46: 13 | B46: Temporary | C46: EARECUFY04GB30D | F46: 0 | G46: 0 | I46: =VLOOKUP(C46,'Data Products'!$A:$J,2,0) | J46: =IFERROR(I46-TODAY(),"") | K46: 45852 | L46: =TODAY()-K46 | M46: 0 | N46: 0 | Q46: CU | AB46: =N46/30 | AC46: =IFERROR(F46/AB46,"-") | AD46: =IFERROR(TODAY()+AC46,"-") | AE46: =_xlfn.IFS(AC46="-","Not sold yet",AND(AC46<=150,AC46>60),"Out of stock more than 60 days",AC46<=60,"Out of stock less than 60 days",AC46>=150,"Out of stock more than 150 days") | AF46: =VLOOKUP(C46,'Data Products'!$A:$J,10,0) | AG46: =AF46*F46 | AH46: =IF(J46<=90,F46,0)
A47: 14 | B47: Inactive | C47: EKORCUFY20GB08D | D47: 1CKORCUF02008 | F47: 0 | G47: 0 | I47: =VLOOKUP(C47,'Data Products'!$A:$J,2,0) | J47: =IFERROR(I47-TODAY(),"") | K47: 45853 | L47: =TODAY()-K47 | M47: 0 | N47: 0 | Q47: CU | AB47: =N47/30 | AC47: =IFERROR(F47/AB47,"-") | AD47: =IFERROR(TODAY()+AC47,"-") | AE47: =_xlfn.IFS(AC47="-","Not sold yet",AND(AC47<=150,AC47>60),"Out of stock more than 60 days",AC47<=60,"Out of stock less than 60 days",AC47>=150,"Out of stock more than 150 days") | AF47: =VLOOKUP(C47,'Data Products'!$A:$J,10,0) | AG47: =AF47*F47 | AH47: =IF(J47<=90,F47,0)
A48: 15 | B48: Inactive | C48: ECNMCUFX10GB15D | F48: 0 | G48: 0 | I48: =VLOOKUP(C48,'Data Products'!$A:$J,2,0) | J48: =IFERROR(I48-TODAY(),"") | K48: 45854 | L48: =TODAY()-K48 | M48: 0 | N48: 0 | Q48: CU | AB48: =N48/30 | AC48: =IFERROR(F48/AB48,"-") | AD48: =IFERROR(TODAY()+AC48,"-") | AE48: =_xlfn.IFS(AC48="-","Not sold yet",AND(AC48<=150,AC48>60),"Out of stock more than 60 days",AC48<=60,"Out of stock less than 60 days",AC48>=150,"Out of stock more than 150 days") | AF48: =VLOOKUP(C48,'Data Products'!$A:$J,10,0) | AG48: =AF48*F48 | AH48: =IF(J48<=90,F48,0) | AK48: 340
A49: 16 | B49: Inactive | C49: ETHDD1FY50GB10D | F49: 0 | G49: 0 | I49: =VLOOKUP(C49,'Data Products'!$A:$J,2,0) | J49: =IFERROR(I49-TODAY(),"") | K49: 45855 | L49: =TODAY()-K49 | M49: 0 | N49: 0 | Q49: Dtac | AB49: =N49/30 | AC49: =IFERROR(F49/AB49,"-") | AD49: =IFERROR(TODAY()+AC49,"-") | AE49: =_xlfn.IFS(AC49="-","Not sold yet",AND(AC49<=150,AC49>60),"Out of stock more than 60 days",AC49<=60,"Out of stock less than 60 days",AC49>=150,"Out of stock more than 150 days") | AF49: =VLOOKUP(C49,'Data Products'!$A:$J,10,0) | AG49: =AF49*F49 | AH49: =IF(J49<=90,F49,0)
A50: 17 | B50: Inactive | C50: ETHDDTFY50GB10D | F50: 0 | G50: 0 | I50: =VLOOKUP(C50,'Data Products'!$A:$J,2,0) | J50: =IFERROR(I50-TODAY(),"") | K50: 45856 | L50: =TODAY()-K50 | M50: 0 | N50: 0 | Q50: Dtac | AB50: =N50/30 | AC50: =IFERROR(F50/AB50,"-") | AD50: =IFERROR(TODAY()+AC50,"-") | AE50: =_xlfn.IFS(AC50="-","Not sold yet",AND(AC50<=150,AC50>60),"Out of stock more than 60 days",AC50<=60,"Out of stock less than 60 days",AC50>=150,"Out of stock more than 150 days") | AF50: =VLOOKUP(C50,'Data Products'!$A:$J,10,0) | AG50: =AF50*F50 | AH50: =IF(J50<=90,F50,0) | AK50: 3620
A51: 18 | B51: Inactive | C51: ETHDDTFY15GB07D | F51: 0 | G51: 0 | I51: =VLOOKUP(C51,'Data Products'!$A:$J,2,0) | J51: =IFERROR(I51-TODAY(),"") | K51: 45857 | L51: =TODAY()-K51 | M51: 0 | N51: 0 | Q51: Dtac | AB51: =N51/30 | AC51: =IFERROR(F51/AB51,"-") | AD51: =IFERROR(TODAY()+AC51,"-") | AE51: =_xlfn.IFS(AC51="-","Not sold yet",AND(AC51<=150,AC51>60),"Out of stock more than 60 days",AC51<=60,"Out of stock less than 60 days",AC51>=150,"Out of stock more than 150 days") | AF51: =VLOOKUP(C51,'Data Products'!$A:$J,10,0) | AG51: =AF51*F51 | AH51: =IF(J51<=90,F51,0)
A52: 19 | B52: Active | C52: ETHATMFY50GB10D | D52: 1CTHATMF05010 | E52: 1CTHATMF05010 | F52: 0 | G52: 0 | I52: =VLOOKUP(C52,'Data Products'!$A:$J,2,0) | J52: =IFERROR(I52-TODAY(),"") | K52: 45858 | L52: =TODAY()-K52 | M52: 0 | N52: 0 | Q52: TrueMove | AB52: =N52/30 | AC52: =IFERROR(F52/AB52,"-") | AD52: =IFERROR(TODAY()+AC52,"-") | AE52: =_xlfn.IFS(AC52="-","Not sold yet",AND(AC52<=150,AC52>60),"Out of stock more than 60 days",AC52<=60,"Out of stock less than 60 days",AC52>=150,"Out of stock more than 150 days") | AF52: =VLOOKUP(C52,'Data Products'!$A:$J,10,0) | AG52: =AF52*F52 | AH52: =IF(J52<=90,F52,0) | AI52: mốt có hàng của CB nhé
A53: 20 | B53: Inactive | C53: ETHATMFY15GB07D | D53: 1CTHATMF01507 | E53: 1CTHATMF01507 | F53: 8 | G53: 8 | I53: =VLOOKUP(C53,'Data Products'!$A:$J,2,0) | J53: =IFERROR(I53-TODAY(),"") | K53: 45859 | L53: =TODAY()-K53 | M53: 0 | N53: 0 | Q53: TrueMove | AB53: =N53/30 | AC53: =IFERROR(F53/AB53,"-") | AD53: =IFERROR(TODAY()+AC53,"-") | AE53: =_xlfn.IFS(AC53="-","Not sold yet",AND(AC53<=150,AC53>60),"Out of stock more than 60 days",AC53<=60,"Out of stock less than 60 days",AC53>=150,"Out of stock more than 150 days") | AF53: =VLOOKUP(C53,'Data Products'!$A:$J,10,0) | AG53: =AF53*F53 | AH53: =IF(J53<=90,F53,0) | AI53: dự kiến cuối tháng 4 có hàng
A54: 21 | B54: Inactive | C54: ETHDCBFY50GB10D | D54: 2CTHACBF05010 | E54: 2CTHACBF05010 | F54: 0 | G54: 0 | I54: =VLOOKUP(C54,'Data Products'!$A:$J,2,0) | J54: =IFERROR(I54-TODAY(),"") | K54: 45860 | L54: =TODAY()-K54 | M54: 0 | N54: 0 | Q54: Commbitz | AB54: =N54/30 | AC54: =IFERROR(F54/AB54,"-") | AD54: =IFERROR(TODAY()+AC54,"-") | AE54: =_xlfn.IFS(AC54="-","Not sold yet",AND(AC54<=150,AC54>60),"Out of stock more than 60 days",AC54<=60,"Out of stock less than 60 days",AC54>=150,"Out of stock more than 150 days") | AF54: =VLOOKUP(C54,'Data Products'!$A:$J,10,0) | AG54: =AF54*F54 | AH54: =IF(J54<=90,F54,0)
A55: 22 | B55: Temporary | C55: 2CTHACBF05010 | D55: 2CTHACBF05010 | E55: 2CTHACBF05010 | F55: 2 | G55: 2 | I55: =VLOOKUP(C55,'Data Products'!$A:$J,2,0) | J55: =IFERROR(I55-TODAY(),"") | K55: 45861 | L55: =TODAY()-K55 | M55: 0 | N55: 0 | Q55: Commbitzz | AB55: =N55/30 | AC55: =IFERROR(F55/AB55,"-") | AD55: =IFERROR(TODAY()+AC55,"-") | AE55: =_xlfn.IFS(AC55="-","Not sold yet",AND(AC55<=150,AC55>60),"Out of stock more than 60 days",AC55<=60,"Out of stock less than 60 days",AC55>=150,"Out of stock more than 150 days") | AF55: =VLOOKUP(C55,'Data Products'!$A:$J,10,0) | AG55: =AF55*F55 | AI55: bán hết sẽ clear tồn
A56: 23 | B56: Inactive | C56: ETHDYDFY50GB10D | F56: 0 | G56: 0 | I56: =VLOOKUP(C56,'Data Products'!$A:$J,2,0) | J56: =IFERROR(I56-TODAY(),"") | K56: 45862 | L56: =TODAY()-K56 | M56: 0 | N56: 0 | Q56: YiDao | AB56: =N56/30 | AC56: =IFERROR(F56/AB56,"-") | AD56: =IFERROR(TODAY()+AC56,"-") | AE56: =_xlfn.IFS(AC56="-","Not sold yet",AND(AC56<=150,AC56>60),"Out of stock more than 60 days",AC56<=60,"Out of stock less than 60 days",AC56>=150,"Out of stock more than 150 days") | AF56: =VLOOKUP(C56,'Data Products'!$A:$J,10,0) | AG56: =AF56*F56 | AH56: =IF(J56<=90,F56,0)
A57: 24 | B57: Inactive | C57: ESGP3HFY15GB30D | F57: 0 | G57: 0 | I57: =VLOOKUP(C57,'Data Products'!$A:$J,2,0) | J57: =IFERROR(I57-TODAY(),"") | K57: 45863 | L57: =TODAY()-K57 | M57: 0 | N57: 0 | Q57: 3HK | AB57: =N57/30 | AC57: =IFERROR(F57/AB57,"-") | AD57: =IFERROR(TODAY()+AC57,"-") | AE57: =_xlfn.IFS(AC57="-","Not sold yet",AND(AC57<=150,AC57>60),"Out of stock more than 60 days",AC57<=60,"Out of stock less than 60 days",AC57>=150,"Out of stock more than 150 days") | AF57: =VLOOKUP(C57,'Data Products'!$A:$J,10,0) | AG57: =AF57*F57 | AH57: =IF(J57<=90,F57,0)
A58: 25 | B58: Inactive | C58: ESGP3HFY30GB30D | F58: 0 | G58: 0 | I58: =VLOOKUP(C58,'Data Products'!$A:$J,2,0) | J58: =IFERROR(I58-TODAY(),"") | K58: 45864 | L58: =TODAY()-K58 | M58: 0 | N58: 0 | Q58: 3HK | AB58: =N58/30 | AC58: =IFERROR(F58/AB58,"-") | AD58: =IFERROR(TODAY()+AC58,"-") | AE58: =_xlfn.IFS(AC58="-","Not sold yet",AND(AC58<=150,AC58>60),"Out of stock more than 60 days",AC58<=60,"Out of stock less than 60 days",AC58>=150,"Out of stock more than 150 days") | AF58: =VLOOKUP(C58,'Data Products'!$A:$J,10,0) | AG58: =AF58*F58 | AH58: =IF(J58<=90,F58,0)
A59: 26 | B59: Inactive | C59: EJPNKDPYUNLI04D | F59: 0 | G59: 0 | H59: 200 HSD 21/06/2025 300 HSD 20/08/2025 | I59: =VLOOKUP(C59,'Data Products'!$A:$J,2,0) | J59: =IFERROR(I59-TODAY(),"") | K59: 45865 | L59: =TODAY()-K59 | M59: 0 | N59: 0 | Q59: KDDI | AB59: =N59/30 | AC59: =IFERROR(F59/AB59,"-") | AD59: =IFERROR(TODAY()+AC59,"-") | AE59: =_xlfn.IFS(AC59="-","Not sold yet",AND(AC59<=150,AC59>60),"Out of stock more than 60 days",AC59<=60,"Out of stock less than 60 days",AC59>=150,"Out of stock more than 150 days") | AF59: =VLOOKUP(C59,'Data Products'!$A:$J,10,0) | AG59: =AF59*F59 | AH59: =IF(J59<=90,F59,0) | AK59: 50
A60: 27 | B60: Inactive | C60: EJPNKDPYUNLI07D | F60: 0 | G60: 0 | I60: =VLOOKUP(C60,'Data Products'!$A:$J,2,0) | J60: =IFERROR(I60-TODAY(),"") | K60: 45866 | L60: =TODAY()-K60 | M60: 0 | N60: 0 | Q60: KDDI | AB60: =N60/30 | AC60: =IFERROR(F60/AB60,"-") | AD60: =IFERROR(TODAY()+AC60,"-") | AE60: =_xlfn.IFS(AC60="-","Not sold yet",AND(AC60<=150,AC60>60),"Out of stock more than 60 days",AC60<=60,"Out of stock less than 60 days",AC60>=150,"Out of stock more than 150 days") | AF60: =VLOOKUP(C60,'Data Products'!$A:$J,10,0) | AG60: =AF60*F60 | AH60: =IF(J60<=90,F60,0) | AK60: 80
A61: 28 | B61: Inactive | C61: EJPNKDPYUNLI10D | F61: 0 | G61: 0 | I61: =VLOOKUP(C61,'Data Products'!$A:$J,2,0) | J61: =IFERROR(I61-TODAY(),"") | K61: 45867 | L61: =TODAY()-K61 | M61: 0 | N61: 0 | Q61: KDDI | AB61: =N61/30 | AC61: =IFERROR(F61/AB61,"-") | AD61: =IFERROR(TODAY()+AC61,"-") | AE61: =_xlfn.IFS(AC61="-","Not sold yet",AND(AC61<=150,AC61>60),"Out of stock more than 60 days",AC61<=60,"Out of stock less than 60 days",AC61>=150,"Out of stock more than 150 days") | AF61: =VLOOKUP(C61,'Data Products'!$A:$J,10,0) | AG61: =AF61*F61 | AH61: =IF(J61<=90,F61,0) | AK61: 60
A62: 29 | B62: Inactive | C62: EJPNKDFY20GB07D | F62: 0 | G62: 0 | H62: 100 HSD 20/08/2025 | I62: =VLOOKUP(C62,'Data Products'!$A:$J,2,0) | J62: =IFERROR(I62-TODAY(),"") | K62: 45868 | L62: =TODAY()-K62 | M62: 0 | N62: 0 | Q62: KDDI | AB62: =N62/30 | AC62: =IFERROR(F62/AB62,"-") | AD62: =IFERROR(TODAY()+AC62,"-") | AE62: =_xlfn.IFS(AC62="-","Not sold yet",AND(AC62<=150,AC62>60),"Out of stock more than 60 days",AC62<=60,"Out of stock less than 60 days",AC62>=150,"Out of stock more than 150 days") | AF62: =VLOOKUP(C62,'Data Products'!$A:$J,10,0) | AG62: =AF62*F62 | AH62: =IF(J62<=90,F62,0) | AK62: 40
A63: 30 | B63: Inactive | C63: EJPNK1PYUNLI07D | F63: 0 | G63: 0 | I63: =VLOOKUP(C63,'Data Products'!$A:$J,2,0) | J63: =IFERROR(I63-TODAY(),"") | K63: 45869 | L63: =TODAY()-K63 | M63: 0 | N63: 0 | Q63: KDDI | AB63: =N63/30 | AC63: =IFERROR(F63/AB63,"-") | AD63: =IFERROR(TODAY()+AC63,"-") | AE63: =_xlfn.IFS(AC63="-","Not sold yet",AND(AC63<=150,AC63>60),"Out of stock more than 60 days",AC63<=60,"Out of stock less than 60 days",AC63>=150,"Out of stock more than 150 days") | AF63: =VLOOKUP(C63,'Data Products'!$A:$J,10,0) | AG63: =AF63*F63 | AH63: =IF(J63<=90,F63,0)
A64: 31 | B64: Inactive | C64: EJPNKDPYUNLI15D | F64: 0 | G64: 0 | I64: =VLOOKUP(C64,'Data Products'!$A:$J,2,0) | J64: =IFERROR(I64-TODAY(),"") | K64: 45870 | L64: =TODAY()-K64 | M64: 0 | N64: 0 | Q64: KDDI | AB64: =N64/30 | AC64: =IFERROR(F64/AB64,"-") | AD64: =IFERROR(TODAY()+AC64,"-") | AE64: =_xlfn.IFS(AC64="-","Not sold yet",AND(AC64<=150,AC64>60),"Out of stock more than 60 days",AC64<=60,"Out of stock less than 60 days",AC64>=150,"Out of stock more than 150 days") | AF64: =VLOOKUP(C64,'Data Products'!$A:$J,10,0) | AG64: =AF64*F64 | AH64: =IF(J64<=90,F64,0)
A65: 32 | B65: Inactive | C65: EKORSBPXUNLI05D | F65: 0 | G65: 0 | I65: =VLOOKUP(C65,'Data Products'!$A:$J,2,0) | J65: =IFERROR(I65-TODAY(),"") | K65: 45871 | L65: =TODAY()-K65 | M65: 0 | N65: 0 | Q65: Softbay | AB65: =N65/30 | AC65: =IFERROR(F65/AB65,"-") | AD65: =IFERROR(TODAY()+AC65,"-") | AE65: =_xlfn.IFS(AC65="-","Not sold yet",AND(AC65<=150,AC65>60),"Out of stock more than 60 days",AC65<=60,"Out of stock less than 60 days",AC65>=150,"Out of stock more than 150 days") | AF65: =VLOOKUP(C65,'Data Products'!$A:$J,10,0) | AG65: =AF65*F65 | AH65: =IF(J65<=90,F65,0)
A66: 33 | B66: Inactive | C66: EKORSBPXUNLI07D | F66: 0 | G66: 0 | I66: =VLOOKUP(C66,'Data Products'!$A:$J,2,0) | J66: =IFERROR(I66-TODAY(),"") | K66: 45872 | L66: =TODAY()-K66 | M66: 0 | N66: 0 | Q66: Softbay | AB66: =N66/30 | AC66: =IFERROR(F66/AB66,"-") | AD66: =IFERROR(TODAY()+AC66,"-") | AE66: =_xlfn.IFS(AC66="-","Not sold yet",AND(AC66<=150,AC66>60),"Out of stock more than 60 days",AC66<=60,"Out of stock less than 60 days",AC66>=150,"Out of stock more than 150 days") | AF66: =VLOOKUP(C66,'Data Products'!$A:$J,10,0) | AG66: =AF66*F66 | AH66: =IF(J66<=90,F66,0)
A67: 34 | B67: Inactive | C67: EKORSBPXUNLI10D | F67: 0 | G67: 0 | I67: =VLOOKUP(C67,'Data Products'!$A:$J,2,0) | J67: =IFERROR(I67-TODAY(),"") | K67: 45873 | L67: =TODAY()-K67 | M67: 0 | N67: 0 | Q67: Softbay | AB67: =N67/30 | AC67: =IFERROR(F67/AB67,"-") | AD67: =IFERROR(TODAY()+AC67,"-") | AE67: =_xlfn.IFS(AC67="-","Not sold yet",AND(AC67<=150,AC67>60),"Out of stock more than 60 days",AC67<=60,"Out of stock less than 60 days",AC67>=150,"Out of stock more than 150 days") | AF67: =VLOOKUP(C67,'Data Products'!$A:$J,10,0) | AG67: =AF67*F67 | AH67: =IF(J67<=90,F67,0)
A68: 35 | B68: Active | C68: EVNMVMPX02GB20D | D68: 11VNMVMZ00220 | E68: 11VNMVMZ00220 | F68: 0 | G68: 0 | I68: =VLOOKUP(C68,'Data Products'!$A:$J,2,0) | J68: =IFERROR(I68-TODAY(),"") | K68: 45874 | L68: =TODAY()-K68 | M68: 0 | N68: 0 | Q68: VietnamMobile | AB68: =N68/30 | AC68: =IFERROR(F68/AB68,"-") | AD68: =IFERROR(TODAY()+AC68,"-") | AE68: =_xlfn.IFS(AC68="-","Not sold yet",AND(AC68<=150,AC68>60),"Out of stock more than 60 days",AC68<=60,"Out of stock less than 60 days",AC68>=150,"Out of stock more than 150 days") | AF68: =VLOOKUP(C68,'Data Products'!$A:$J,10,0) | AG68: =AF68*F68 | AH68: =IF(J68<=90,F68,0) | AK68: 50
A69: 36 | B69: Deleted | C69: EUSAVMFY05GB03D | F69: 0 | G69: 0 | I69: =VLOOKUP(C69,'Data Products'!$A:$J,2,0) | J69: =IFERROR(I69-TODAY(),"") | K69: 45875 | L69: =TODAY()-K69 | M69: 0 | N69: 0 | Q69: VietnamMobile | AB69: =N69/30 | AC69: =IFERROR(F69/AB69,"-") | AD69: =IFERROR(TODAY()+AC69,"-") | AE69: =_xlfn.IFS(AC69="-","Not sold yet",AND(AC69<=150,AC69>60),"Out of stock more than 60 days",AC69<=60,"Out of stock less than 60 days",AC69>=150,"Out of stock more than 150 days") | AF69: =VLOOKUP(C69,'Data Products'!$A:$J,10,0) | AG69: =AF69*F69 | AH69: =IF(J69<=90,F69,0)
A70: 37 | B70: Deleted | C70: EUSAVMFY60GB30D | F70: 0 | G70: 0 | I70: =VLOOKUP(C70,'Data Products'!$A:$J,2,0) | J70: =IFERROR(I70-TODAY(),"") | K70: 45876 | L70: =TODAY()-K70 | M70: 0 | N70: 0 | Q70: VietnamMobile | AB70: =N70/30 | AC70: =IFERROR(F70/AB70,"-") | AD70: =IFERROR(TODAY()+AC70,"-") | AE70: =_xlfn.IFS(AC70="-","Not sold yet",AND(AC70<=150,AC70>60),"Out of stock more than 60 days",AC70<=60,"Out of stock less than 60 days",AC70>=150,"Out of stock more than 150 days") | AF70: =VLOOKUP(C70,'Data Products'!$A:$J,10,0) | AG70: =AF70*F70 | AH70: =IF(J70<=90,F70,0)
A71: 38 | B71: Deleted | C71: EUSAVMFY10GB15D | F71: 0 | G71: 0 | I71: =VLOOKUP(C71,'Data Products'!$A:$J,2,0) | J71: =IFERROR(I71-TODAY(),"") | K71: 45877 | L71: =TODAY()-K71 | M71: 0 | N71: 0 | Q71: VietnamMobile | AB71: =N71/30 | AC71: =IFERROR(F71/AB71,"-") | AD71: =IFERROR(TODAY()+AC71,"-") | AE71: =_xlfn.IFS(AC71="-","Not sold yet",AND(AC71<=150,AC71>60),"Out of stock more than 60 days",AC71<=60,"Out of stock less than 60 days",AC71>=150,"Out of stock more than 150 days") | AF71: =VLOOKUP(C71,'Data Products'!$A:$J,10,0) | AG71: =AF71*F71 | AH71: =IF(J71<=90,F71,0)
A72: 39 | B72: Active | C72: EVNMSFPY03GB15D | D72: 11VNMSFP00315 | E72: 11VNMSFP00315 | F72: 0 | G72: 0 | I72: =VLOOKUP(C72,'Data Products'!$A:$J,2,0) | J72: =IFERROR(I72-TODAY(),"") | K72: 45878 | L72: =TODAY()-K72 | M72: 0 | N72: 0 | Q72: Skyfi | AB72: =N72/30 | AC72: =IFERROR(F72/AB72,"-") | AD72: =IFERROR(TODAY()+AC72,"-") | AE72: =_xlfn.IFS(AC72="-","Not sold yet",AND(AC72<=150,AC72>60),"Out of stock more than 60 days",AC72<=60,"Out of stock less than 60 days",AC72>=150,"Out of stock more than 150 days") | AF72: =VLOOKUP(C72,'Data Products'!$A:$J,10,0) | AG72: =AF72*F72
A73: 40 | B73: Inactive | C73: EVNMMBPX03GB07D | F73: 0 | G73: 0 | I73: =VLOOKUP(C73,'Data Products'!$A:$J,2,0) | J73: =IFERROR(I73-TODAY(),"") | K73: 45879 | L73: =TODAY()-K73 | M73: 0 | N73: 0 | Q73: Mobifone | AB73: =N73/30 | AC73: =IFERROR(F73/AB73,"-") | AD73: =IFERROR(TODAY()+AC73,"-") | AE73: =_xlfn.IFS(AC73="-","Not sold yet",AND(AC73<=150,AC73>60),"Out of stock more than 60 days",AC73<=60,"Out of stock less than 60 days",AC73>=150,"Out of stock more than 150 days") | AF73: =VLOOKUP(C73,'Data Products'!$A:$J,10,0) | AG73: =AF73*F73 | AH73: =IF(J73<=90,F73,0)
A74: 41 | B74: Inactive | C74: EVNMMBPX04GB15D | F74: 0 | G74: 0 | I74: =VLOOKUP(C74,'Data Products'!$A:$J,2,0) | J74: =IFERROR(I74-TODAY(),"") | K74: 45880 | L74: =TODAY()-K74 | M74: 0 | N74: 0 | Q74: Mobifone | AB74: =N74/30 | AC74: =IFERROR(F74/AB74,"-") | AD74: =IFERROR(TODAY()+AC74,"-") | AE74: =_xlfn.IFS(AC74="-","Not sold yet",AND(AC74<=150,AC74>60),"Out of stock more than 60 days",AC74<=60,"Out of stock less than 60 days",AC74>=150,"Out of stock more than 150 days") | AF74: =VLOOKUP(C74,'Data Products'!$A:$J,10,0) | AG74: =AF74*F74 | AH74: =IF(J74<=90,F74,0)
A75: 42 | B75: Inactive | C75: EVNMMBPX05GB15D | F75: 0 | G75: 0 | I75: =VLOOKUP(C75,'Data Products'!$A:$J,2,0) | J75: =IFERROR(I75-TODAY(),"") | K75: 45881 | L75: =TODAY()-K75 | M75: 0 | N75: 0 | Q75: Mobifone | AB75: =N75/30 | AC75: =IFERROR(F75/AB75,"-") | AD75: =IFERROR(TODAY()+AC75,"-") | AE75: =_xlfn.IFS(AC75="-","Not sold yet",AND(AC75<=150,AC75>60),"Out of stock more than 60 days",AC75<=60,"Out of stock less than 60 days",AC75>=150,"Out of stock more than 150 days") | AF75: =VLOOKUP(C75,'Data Products'!$A:$J,10,0) | AG75: =AF75*F75 | AH75: =IF(J75<=90,F75,0)
A76: 43 | B76: Inactive | C76: EVNMMBPY05GB20D | F76: 0 | G76: 0 | I76: =VLOOKUP(C76,'Data Products'!$A:$J,2,0) | J76: =IFERROR(I76-TODAY(),"") | K76: 45882 | L76: =TODAY()-K76 | M76: 0 | N76: 0 | Q76: Mobifone | AB76: =N76/30 | AC76: =IFERROR(F76/AB76,"-") | AD76: =IFERROR(TODAY()+AC76,"-") | AE76: =_xlfn.IFS(AC76="-","Not sold yet",AND(AC76<=150,AC76>60),"Out of stock more than 60 days",AC76<=60,"Out of stock less than 60 days",AC76>=150,"Out of stock more than 150 days") | AF76: =VLOOKUP(C76,'Data Products'!$A:$J,10,0) | AG76: =AF76*F76 | AH76: =IF(J76<=90,F76,0)
A77: 44 | B77: Active | C77: 11VNMMBZ00610 | D77: 11VNMMBZ00610 | E77: 11VNMMBZ00610 | F77: 0 | G77: 0 | I77: =VLOOKUP(C77,'Data Products'!$A:$J,2,0) | J77: =IFERROR(I77-TODAY(),"") | K77: 45883 | L77: =TODAY()-K77 | M77: 0 | N77: 0 | Q77: Mobifone | AB77: =N77/30 | AC77: =IFERROR(F77/AB77,"-") | AD77: =IFERROR(TODAY()+AC77,"-") | AE77: =_xlfn.IFS(AC77="-","Not sold yet",AND(AC77<=150,AC77>60),"Out of stock more than 60 days",AC77<=60,"Out of stock less than 60 days",AC77>=150,"Out of stock more than 150 days") | AF77: =VLOOKUP(C77,'Data Products'!$A:$J,10,0) | AG77: =AF77*F77 | AH77: =IF(J77<=90,F77,0)
A78: 45 | B78: Inactive | C78: EUSATLFX01GB07D | F78: 0 | G78: 0 | I78: =VLOOKUP(C78,'Data Products'!$A:$J,2,0) | J78: =IFERROR(I78-TODAY(),"") | K78: 45884 | L78: =TODAY()-K78 | M78: 0 | N78: 0 | Q78: Mobifone | AB78: =N78/30 | AC78: =IFERROR(F78/AB78,"-") | AD78: =IFERROR(TODAY()+AC78,"-") | AE78: =_xlfn.IFS(AC78="-","Not sold yet",AND(AC78<=150,AC78>60),"Out of stock more than 60 days",AC78<=60,"Out of stock less than 60 days",AC78>=150,"Out of stock more than 150 days") | AF78: =VLOOKUP(C78,'Data Products'!$A:$J,10,0) | AG78: =AF78*F78 | AH78: =IF(J78<=90,F78,0)
A79: 46 | B79: Inactive | C79: EUSATLFX05GB30D | F79: 0 | G79: 0 | I79: =VLOOKUP(C79,'Data Products'!$A:$J,2,0) | J79: =IFERROR(I79-TODAY(),"") | K79: 45885 | L79: =TODAY()-K79 | M79: 0 | N79: 0 | Q79: Mobifone | AB79: =N79/30 | AC79: =IFERROR(F79/AB79,"-") | AD79: =IFERROR(TODAY()+AC79,"-") | AE79: =_xlfn.IFS(AC79="-","Not sold yet",AND(AC79<=150,AC79>60),"Out of stock more than 60 days",AC79<=60,"Out of stock less than 60 days",AC79>=150,"Out of stock more than 150 days") | AF79: =VLOOKUP(C79,'Data Products'!$A:$J,10,0) | AG79: =AF79*F79 | AH79: =IF(J79<=90,F79,0)
A80: 47 | B80: Inactive | C80: EUSATLFX10GB30D | F80: 0 | G80: 0 | I80: =VLOOKUP(C80,'Data Products'!$A:$J,2,0) | J80: =IFERROR(I80-TODAY(),"") | K80: 45886 | L80: =TODAY()-K80 | M80: 0 | N80: 0 | Q80: Mobifone | AB80: =N80/30 | AC80: =IFERROR(F80/AB80,"-") | AD80: =IFERROR(TODAY()+AC80,"-") | AE80: =_xlfn.IFS(AC80="-","Not sold yet",AND(AC80<=150,AC80>60),"Out of stock more than 60 days",AC80<=60,"Out of stock less than 60 days",AC80>=150,"Out of stock more than 150 days") | AF80: =VLOOKUP(C80,'Data Products'!$A:$J,10,0) | AG80: =AF80*F80 | AH80: =IF(J80<=90,F80,0)
A81: 48 | B81: Inactive | C81: EUSATLFX20GB30D | F81: 0 | G81: 0 | I81: =VLOOKUP(C81,'Data Products'!$A:$J,2,0) | J81: =IFERROR(I81-TODAY(),"") | K81: 45887 | L81: =TODAY()-K81 | M81: 0 | N81: 0 | Q81: Mobifone | AB81: =N81/30 | AC81: =IFERROR(F81/AB81,"-") | AD81: =IFERROR(TODAY()+AC81,"-") | AE81: =_xlfn.IFS(AC81="-","Not sold yet",AND(AC81<=150,AC81>60),"Out of stock more than 60 days",AC81<=60,"Out of stock less than 60 days",AC81>=150,"Out of stock more than 150 days") | AF81: =VLOOKUP(C81,'Data Products'!$A:$J,10,0) | AG81: =AF81*F81 | AH81: =IF(J81<=90,F81,0)
A82: 49 | B82: Inactive | C82: EUSATLFX50GB30D | F82: 0 | G82: 0 | I82: =VLOOKUP(C82,'Data Products'!$A:$J,2,0) | J82: =IFERROR(I82-TODAY(),"") | K82: 45888 | L82: =TODAY()-K82 | M82: 0 | N82: 0 | Q82: Mobifone | AB82: =N82/30 | AC82: =IFERROR(F82/AB82,"-") | AD82: =IFERROR(TODAY()+AC82,"-") | AE82: =_xlfn.IFS(AC82="-","Not sold yet",AND(AC82<=150,AC82>60),"Out of stock more than 60 days",AC82<=60,"Out of stock less than 60 days",AC82>=150,"Out of stock more than 150 days") | AF82: =VLOOKUP(C82,'Data Products'!$A:$J,10,0) | AG82: =AF82*F82 | AH82: =IF(J82<=90,F82,0)
A83: 50 | B83: Inactive | C83: EE33UBPY500M01D | D83: 4CE33UBP5HM01 | E83: 4CE33UBP5HM01 | F83: 0 | G83: 0 | I83: =VLOOKUP(C83,'Data Products'!$A:$J,2,0) | J83: =IFERROR(I83-TODAY(),"") | K83: 45889 | L83: =TODAY()-K83 | M83: 0 | N83: 0 | Q83: Mobifone | AB83: =N83/30 | AC83: =IFERROR(F83/AB83,"-") | AD83: =IFERROR(TODAY()+AC83,"-") | AE83: =_xlfn.IFS(AC83="-","Not sold yet",AND(AC83<=150,AC83>60),"Out of stock more than 60 days",AC83<=60,"Out of stock less than 60 days",AC83>=150,"Out of stock more than 150 days") | AF83: =VLOOKUP(C83,'Data Products'!$A:$J,10,0) | AG83: =AF83*F83 | AH83: =IF(J83<=90,F83,0)
A84: 51 | B84: Inactive | C84: EE33UBPY500M03D | D84: 4CE33UBP5HM03 | E84: 4CE33UBP5HM03 | F84: 0 | G84: 0 | I84: =VLOOKUP(C84,'Data Products'!$A:$J,2,0) | J84: =IFERROR(I84-TODAY(),"") | K84: 45890 | L84: =TODAY()-K84 | M84: 0 | N84: 0 | Q84: Mobifone | AB84: =N84/30 | AC84: =IFERROR(F84/AB84,"-") | AD84: =IFERROR(TODAY()+AC84,"-") | AE84: =_xlfn.IFS(AC84="-","Not sold yet",AND(AC84<=150,AC84>60),"Out of stock more than 60 days",AC84<=60,"Out of stock less than 60 days",AC84>=150,"Out of stock more than 150 days") | AF84: =VLOOKUP(C84,'Data Products'!$A:$J,10,0) | AG84: =AF84*F84 | AH84: =IF(J84<=90,F84,0)
A85: 52 | B85: Inactive | C85: EE33UBPY500M05D | D85: 4CE33UBP5HM05 | E85: 4CE33UBP5HM05 | F85: 0 | G85: 0 | I85: =VLOOKUP(C85,'Data Products'!$A:$J,2,0) | J85: =IFERROR(I85-TODAY(),"") | K85: 45891 | L85: =TODAY()-K85 | M85: 0 | N85: 0 | Q85: Mobifone | AB85: =N85/30 | AC85: =IFERROR(F85/AB85,"-") | AD85: =IFERROR(TODAY()+AC85,"-") | AE85: =_xlfn.IFS(AC85="-","Not sold yet",AND(AC85<=150,AC85>60),"Out of stock more than 60 days",AC85<=60,"Out of stock less than 60 days",AC85>=150,"Out of stock more than 150 days") | AF85: =VLOOKUP(C85,'Data Products'!$A:$J,10,0) | AG85: =AF85*F85 | AH85: =IF(J85<=90,F85,0)
A86: 53 | B86: Inactive | C86: EE33UBPY500M07D | D86: 4CE33UBP5HM07 | E86: 4CE33UBP5HM07 | F86: 0 | G86: 0 | I86: =VLOOKUP(C86,'Data Products'!$A:$J,2,0) | J86: =IFERROR(I86-TODAY(),"") | K86: 45892 | L86: =TODAY()-K86 | M86: 0 | N86: 0 | Q86: Mobifone | AB86: =N86/30 | AC86: =IFERROR(F86/AB86,"-") | AD86: =IFERROR(TODAY()+AC86,"-") | AE86: =_xlfn.IFS(AC86="-","Not sold yet",AND(AC86<=150,AC86>60),"Out of stock more than 60 days",AC86<=60,"Out of stock less than 60 days",AC86>=150,"Out of stock more than 150 days") | AF86: =VLOOKUP(C86,'Data Products'!$A:$J,10,0) | AG86: =AF86*F86 | AH86: =IF(J86<=90,F86,0)
A87: 54 | B87: Inactive | C87: EE33UBPY500M10D | D87: 4CE33UBP5HM10 | E87: 4CE33UBP5HM10 | F87: 0 | G87: 0 | I87: =VLOOKUP(C87,'Data Products'!$A:$J,2,0) | J87: =IFERROR(I87-TODAY(),"") | K87: 45893 | L87: =TODAY()-K87 | M87: 0 | N87: 0 | Q87: Mobifone | AB87: =N87/30 | AC87: =IFERROR(F87/AB87,"-") | AD87: =IFERROR(TODAY()+AC87,"-") | AE87: =_xlfn.IFS(AC87="-","Not sold yet",AND(AC87<=150,AC87>60),"Out of stock more than 60 days",AC87<=60,"Out of stock less than 60 days",AC87>=150,"Out of stock more than 150 days") | AF87: =VLOOKUP(C87,'Data Products'!$A:$J,10,0) | AG87: =AF87*F87 | AH87: =IF(J87<=90,F87,0)
A88: 55 | B88: Inactive | C88: EE33UBPY500M15D | D88: 4CE33UBP5HM15 | E88: 4CE33UBP5HM15 | F88: 0 | G88: 0 | I88: =VLOOKUP(C88,'Data Products'!$A:$J,2,0) | J88: =IFERROR(I88-TODAY(),"") | K88: 45894 | L88: =TODAY()-K88 | M88: 0 | N88: 0 | Q88: Mobifone | AB88: =N88/30 | AC88: =IFERROR(F88/AB88,"-") | AD88: =IFERROR(TODAY()+AC88,"-") | AE88: =_xlfn.IFS(AC88="-","Not sold yet",AND(AC88<=150,AC88>60),"Out of stock more than 60 days",AC88<=60,"Out of stock less than 60 days",AC88>=150,"Out of stock more than 150 days") | AF88: =VLOOKUP(C88,'Data Products'!$A:$J,10,0) | AG88: =AF88*F88 | AH88: =IF(J88<=90,F88,0)
A89: 56 | B89: Inactive | C89: EE33UBPY01GB03D | D89: 4CE33UBP5HM | E89: 4CE33UBP5HM | F89: 0 | G89: 0 | I89: =VLOOKUP(C89,'Data Products'!$A:$J,2,0) | J89: =IFERROR(I89-TODAY(),"") | K89: 45895 | L89: =TODAY()-K89 | M89: 0 | N89: 0 | Q89: Mobifone | AB89: =N89/30 | AC89: =IFERROR(F89/AB89,"-") | AD89: =IFERROR(TODAY()+AC89,"-") | AE89: =_xlfn.IFS(AC89="-","Not sold yet",AND(AC89<=150,AC89>60),"Out of stock more than 60 days",AC89<=60,"Out of stock less than 60 days",AC89>=150,"Out of stock more than 150 days") | AF89: =VLOOKUP(C89,'Data Products'!$A:$J,10,0) | AG89: =AF89*F89 | AH89: =IF(J89<=90,F89,0)
A90: 57 | B90: Inactive | C90: EE33UBPY01GB05D | D90: 4CE33UBP00105 | E90: 4CE33UBP00105 | F90: 0 | G90: 0 | I90: =VLOOKUP(C90,'Data Products'!$A:$J,2,0) | J90: =IFERROR(I90-TODAY(),"") | K90: 45896 | L90: =TODAY()-K90 | M90: 0 | N90: 0 | Q90: Mobifone | AB90: =N90/30 | AC90: =IFERROR(F90/AB90,"-") | AD90: =IFERROR(TODAY()+AC90,"-") | AE90: =_xlfn.IFS(AC90="-","Not sold yet",AND(AC90<=150,AC90>60),"Out of stock more than 60 days",AC90<=60,"Out of stock less than 60 days",AC90>=150,"Out of stock more than 150 days") | AF90: =VLOOKUP(C90,'Data Products'!$A:$J,10,0) | AG90: =AF90*F90 | AH90: =IF(J90<=90,F90,0)
A91: 58 | B91: Inactive | C91: EE33UBPY01GB07D | D91: 4CE33UBP00107 | E91: 4CE33UBP00107 | F91: 0 | G91: 0 | I91: =VLOOKUP(C91,'Data Products'!$A:$J,2,0) | J91: =IFERROR(I91-TODAY(),"") | K91: 45897 | L91: =TODAY()-K91 | M91: 0 | N91: 0 | Q91: Mobifone | AB91: =N91/30 | AC91: =IFERROR(F91/AB91,"-") | AD91: =IFERROR(TODAY()+AC91,"-") | AE91: =_xlfn.IFS(AC91="-","Not sold yet",AND(AC91<=150,AC91>60),"Out of stock more than 60 days",AC91<=60,"Out of stock less than 60 days",AC91>=150,"Out of stock more than 150 days") | AF91: =VLOOKUP(C91,'Data Products'!$A:$J,10,0) | AG91: =AF91*F91 | AH91: =IF(J91<=90,F91,0)
A92: 59 | B92: Inactive | C92: EE33UBPY01GB10D | D92: 4CE33UBP00110 | E92: 4CE33UBP00110 | F92: 0 | G92: 0 | I92: =VLOOKUP(C92,'Data Products'!$A:$J,2,0) | J92: =IFERROR(I92-TODAY(),"") | K92: 45898 | L92: =TODAY()-K92 | M92: 0 | N92: 0 | Q92: Mobifone | AB92: =N92/30 | AC92: =IFERROR(F92/AB92,"-") | AD92: =IFERROR(TODAY()+AC92,"-") | AE92: =_xlfn.IFS(AC92="-","Not sold yet",AND(AC92<=150,AC92>60),"Out of stock more than 60 days",AC92<=60,"Out of stock less than 60 days",AC92>=150,"Out of stock more than 150 days") | AF92: =VLOOKUP(C92,'Data Products'!$A:$J,10,0) | AG92: =AF92*F92 | AH92: =IF(J92<=90,F92,0)
A93: 60 | B93: Inactive | C93: EE33UBPY01GB15D | D93: 4CE33UBP00115 | E93: 4CE33UBP00115 | F93: 0 | G93: 0 | I93: =VLOOKUP(C93,'Data Products'!$A:$J,2,0) | J93: =IFERROR(I93-TODAY(),"") | K93: 45899 | L93: =TODAY()-K93 | M93: 0 | N93: 0 | Q93: Mobifone | AB93: =N93/30 | AC93: =IFERROR(F93/AB93,"-") | AD93: =IFERROR(TODAY()+AC93,"-") | AE93: =_xlfn.IFS(AC93="-","Not sold yet",AND(AC93<=150,AC93>60),"Out of stock more than 60 days",AC93<=60,"Out of stock less than 60 days",AC93>=150,"Out of stock more than 150 days") | AF93: =VLOOKUP(C93,'Data Products'!$A:$J,10,0) | AG93: =AF93*F93 | AH93: =IF(J93<=90,F93,0)
A94: 61 | B94: Inactive | C94: EE33UBPY01GB20D | D94: 4CE33UBP00120 | E94: 4CE33UBP00120 | F94: 0 | G94: 0 | I94: =VLOOKUP(C94,'Data Products'!$A:$J,2,0) | J94: =IFERROR(I94-TODAY(),"") | K94: 45900 | L94: =TODAY()-K94 | M94: 0 | N94: 0 | Q94: Mobifone | AB94: =N94/30 | AC94: =IFERROR(F94/AB94,"-") | AD94: =IFERROR(TODAY()+AC94,"-") | AE94: =_xlfn.IFS(AC94="-","Not sold yet",AND(AC94<=150,AC94>60),"Out of stock more than 60 days",AC94<=60,"Out of stock less than 60 days",AC94>=150,"Out of stock more than 150 days") | AF94: =VLOOKUP(C94,'Data Products'!$A:$J,10,0) | AG94: =AF94*F94 | AH94: =IF(J94<=90,F94,0)
... A102: 69 | B102: Inactive | C102: EE33UBPY02GB30D | D102: 4CE33UBP00230 | E102: 4CE33UBP00230 | F102: 0 | G102: 0 | I102: =VLOOKUP(C102,'Data Products'!$A:$J,2,0) | J102: =IFERROR(I102-TODAY(),"") | K102: 45908 | L102: =TODAY()-K102 | M102: 0 | N102: 0 | Q102: Mobifone | AB102: =N102/30 | AC102: =IFERROR(F102/AB102,"-") | AD102: =IFERROR(TODAY()+AC102,"-") | AE102: =_xlfn.IFS(AC102="-","Not sold yet",AND(AC102<=150,AC102>60),"Out of stock more than 60 days",AC102<=60,"Out of stock less than 60 days",AC102>=150,"Out of stock more than 150 days") | AF102: =VLOOKUP(C102,'Data Products'!$A:$J,10,0) | AG102: =AF102*F102 | AH102: =IF(J102<=90,F102,0)
A103: 70 | B103: Inactive | C103: ETWNW1FY05GB10D | F103: 0 | G103: 0 | I103: =VLOOKUP(C103,'Data Products'!$A:$J,2,0) | J103: =IFERROR(I103-TODAY(),"") | K103: 45909 | L103: =TODAY()-K103 | M103: 0 | N103: 0 | Q103: Mobifone | AB103: =N103/30 | AC103: =IFERROR(F103/AB103,"-") | AD103: =IFERROR(TODAY()+AC103,"-") | AE103: =_xlfn.IFS(AC103="-","Not sold yet",AND(AC103<=150,AC103>60),"Out of stock more than 60 days",AC103<=60,"Out of stock less than 60 days",AC103>=150,"Out of stock more than 150 days") | AF103: =VLOOKUP(C103,'Data Products'!$A:$J,10,0) | AG103: =AF103*F103 | AH103: =IF(J103<=90,F103,0)
A104: 71 | B104: Inactive | C104: ETWNW1FY05GB15D | F104: 0 | G104: 0 | I104: =VLOOKUP(C104,'Data Products'!$A:$J,2,0) | J104: =IFERROR(I104-TODAY(),"") | K104: 45910 | L104: =TODAY()-K104 | M104: 0 | N104: 0 | Q104: Mobifone | AB104: =N104/30 | AC104: =IFERROR(F104/AB104,"-") | AD104: =IFERROR(TODAY()+AC104,"-") | AE104: =_xlfn.IFS(AC104="-","Not sold yet",AND(AC104<=150,AC104>60),"Out of stock more than 60 days",AC104<=60,"Out of stock less than 60 days",AC104>=150,"Out of stock more than 150 days") | AF104: =VLOOKUP(C104,'Data Products'!$A:$J,10,0) | AG104: =AF104*F104 | AH104: =IF(J104<=90,F104,0) | AI104: đã lên ticket nhờ đẩy tồn
A105: 72 | B105: Inactive | C105: ETWNW1FY10GB15D | F105: 0 | G105: 0 | I105: =VLOOKUP(C105,'Data Products'!$A:$J,2,0) | J105: =IFERROR(I105-TODAY(),"") | K105: 45911 | L105: =TODAY()-K105 | M105: 0 | N105: 0 | Q105: Mobifone | AB105: =N105/30 | AC105: =IFERROR(F105/AB105,"-") | AD105: =IFERROR(TODAY()+AC105,"-") | AE105: =_xlfn.IFS(AC105="-","Not sold yet",AND(AC105<=150,AC105>60),"Out of stock more than 60 days",AC105<=60,"Out of stock less than 60 days",AC105>=150,"Out of stock more than 150 days") | AF105: =VLOOKUP(C105,'Data Products'!$A:$J,10,0) | AG105: =AF105*F105 | AH105: =IF(J105<=90,F105,0)
A106: 45 | B106: Active | C106: ETWNW1FY20GB15D | D106: 2CTHATMF05010 | E106: 2CTHATMF05010 | F106: 0 | G106: 0 | I106: =VLOOKUP(C106,'Data Products'!$A:$J,2,0) | J106: =IFERROR(I106-TODAY(),"") | K106: 45912 | L106: =TODAY()-K106 | M106: 0 | N106: 0 | Q106: TrueMove | AB106: =N106/30 | AC106: =IFERROR(F106/AB106,"-") | AD106: =IFERROR(TODAY()+AC106,"-") | AE106: =_xlfn.IFS(AC106="-","Not sold yet",AND(AC106<=150,AC106>60),"Out of stock more than 60 days",AC106<=60,"Out of stock less than 60 days",AC106>=150,"Out of stock more than 150 days") | AF106: =VLOOKUP(C106,'Data Products'!$A:$J,10,0) | AG106: =AF106*F106
A107: 46 | B107: Active | C107: 1CCNMCUF00708 | D107: 1CCNMCUF00708 | E107: 1CCNMCUF00708 | F107: 0 | G107: 0 | I107: =VLOOKUP(C107,'Data Products'!$A:$J,2,0) | J107: =IFERROR(I107-TODAY(),"") | K107: 45913 | L107: =TODAY()-K107 | M107: 0 | N107: 0 | Q107: TrueMove | AB107: =N107/30 | AC107: =IFERROR(F107/AB107,"-") | AD107: =IFERROR(TODAY()+AC107,"-") | AE107: =_xlfn.IFS(AC107="-","Not sold yet",AND(AC107<=150,AC107>60),"Out of stock more than 60 days",AC107<=60,"Out of stock less than 60 days",AC107>=150,"Out of stock more than 150 days") | AF107: =VLOOKUP(C107,'Data Products'!$A:$J,10,0) | AG107: =AF107*F107 | AI107: không nhập thêm
A108: 47 | B108: Active | C108: 1CKORCUF01005 | D108: 1CKORCUF01005 | E108: 1CKORCUF01005 | F108: 31 | G108: 31 | I108: =VLOOKUP(C108,'Data Products'!$A:$J,2,0) | J108: =IFERROR(I108-TODAY(),"") | K108: 45914 | L108: =TODAY()-K108 | M108: 0 | N108: 0 | Q108: 4HK | AB108: =N108/30 | AC108: =IFERROR(F108/AB108,"-") | AD108: =IFERROR(TODAY()+AC108,"-") | AE108: =_xlfn.IFS(AC108="-","Not sold yet",AND(AC108<=150,AC108>60),"Out of stock more than 60 days",AC108<=60,"Out of stock less than 60 days",AC108>=150,"Out of stock more than 150 days") | AF108: =VLOOKUP(C108,'Data Products'!$A:$J,10,0) | AG108: =AF108*F108 | AI108: khuyến mãi đẩy tồn
...

Sheet 03.08
A1: SIM | B1: Status | C1: SKU (Sapo) | D1: SKU (mới) | E1: SKU (full) | F1: Total Inventory | H1: Quantity due to expiration | I1: Expiration | J1: Expired date left | K1: Date of Import | L1: Inventory Age | M1: Last 15 days | N1: Last 30 days | O1: Safety Stock (15D) | P1: Reorder Point (30D) | Q1: Vendor | R1: Kho tổng | T1: Phổ Quang - HCM | V1: Đống Đa - Hà Nội | X1: Tân Sơn Nhất - HCM | Z1: Chi nhánh Ký gửi | AB1: Avg Pcs/day | AC1: DOI (Số ngày tồn kho) | AD1: Estimated date out of stock | AE1: Evaluate | AF1: Retail Price | AG1: Total retail price | AH1: Near Expiration Inventory | AI1: OPS | AJ1: Telco | AK1: OD | AL1: WS | AM1: B2C | AN1: Marketing
A2: No. | F2: Stock | G2: Available for sale | M2: Sold | N2: Sold | R2: Stock | S2: Available for sale | T2: Stock | U2: Available for sale | V2: Stock | W2: Available for sale | X2: Stock | Y2: Available for sale | Z2: Stock | AA2: Available for sale
A3: 1 | B3: Temporary | C3: 3HKDATAPOOLSIM | D3: 3HKDATAPOOLSIM | E3: 1D0003DK00000 | F3: 419 | G3: 419 | I3: =VLOOKUP(C3,'Data Products'!$A:$B,2,0) | J3: =IFERROR(I3-TODAY(),"") | K3: 45723 | L3: =TODAY()-K3 | M3: 354 | N3: 380 | R3: 0 | S3: 0 | T3: 326 | U3: 326 | V3: 146 | W3: 146 | X3: 0 | Y3: 0 | Z3: 0 | AA3: 0 | AB3: =N3/30 | AC3: =IFERROR(F3/AB3,"-") | AD3: =IFERROR(TODAY()+AC3,"-") | AE3: =_xlfn.IFS(AC3="-","Not sold yet",AND(AC3<=150,AC3>60),"Out of stock more than 60 days",AC3<=60,"Out of stock less than 60 days",AC3>=150,"Out of stock more than 150 days") | AF3: =VLOOKUP(C3,'Data Products'!$A:$J,10,0) | AG3: =AF3*F3 | AH3: =IF(J3<=90,F3,0) | AI3: =IFERROR(VLOOKUP(C3,$C$3:$AI$42,34,0),"")
A4: 1 | B4: Active | C4: 1D0003DK00000 | D4: 1D0003DK00000 | E4: 1D0003DK00000 | F4: 20932 | G4: 20859 | I4: =VLOOKUP(C4,'Data Products'!$A:$B,2,0) | J4: =IFERROR(I4-TODAY(),"") | K4: 45617 | L4: =TODAY()-K4 | M4: 9696 | N4: 16539 | R4: 0 | S4: 0 | T4: 1378 | U4: 1369 | V4: 115 | W4: 112 | X4: 46 | Y4: 22 | Z4: 0 | AA4: 0 | AB4: =N4/30 | AC4: =IFERROR(F4/AB4,"-") | AD4: =IFERROR(TODAY()+AC4,"-") | AE4: =_xlfn.IFS(AC4="-","Not sold yet",AND(AC4<=150,AC4>60),"Out of stock more than 60 days",AC4<=60,"Out of stock less than 60 days",AC4>=150,"Out of stock more than 150 days") | AF4: =VLOOKUP(C4,'Data Products'!$A:$J,10,0) | AG4: =AF4*F4 | AH4: =IF(J4<=90,F4,0) | AI4: cần có hàng mới 20 - 25/08 để an toàn
A5: 2 | B5: Active | C5: 1D000BCK00000 | D5: 1D000BCK00000 | E5: 1D000BCK00000 | F5: 293 | G5: 292 | I5: =VLOOKUP(C5,'Data Products'!$A:$B,2,0) | J5: =IFERROR(I5-TODAY(),"") | K5: 45191 | L5: =TODAY()-K5 | M5: 17 | N5: 34 | R5: 0 | S5: 0 | T5: 26 | U5: 26 | V5: 416 | W5: 416 | X5: 0 | Y5: 0 | Z5: 0 | AA5: 0 | AB5: =N5/30 | AC5: =IFERROR(F5/AB5,"-") | AD5: =IFERROR(TODAY()+AC5,"-") | AE5: =_xlfn.IFS(AC5="-","Not sold yet",AND(AC5<=150,AC5>60),"Out of stock more than 60 days",AC5<=60,"Out of stock less than 60 days",AC5>=150,"Out of stock more than 150 days") | AF5: =VLOOKUP(C5,'Data Products'!$A:$J,10,0) | AG5: =AF5*F5 | AH5: =IF(J5<=90,F5,0) | AI5: sắp hết hạn, gia hạn thêm 1 tháng
A6: 3 | B6: Active | C6: 1D000ELK00000 | D6: 1D000ELK00000 | E6: 1D000ELK00000 | F6: 4296 | G6: 4296 | I6: =VLOOKUP(C6,'Data Products'!$A:$B,2,0) | J6: =IFERROR(I6-TODAY(),"") | K6: 45752 | L6: =TODAY()-K6 | M6: 20 | N6: 20 | R6: 0 | S6: 0 | T6: 1 | U6: 1 | V6: 1 | W6: 1 | X6: 0 | Y6: 0 | Z6: 0 | AA6: 0 | AB6: =N6/30 | AC6: =IFERROR(F6/AB6,"-") | AD6: =IFERROR(TODAY()+AC6,"-") | AE6: =_xlfn.IFS(AC6="-","Not sold yet",AND(AC6<=150,AC6>60),"Out of stock more than 60 days",AC6<=60,"Out of stock less than 60 days",AC6>=150,"Out of stock more than 150 days") | AF6: =VLOOKUP(C6,'Data Products'!$A:$J,10,0) | AG6: =AF6*F6 | AH6: =IF(J6<=90,F6,0) | AI6: =IFERROR(VLOOKUP(C6,$C$3:$AI$42,34,0),"")
A7: 4 | B7: Active | C7: 1D000JYK00000 | D7: 1D000JYK00000 | E7: 1D000JYK00000 | F7: 885 | G7: 865 | I7: =VLOOKUP(C7,'Data Products'!$A:$B,2,0) | J7: =IFERROR(I7-TODAY(),"") | K7: 45854 | L7: =TODAY()-K7 | M7: 2 | N7: 7 | R7: 0 | S7: 0 | T7: 288 | U7: 288 | V7: 512 | W7: 512 | X7: 20 | Y7: 20 | Z7: 0 | AA7: 0 | AB7: =N7/30 | AC7: =IFERROR(F7/AB7,"-") | AD7: =IFERROR(TODAY()+AC7,"-") | AE7: =_xlfn.IFS(AC7="-","Not sold yet",AND(AC7<=150,AC7>60),"Out of stock more than 60 days",AC7<=60,"Out of stock less than 60 days",AC7>=150,"Out of stock more than 150 days") | AF7: =VLOOKUP(C7,'Data Products'!$A:$J,10,0) | AG7: =AF7*F7 | AH7: =IF(J7<=90,F7,0) | AI7: =IFERROR(VLOOKUP(C7,$C$3:$AI$42,34,0),"")
A8: 5 | B8: Active | C8: 1D000SSK00000 | D8: 1D000SSK00000 | E8: 1D000SSK00000 | F8: 2472 | G8: 2471 | I8: =VLOOKUP(C8,'Data Products'!$A:$B,2,0) | J8: =IFERROR(I8-TODAY(),"") | K8: 45855 | L8: =TODAY()-K8 | M8: 7 | N8: 52 | R8: 0 | S8: 0 | T8: 51 | U8: 51 | V8: 101 | W8: 101 | X8: 0 | Y8: 0 | Z8: 0 | AA8: 0 | AB8: =N8/30 | AC8: =IFERROR(F8/AB8,"-") | AD8: =IFERROR(TODAY()+AC8,"-") | AE8: =_xlfn.IFS(AC8="-","Not sold yet",AND(AC8<=150,AC8>60),"Out of stock more than 60 days",AC8<=60,"Out of stock less than 60 days",AC8>=150,"Out of stock more than 150 days") | AF8: =VLOOKUP(C8,'Data Products'!$A:$J,10,0) | AG8: =AF8*F8 | AH8: =IF(J8<=90,F8,0) | AI8: =IFERROR(VLOOKUP(C8,$C$3:$AI$42,34,0)," ")
A9: 6 | B9: Active | C9: 1D000UBK00000 | D9: 1D000UBK00000 | E9: 1D000UBK00000 | F9: 2062 | G9: 2062 | I9: =VLOOKUP(C9,'Data Products'!$A:$B,2,0) | J9: =IFERROR(I9-TODAY(),"") | K9: 45856 | L9: =TODAY()-K9 | M9: 0 | N9: 0 | R9: 0 | S9: 0 | T9: 1480 | U9: 1478 | V9: 1112 | W9: 1112 | X9: 0 | Y9: 0 | Z9: 0 | AA9: 0 | AB9: =N9/30 | AC9: =IFERROR(F9/AB9,"-") | AD9: =IFERROR(TODAY()+AC9,"-") | AE9: =_xlfn.IFS(AC9="-","Not sold yet",AND(AC9<=150,AC9>60),"Out of stock more than 60 days",AC9<=60,"Out of stock less than 60 days",AC9>=150,"Out of stock more than 150 days") | AF9: =VLOOKUP(C9,'Data Products'!$A:$J,10,0) | AG9: =AF9*F9 | AH9: =IF(J9<=90,F9,0) | AI9: =IFERROR(VLOOKUP(C9,$C$3:$AI$42,34,0),"")
A10: 7 | B10: Active | C10: 1D000WMK00000 | D10: 1D000WMK00000 | E10: 1D000WMK00000 | F10: 518 | G10: 515 | I10: =VLOOKUP(C10,'Data Products'!$A:$B,2,0) | J10: =IFERROR(I10-TODAY(),"") | K10: 45857 | L10: =TODAY()-K10 | M10: 138 | N10: 242 | R10: 0 | S10: 0 | T10: 0 | U10: 0 | V10: 2 | W10: 2 | X10: 0 | Y10: 0 | Z10: 0 | AA10: 0 | AB10: =N10/30 | AC10: =IFERROR(F10/AB10,"-") | AD10: =IFERROR(TODAY()+AC10,"-") | AE10: =_xlfn.IFS(AC10="-","Not sold yet",AND(AC10<=150,AC10>60),"Out of stock more than 60 days",AC10<=60,"Out of stock less than 60 days",AC10>=150,"Out of stock more than 150 days") | AF10: =VLOOKUP(C10,'Data Products'!$A:$J,10,0) | AG10: =AF10*F10 | AH10: =IF(J10<=90,F10,0) | AI10: =IFERROR(VLOOKUP(C10,$C$3:$AI$42,34,0),"")
A11: 8 | B11: Temporary | C11: CNMCU05GBFY05D | D11: CNMCU05GBFY05D | E11: CNMCU05GBFY05D | F11: 1200 | G11: 1200 | I11: =VLOOKUP(C11,'Data Products'!$A:$B,2,0) | J11: =IFERROR(I11-TODAY(),"") | K11: 45858 | L11: =TODAY()-K11 | M11: 0 | N11: 0 | R11: 0 | S11: 0 | T11: 1289 | U11: 1289 | V11: 773 | W11: 773 | X11: 0 | Y11: 0 | Z11: 0 | AA11: 0 | AB11: =N11/30 | AC11: =IFERROR(F11/AB11,"-") | AD11: =IFERROR(TODAY()+AC11,"-") | AE11: =_xlfn.IFS(AC11="-","Not sold yet",AND(AC11<=150,AC11>60),"Out of stock more than 60 days",AC11<=60,"Out of stock less than 60 days",AC11>=150,"Out of stock more than 150 days") | AF11: =VLOOKUP(C11,'Data Products'!$A:$J,10,0) | AG11: =AF11*F11 | AH11: =IF(J11<=90,F11,0) | AI11: =IFERROR(VLOOKUP(C11,$C$3:$AI$42,34,0),"")
A12: 9 | B12: Temporary | C12: CNMCU07GBFY08D | D12: CNMCU07GBFY08D | E12: CNMCU07GBFY08D | F12: 1000 | G12: 1000 | I12: =VLOOKUP(C12,'Data Products'!$A:$B,2,0) | J12: =IFERROR(I12-TODAY(),"") | K12: 45532 | L12: =TODAY()-K12 | M12: 0 | N12: 0 | R12: 0 | S12: 0 | T12: 417 | U12: 416 | V12: 785 | W12: 785 | X12: 0 | Y12: 0 | Z12: 0 | AA12: 0 | AB12: =N12/30 | AC12: =IFERROR(F12/AB12,"-") | AD12: =IFERROR(TODAY()+AC12,"-") | AE12: =_xlfn.IFS(AC12="-","Not sold yet",AND(AC12<=150,AC12>60),"Out of stock more than 60 days",AC12<=60,"Out of stock less than 60 days",AC12>=150,"Out of stock more than 150 days") | AF12: =VLOOKUP(C12,'Data Products'!$A:$J,10,0) | AG12: =AF12*F12 | AH12: =IF(J12<=90,F12,0) | AI12: qua tết push lại, mỗi tuần nhắc lại
A13: 10 | B13: Temporary | C13: KORCU10GBFY05D | D13: KORCU10GBFY05D | E13: KORCU10GBFY05D | F13: 500 | G13: 500 | I13: =VLOOKUP(C13,'Data Products'!$A:$B,2,0) | J13: =IFERROR(I13-TODAY(),"") | K13: 45504 | L13: =TODAY()-K13 | M13: 0 | N13: 0 | R13: 0 | S13: 0 | T13: 3870 | U13: 1017 | V13: 366 | W13: 366 | X13: 0 | Y13: 0 | Z13: 0 | AA13: 0 | AB13: =N13/30 | AC13: =IFERROR(F13/AB13,"-") | AD13: =IFERROR(TODAY()+AC13,"-") | AE13: =_xlfn.IFS(AC13="-","Not sold yet",AND(AC13<=150,AC13>60),"Out of stock more than 60 days",AC13<=60,"Out of stock less than 60 days",AC13>=150,"Out of stock more than 150 days") | AF13: =VLOOKUP(C13,'Data Products'!$A:$J,10,0) | AG13: =AF13*F13 | AH13: =IF(J13<=90,F13,0) | AI13: =IFERROR(VLOOKUP(C13,$C$3:$AI$42,34,0),"")
A14: 11 | B14: Active | C14: 1DCNMCTF00705 | D14: 1DCNMCTF00705 | E14: 1ECNMCTF00705 | F14: 182 | G14: 182 | I14: =VLOOKUP(C14,'Data Products'!$A:$B,2,0) | J14: =IFERROR(I14-TODAY(),"") | K14: 45504 | L14: =TODAY()-K14 | M14: 0 | N14: 0 | R14: 1200 | S14: 1200 | T14: 0 | U14: 0 | V14: 0 | W14: 0 | X14: 0 | Y14: 0 | Z14: 0 | AA14: 0 | AB14: =N14/30 | AC14: =IFERROR(F14/AB14,"-") | AD14: =IFERROR(TODAY()+AC14,"-") | AE14: =_xlfn.IFS(AC14="-","Not sold yet",AND(AC14<=150,AC14>60),"Out of stock more than 60 days",AC14<=60,"Out of stock less than 60 days",AC14>=150,"Out of stock more than 150 days") | AF14: =VLOOKUP(C14,'Data Products'!$A:$J,10,0) | AG14: =AF14*F14 | AH14: =IF(J14<=90,F14,0) | AI14: =IFERROR(VLOOKUP(C14,$C$3:$AI$42,34,0)," ")
A15: 12 | B15: Active | C15: 1DCNMCUF01530 | D15: 1DCNMCUF01530 | E15: 1ECNMCUF01530 | F15: 101 | G15: 100 | I15: =VLOOKUP(C15,'Data Products'!$A:$B,2,0) | J15: =IFERROR(I15-TODAY(),"") | K15: 45648 | L15: =TODAY()-K15 | M15: 3 | N15: 6 | R15: 1000 | S15: 1000 | T15: 0 | U15: 0 | V15: 0 | W15: 0 | X15: 0 | Y15: 0 | Z15: 0 | AA15: 0 | AB15: =N15/30 | AC15: =IFERROR(F15/AB15,"-") | AD15: =IFERROR(TODAY()+AC15,"-") | AE15: =_xlfn.IFS(AC15="-","Not sold yet",AND(AC15<=150,AC15>60),"Out of stock more than 60 days",AC15<=60,"Out of stock less than 60 days",AC15>=150,"Out of stock more than 150 days") | AF15: =VLOOKUP(C15,'Data Products'!$A:$J,10,0) | AG15: =AF15*F15 | AH15: =IF(J15<=90,F15,0) | AI15: =IFERROR(VLOOKUP(C15,$C$3:$AI$42,34,0),"")
A16: 13 | B16: Active | C16: 1DCNMCUF00303 | D16: 1DCNMCUF00303 | E16: 1ECNMCUF00303 | F16: 847 | G16: 847 | I16: =VLOOKUP(C16,'Data Products'!$A:$B,2,0) | J16: =IFERROR(I16-TODAY(),"") | K16: 45504 | L16: =TODAY()-K16 | M16: 101 | N16: 102 | R16: 500 | S16: 500 | T16: 0 | U16: 0 | V16: 0 | W16: 0 | X16: 0 | Y16: 0 | Z16: 0 | AA16: 0 | AB16: =N16/30 | AC16: =IFERROR(F16/AB16,"-") | AD16: =IFERROR(TODAY()+AC16,"-") | AE16: =_xlfn.IFS(AC16="-","Not sold yet",AND(AC16<=150,AC16>60),"Out of stock more than 60 days",AC16<=60,"Out of stock less than 60 days",AC16>=150,"Out of stock more than 150 days") | AF16: =VLOOKUP(C16,'Data Products'!$A:$J,10,0) | AG16: =AF16*F16 | AH16: =IF(J16<=90,F16,0) | AI16: =IFERROR(VLOOKUP(C16,$C$3:$AI$42,34,0),"")
A17: 14 | B17: Active | C17: 1DCNMCUF00505 | D17: 1DCNMCUF00505 | E17: 1ECNMCUF00505 | F17: 0 | G17: 0 | I17: =VLOOKUP(C17,'Data Products'!$A:$B,2,0) | J17: =IFERROR(I17-TODAY(),"") | K17: 45653 | L17: =TODAY()-K17 | M17: 0 | N17: 0 | R17: 0 | S17: 0 | T17: 128 | U17: 128 | V17: 54 | W17: 54 | X17: 0 | Y17: 0 | Z17: 0 | AA17: 0 | AB17: =N17/30 | AC17: =IFERROR(F17/AB17,"-") | AD17: =IFERROR(TODAY()+AC17,"-") | AE17: =_xlfn.IFS(AC17="-","Not sold yet",AND(AC17<=150,AC17>60),"Out of stock more than 60 days",AC17<=60,"Out of stock less than 60 days",AC17>=150,"Out of stock more than 150 days") | AF17: =VLOOKUP(C17,'Data Products'!$A:$J,10,0) | AG17: =AF17*F17 | AH17: =IF(J17<=90,F17,0) | AI17: =IFERROR(VLOOKUP(C17,$C$3:$AI$42,34,0),"")
A18: 15 | B18: Active | C18: 1DTHADTF05010 | D18: 1DTHADTF05010 | E18: 1ETHADTF05010 | F18: 5 | G18: 5 | I18: =VLOOKUP(C18,'Data Products'!$A:$B,2,0) | J18: =IFERROR(I18-TODAY(),"") | K18: 45737 | L18: =TODAY()-K18 | M18: 0 | N18: 3 | R18: 0 | S18: 0 | T18: 0 | U18: 0 | V18: 116 | W18: 116 | X18: 0 | Y18: 0 | Z18: 0 | AA18: 0 | AB18: =N18/30 | AC18: =IFERROR(F18/AB18,"-") | AD18: =IFERROR(TODAY()+AC18,"-") | AE18: =_xlfn.IFS(AC18="-","Not sold yet",AND(AC18<=150,AC18>60),"Out of stock more than 60 days",AC18<=60,"Out of stock less than 60 days",AC18>=150,"Out of stock more than 150 days") | AF18: =VLOOKUP(C18,'Data Products'!$A:$J,10,0) | AG18: =AF18*F18 | AH18: =IF(J18<=90,F18,0)
A19: 16 | B19: Active | C19: 1DWORCBF01030 | D19: 1DWORCBF01030 | E19: 1DWORCBF01030 | F19: 353 | G19: 353 | I19: =VLOOKUP(C19,'Data Products'!$A:$B,2,0) | J19: =IFERROR(I19-TODAY(),"") | K19: 45653 | L19: =TODAY()-K19 | M19: 80 | N19: 84 | R19: 600 | S19: 600 | T19: 100 | U19: 100 | V19: 300 | W19: 300 | X19: 0 | Y19: 0 | Z19: 0 | AA19: 0 | AB19: =N19/30 | AC19: =IFERROR(F19/AB19,"-") | AD19: =IFERROR(TODAY()+AC19,"-") | AE19: =_xlfn.IFS(AC19="-","Not sold yet",AND(AC19<=150,AC19>60),"Out of stock more than 60 days",AC19<=60,"Out of stock less than 60 days",AC19>=150,"Out of stock more than 150 days") | AF19: =VLOOKUP(C19,'Data Products'!$A:$J,10,0) | AG19: =AF19*F19 | AH19: =IF(J19<=90,F19,0)
A20: 17 | B20: Active | C20: 1DTHATMF01507 | D20: 1DTHATMF01507 | E20: 1ETHATMF01507 | F20: 4226 | G20: 4221 | I20: =VLOOKUP(C20,'Data Products'!$A:$B,2,0) | J20: =IFERROR(I20-TODAY(),"") | K20: 45653 | L20: =TODAY()-K20 | M20: 696 | N20: 2994 | R20: 0 | S20: 0 | T20: 27 | U20: 27 | V20: 25 | W20: 25 | X20: 0 | Y20: 0 | Z20: 0 | AA20: 0 | AB20: =N20/30 | AC20: =IFERROR(F20/AB20,"-") | AD20: =IFERROR(TODAY()+AC20,"-") | AE20: =_xlfn.IFS(AC20="-","Not sold yet",AND(AC20<=150,AC20>60),"Out of stock more than 60 days",AC20<=60,"Out of stock less than 60 days",AC20>=150,"Out of stock more than 150 days") | AF20: =VLOOKUP(C20,'Data Products'!$A:$J,10,0) | AG20: =AF20*F20 | AH20: =IF(J20<=90,F20,0) | AI20: cần đầu tháng 9 có hàng mới
A21: 18 | B21: Active | C21: 1DTHATMF05010 | D21: 1DTHATMF05010 | E21: 1ETHATMF05010 | F21: 7702 | G21: 7688 | I21: =VLOOKUP(C21,'Data Products'!$A:$B,2,0) | J21: =IFERROR(I21-TODAY(),"") | K21: 45847 | L21: =TODAY()-K21 | M21: 488 | N21: 798 | R21: 0 | S21: 0 | T21: 113 | U21: 106 | V21: 1097 | W21: 1097 | X21: 5 | Y21: 0 | Z21: 0 | AA21: 0 | AB21: =N21/30 | AC21: =IFERROR(F21/AB21,"-") | AD21: =IFERROR(TODAY()+AC21,"-") | AE21: =_xlfn.IFS(AC21="-","Not sold yet",AND(AC21<=150,AC21>60),"Out of stock more than 60 days",AC21<=60,"Out of stock less than 60 days",AC21>=150,"Out of stock more than 150 days") | AF21: =VLOOKUP(C21,'Data Products'!$A:$J,10,0) | AG21: =AF21*F21 | AH21: =IF(J21<=90,F21,0) | AI21: cần đầu tháng 9 có hàng mới
A22: 19 | B22: Active | C22: 1DTHATMF01507 | D22: 1DTHATMF01507 | E22: 1ETHATMF01507 | F22: 4226 | G22: 4221 | I22: =VLOOKUP(C22,'Data Products'!$A:$B,2,0) | J22: =IFERROR(I22-TODAY(),"") | K22: 45847 | L22: =TODAY()-K22 | M22: 696 | N22: 2994 | R22: 0 | S22: 0 | T22: 154 | U22: 154 | V22: 310 | W22: 310 | X22: 0 | Y22: 0 | Z22: 0 | AA22: 0 | AB22: =N22/30 | AC22: =IFERROR(F22/AB22,"-") | AD22: =IFERROR(TODAY()+AC22,"-") | AE22: =_xlfn.IFS(AC22="-","Not sold yet",AND(AC22<=150,AC22>60),"Out of stock more than 60 days",AC22<=60,"Out of stock less than 60 days",AC22>=150,"Out of stock more than 150 days") | AF22: =VLOOKUP(C22,'Data Products'!$A:$J,10,0) | AG22: =AF22*F22 | AH22: =IF(J22<=90,F22,0) | AI22: pass quý 1 push lại
A23: 20 | B23: Temporary | C23: CNMCU15GBFY30D | D23: CNMCU15GBFY30D | E23: CNMCU15GBFY30D | F23: 1500 | G23: 1500 | I23: =VLOOKUP(C23,'Data Products'!$A:$B,2,0) | J23: =IFERROR(I23-TODAY(),"") | K23: 45416 | L23: =TODAY()-K23 | M23: 0 | N23: 0 | AB23: =N23/30 | AC23: =IFERROR(F23/AB23,"-") | AD23: =IFERROR(TODAY()+AC23,"-") | AE23: =_xlfn.IFS(AC23="-","Not sold yet",AND(AC23<=150,AC23>60),"Out of stock more than 60 days",AC23<=60,"Out of stock less than 60 days",AC23>=150,"Out of stock more than 150 days") | AF23: =VLOOKUP(C23,'Data Products'!$A:$J,10,0) | AG23: =AF23*F23
A24: 21 | B24: Temporary | C24: CNMCU10GBFY15D | D24: CNMCU10GBFY15D | E24: CNMCU10GBFY15D | F24: 2000 | G24: 2000 | I24: =VLOOKUP(C24,'Data Products'!$A:$B,2,0) | J24: =IFERROR(I24-TODAY(),"") | K24: 45417 | L24: =TODAY()-K24 | M24: 0 | N24: 0 | AB24: =N24/30 | AC24: =IFERROR(F24/AB24,"-") | AD24: =IFERROR(TODAY()+AC24,"-") | AE24: =_xlfn.IFS(AC24="-","Not sold yet",AND(AC24<=150,AC24>60),"Out of stock more than 60 days",AC24<=60,"Out of stock less than 60 days",AC24>=150,"Out of stock more than 150 days") | AF24: =VLOOKUP(C24,'Data Products'!$A:$J,10,0) | AG24: =AF24*F24
AE25: Total stock with retail price | AF25: =AG25/$AG$25 | AG25: =SUM(AG4:AG24) | AH25: =SUM(AH4:AH24) | AI25: =SUM(AI4:AI24)
AE26: Out of stock less than 60 days | AF26: =AG26/$AG$25 | AG26: =SUMIFS($AG$4:$AG$24,$AE$4:$AE$24,$AE$26)
AE27: Not sold yet | AF27: =AG27/$AG$25 | AG27: =SUMIFS($AG$4:$AG$24,$AE$4:$AE$24,AE27)
AE28: Out of stock more than 60 days | AF28: =AG28/$AG$25 | AG28: =SUMIFS($AG$4:$AG$24,$AE$4:$AE$24,AE28)
AE29: Out of stock more than 150 days | AF29: =AG29/$AG$25 | AG29: =SUMIFS($AG$4:$AG$24,$AE$4:$AE$24,AE29)
AE30: Near Expiration Inventory | AF30: =AVERAGE(AE29:AC27)/AVERAGE(AE29:AC27) | AG30: =SUMIF($AC$4:$AC$24,"<90",AG4:AG24)
A32: ESIM VN | B32: Status | C32: SKU | D32: SKU (mới) | F32: Total Inventory | H32: Quantity | I32: Expiration | J32: Expired date left | K32: Date of Import | L32: Inventory Age | M32: Last 15 days | N32: Last 30 days | O32: Safety Stock | P32: Reorder Point | Q32: Vendor | AB32: Avg Pcs/day | AC32: DOI (Số ngày tồn kho) | AD32: Ngày hết hàng dự kiến | AE32: Đánh giá | AF32: Retail Price | AG32: Total retail price | AH32: Near Expiration Inventory | AI32: OPS | AJ32: Telco | AK32: OD | AL32: B2B | AM32: B2C | AN32: Marketing
A33: No. | F33: Stock | G33: Available for sale | M33: Sold | N33: Sold
A34: 1 | B34: Inactive | C34: 3HKDATAPOOLESIM | F34: 1610 | G34: 1610 | I34: =VLOOKUP(C34,'Data Products'!$A:$J,2,0) | J34: =IFERROR(I34-TODAY(),"") | K34: 45840 | L34: =TODAY()-K34 | M34: 0 | N34: 0 | Q34: 3HK | AB34: =N34/30 | AC34: =IFERROR(F34/AB34,"-") | AD34: =IFERROR(TODAY()+AC34,"-") | AE34: =_xlfn.IFS(AC34="-","Not sold yet",AND(AC34<=150,AC34>60),"Out of stock more than 60 days",AC34<=60,"Out of stock less than 60 days",AC34>=150,"Out of stock more than 150 days") | AF34: =VLOOKUP(C34,'Data Products'!$A:$J,10,0) | AG34: =AF34*F34 | AI34: treo chờ xử lý sau
A35: 2 | B35: Inactive | C35: EEURBGFX15GB15D | F35: 0 | G35: 0 | I35: =VLOOKUP(C35,'Data Products'!$A:$J,2,0) | J35: =IFERROR(I35-TODAY(),"") | K35: 45841 | L35: =TODAY()-K35 | M35: 0 | N35: 0 | Q35: Bouygues | AB35: =N35/30 | AC35: =IFERROR(F35/AB35,"-") | AD35: =IFERROR(TODAY()+AC35,"-") | AE35: =_xlfn.IFS(AC35="-","Not sold yet",AND(AC35<=150,AC35>60),"Out of stock more than 60 days",AC35<=60,"Out of stock less than 60 days",AC35>=150,"Out of stock more than 150 days") | AF35: =VLOOKUP(C35,'Data Products'!$A:$J,10,0) | AG35: =AF35*F35 | AH35: =IF(J35<=90,F35,0)
A36: 3 | B36: Inactive | C36: EEURBGFX20GB15D | F36: 0 | G36: 0 | I36: =VLOOKUP(C36,'Data Products'!$A:$J,2,0) | J36: =IFERROR(I36-TODAY(),"") | K36: 45842 | L36: =TODAY()-K36 | M36: 0 | N36: 0 | Q36: Bouygues | AB36: =N36/30 | AC36: =IFERROR(F36/AB36,"-") | AD36: =IFERROR(TODAY()+AC36,"-") | AE36: =_xlfn.IFS(AC36="-","Not sold yet",AND(AC36<=150,AC36>60),"Out of stock more than 60 days",AC36<=60,"Out of stock less than 60 days",AC36>=150,"Out of stock more than 150 days") | AF36: =VLOOKUP(C36,'Data Products'!$A:$J,10,0) | AG36: =AF36*F36 | AH36: =IF(J36<=90,F36,0)
A37: 4 | B37: Inactive | C37: EEURBGFX30GB30D | F37: 0 | G37: 0 | I37: =VLOOKUP(C37,'Data Products'!$A:$J,2,0) | J37: =IFERROR(I37-TODAY(),"") | K37: 45843 | L37: =TODAY()-K37 | M37: 0 | N37: 0 | Q37: Bouygues | AB37: =N37/30 | AC37: =IFERROR(F37/AB37,"-") | AD37: =IFERROR(TODAY()+AC37,"-") | AE37: =_xlfn.IFS(AC37="-","Not sold yet",AND(AC37<=150,AC37>60),"Out of stock more than 60 days",AC37<=60,"Out of stock less than 60 days",AC37>=150,"Out of stock more than 150 days") | AF37: =VLOOKUP(C37,'Data Products'!$A:$J,10,0) | AG37: =AF37*F37 | AH37: =IF(J37<=90,F37,0)
A38: 5 | B38: Deleted | C38: ECMTCUFY05GB05D | F38: 0 | G38: 0 | I38: =VLOOKUP(C38,'Data Products'!$A:$J,2,0) | J38: =IFERROR(I38-TODAY(),"") | K38: 45844 | L38: =TODAY()-K38 | M38: 0 | N38: 0 | Q38: CU | AB38: =N38/30 | AC38: =IFERROR(F38/AB38,"-") | AD38: =IFERROR(TODAY()+AC38,"-") | AE38: =_xlfn.IFS(AC38="-","Not sold yet",AND(AC38<=150,AC38>60),"Out of stock more than 60 days",AC38<=60,"Out of stock less than 60 days",AC38>=150,"Out of stock more than 150 days") | AF38: =VLOOKUP(C38,'Data Products'!$A:$J,10,0) | AG38: =AF38*F38 | AH38: =IF(J38<=90,F38,0) | AK38: 200
A39: 6 | B39: Temporary | C39: ECNMCUFX15GB30D | D39: 1CCNMCUY01530 | F39: 0 | G39: 0 | I39: =VLOOKUP(C39,'Data Products'!$A:$J,2,0) | J39: =IFERROR(I39-TODAY(),"") | K39: 45845 | L39: =TODAY()-K39 | M39: 0 | N39: 0 | Q39: CU | AB39: =N39/30 | AC39: =IFERROR(F39/AB39,"-") | AD39: =IFERROR(TODAY()+AC39,"-") | AE39: =_xlfn.IFS(AC39="-","Not sold yet",AND(AC39<=150,AC39>60),"Out of stock more than 60 days",AC39<=60,"Out of stock less than 60 days",AC39>=150,"Out of stock more than 150 days") | AF39: =VLOOKUP(C39,'Data Products'!$A:$J,10,0) | AG39: =AF39*F39 | AH39: =IF(J39<=90,F39,0)
A40: 7 | B40: Temporary | C40: 1CKORCUF01005 | D40: 1CKORCUF01005 | F40: 0 | G40: 0 | I40: =VLOOKUP(C40,'Data Products'!$A:$J,2,0) | J40: =IFERROR(I40-TODAY(),"") | K40: 45846 | L40: =TODAY()-K40 | M40: 0 | N40: 0 | Q40: CU | AB40: =N40/30 | AC40: =IFERROR(F40/AB40,"-") | AD40: =IFERROR(TODAY()+AC40,"-") | AE40: =_xlfn.IFS(AC40="-","Not sold yet",AND(AC40<=150,AC40>60),"Out of stock more than 60 days",AC40<=60,"Out of stock less than 60 days",AC40>=150,"Out of stock more than 150 days") | AF40: =VLOOKUP(C40,'Data Products'!$A:$J,10,0) | AG40: =AF40*F40 | AH40: =IF(J40<=90,F40,0)
A41: 8 | B41: Temporary | C41: EKORCUFY30GB30D | F41: 0 | G41: 0 | I41: =VLOOKUP(C41,'Data Products'!$A:$J,2,0) | J41: =IFERROR(I41-TODAY(),"") | K41: 45847 | L41: =TODAY()-K41 | M41: 0 | N41: 0 | Q41: CU | AB41: =N41/30 | AC41: =IFERROR(F41/AB41,"-") | AD41: =IFERROR(TODAY()+AC41,"-") | AE41: =_xlfn.IFS(AC41="-","Not sold yet",AND(AC41<=150,AC41>60),"Out of stock more than 60 days",AC41<=60,"Out of stock less than 60 days",AC41>=150,"Out of stock more than 150 days") | AF41: =VLOOKUP(C41,'Data Products'!$A:$J,10,0) | AG41: =AF41*F41 | AH41: =IF(J41<=90,F41,0)
A42: 9 | B42: Temporary | C42: EA10CUFY05GB08D | F42: 0 | G42: 0 | I42: =VLOOKUP(C42,'Data Products'!$A:$J,2,0) | J42: =IFERROR(I42-TODAY(),"") | K42: 45848 | L42: =TODAY()-K42 | M42: 0 | N42: 0 | Q42: CU | AB42: =N42/30 | AC42: =IFERROR(F42/AB42,"-") | AD42: =IFERROR(TODAY()+AC42,"-") | AE42: =_xlfn.IFS(AC42="-","Not sold yet",AND(AC42<=150,AC42>60),"Out of stock more than 60 days",AC42<=60,"Out of stock less than 60 days",AC42>=150,"Out of stock more than 150 days") | AF42: =VLOOKUP(C42,'Data Products'!$A:$J,10,0) | AG42: =AF42*F42 | AH42: =IF(J42<=90,F42,0)
A43: 10 | B43: Temporary | C43: ECMTCUFY07GB08D | F43: 0 | G43: 0 | I43: =VLOOKUP(C43,'Data Products'!$A:$J,2,0) | J43: =IFERROR(I43-TODAY(),"") | K43: 45849 | L43: =TODAY()-K43 | M43: 0 | N43: 0 | Q43: CU | AB43: =N43/30 | AC43: =IFERROR(F43/AB43,"-") | AD43: =IFERROR(TODAY()+AC43,"-") | AE43: =_xlfn.IFS(AC43="-","Not sold yet",AND(AC43<=150,AC43>60),"Out of stock more than 60 days",AC43<=60,"Out of stock less than 60 days",AC43>=150,"Out of stock more than 150 days") | AF43: =VLOOKUP(C43,'Data Products'!$A:$J,10,0) | AG43: =AF43*F43 | AH43: =IF(J43<=90,F43,0) | AK43: 150
A44: 11 | B44: Inactive | C44: ECNMCUFY05GB05D | F44: 0 | G44: 0 | I44: =VLOOKUP(C44,'Data Products'!$A:$J,2,0) | J44: =IFERROR(I44-TODAY(),"") | K44: 45850 | L44: =TODAY()-K44 | M44: 0 | N44: 0 | Q44: CU | AB44: =N44/30 | AC44: =IFERROR(F44/AB44,"-") | AD44: =IFERROR(TODAY()+AC44,"-") | AE44: =_xlfn.IFS(AC44="-","Not sold yet",AND(AC44<=150,AC44>60),"Out of stock more than 60 days",AC44<=60,"Out of stock less than 60 days",AC44>=150,"Out of stock more than 150 days") | AF44: =VLOOKUP(C44,'Data Products'!$A:$J,10,0) | AG44: =AF44*F44 | AH44: =IF(J44<=90,F44,0)
A45: 12 | B45: Temporary | C45: ECNMCUFY07GB08D | D45: 1CCNMCUF00708 | F45: 0 | G45: 0 | I45: =VLOOKUP(C45,'Data Products'!$A:$J,2,0) | J45: =IFERROR(I45-TODAY(),"") | K45: 45851 | L45: =TODAY()-K45 | M45: 0 | N45: 0 | Q45: CU | AB45: =N45/30 | AC45: =IFERROR(F45/AB45,"-") | AD45: =IFERROR(TODAY()+AC45,"-") | AE45: =_xlfn.IFS(AC45="-","Not sold yet",AND(AC45<=150,AC45>60),"Out of stock more than 60 days",AC45<=60,"Out of stock less than 60 days",AC45>=150,"Out of stock more than 150 days") | AF45: =VLOOKUP(C45,'Data Products'!$A:$J,10,0) | AG45: =AF45*F45 | AH45: =IF(J45<=90,F45,0)
